Workbook

Sheet Bank_Cover
B2: BIN AMER REAL ESTATE SPV — Senior Debt Financing Memorandum
B3: Prepared for: Senior Lender Underwriting Committee
B4: Status: For bank review
B6: EXECUTIVE SUMMARY
B7: Bin Amer Holding seeks senior secured financing for the acquisition of a stabilised income real-estate asset in the Kingdom of Saudi Arabia. The proposed structure is 50% LTV / 50% sponsor equity, 10-year tenor, amortising on a 25-year profile with a balloon at maturity (or refinanced at Y5 / Y7). Sources & Uses tie at closing including funded reserve stack (DSRA, OpEx, CapEx, contingency). The base-case underwriting clears DSCR, LLCR, debt-yield and LTV covenants. The Downside scenario maintains DSCR above 1.20x and remains NPV-positive at Project level.
B9: DEAL TERMS (proposed)
B10: ="Senior debt amount: " & TEXT(Assumptions!$D$47,"#,##0")&" SAR"
B11: ="LTV / LTC: " & TEXT(Assumptions!$D$47/Assumptions!$D$11,"0.0%")&" / "&TEXT(Assumptions!$D$47/Sources_Uses!$C$15,"0.0%")
B12: ="Cost of debt: " & TEXT(Assumptions!$D$42,"0.00%")&" (SAIBOR + 175bps blended)"
B13: ="Tenor: " & TEXT(Assumptions!$D$45,"0")&" years"
B14: ="Amortisation: " & IF(Assumptions!$D$44=1,"Yes (25-yr profile, balloon at maturity)","Bullet at maturity — refinance commitment required")
B15: ="DSRA: " & TEXT(Assumptions!$D$89,"0")&" months of debt service"
B16: ="Min DSCR covenant: " & TEXT(Assumptions!$D$73,"0.00\x")
B17: ="Cash sweep: " & "Trigger: DSCR < 1.45x ; sweep 100% excess CF to debt"
B18: ="LLCR test: " & "≥ 1.40x annually"
B19: ="Recourse: " & "Limited to completion + 24-mo debt service guarantee"
B20: ="Reporting: " & "Quarterly compliance certificate + audited financials"
B23: KEY RISKS AND MITIGANTS
B24: • Refinancing risk at maturity — Sponsor pre-arrangement of refinance; LLCR ≥ 1.40x; conservative exit cap.
B25: • Cap-rate expansion at exit — Stress test at +150bps cap (8.5% → 10%); remains positive in Severe.
B26: • Interest-rate exposure — Rate-cap hedge required on ≥ 50% of debt for first 5 years.
B27: • Concentration / single-asset — Cross-collateralisation with sponsor's broader portfolio.
B28: • Tenant credit / lease roll — Lease roll schedule (Asset_Profile sheet); weighted average lease term.
B29: • Saudi tax regime (Zakat, WHT) — Big-4 opinion at closing; 70% property shelter applied.
B30: • Operational underperformance — Operating reserve (3mo OpEx); cap-ex reserve (12mo CapEx).
B31: • Sponsor liquidity — Sponsor recourse for first 24 months DS; clean balance-sheet test.
B34: MODEL SECTIONS REFERENCED
B35: → Sources_Uses — closing day capital stack tie-out
B36: → Bank_Underwrite — single-page credit memo & DSCR/LLCR/DY trajectory
... B43: → Audit — model integrity checks (must be all OK or REVIEW)

Sheet Bank_Underwrite
B2: BANK UNDERWRITING SUMMARY — Bin Amer Real Estate SPV
B3: Single-page credit memo for senior lender review.
B5: DEAL SUMMARY
B6: Sponsor | C6: =Assumptions!$D$120
B7: Borrower (SPV) | C7: =Assumptions!$D$121
B8: Asset class | C8: =Assumptions!$D$122
B9: Geography | C9: =Assumptions!$D$123
B10: Acquisition price (SAR) | C10: =Assumptions!$D$11
B11: Total project cost (SAR) | C11: =Assumptions!$D$16
B12: Senior debt (SAR) | C12: =Assumptions!$D$47
B13: Sponsor equity (SAR) | C13: =Assumptions!$D$48
B14: Holding period | C14: =Assumptions!$D$7
B15: Closing year | C15: =Assumptions!$D$6
B16: Exit year | C16: =Assumptions!$D$8
B19: TRAJECTORY (operating years Y1–Y10)
B20: Metric | C20: Y1 | D20: Y2 | E20: Y3 | F20: Y4 | G20: Y5 | H20: Y6 | I20: Y7 | J20: Y8 | K20: Y9 | L20: Y10
B21: NOI (SAR M) | C21: =OpEx_CapEx!E9/1000000 | D21: =OpEx_CapEx!F9/1000000 | E21: =OpEx_CapEx!G9/1000000 | F21: =OpEx_CapEx!H9/1000000 | G21: =OpEx_CapEx!I9/1000000 | H21: =OpEx_CapEx!J9/1000000 | I21: =OpEx_CapEx!K9/1000000 | J21: =OpEx_CapEx!L9/1000000 | ... L21: =OpEx_CapEx!N9/1000000
B22: CFADS (SAR M) | C22: =Lender_Metrics!E6/1000000 | D22: =Lender_Metrics!F6/1000000 | E22: =Lender_Metrics!G6/1000000 | F22: =Lender_Metrics!H6/1000000 | G22: =Lender_Metrics!I6/1000000 | H22: =Lender_Metrics!J6/1000000 | I22: =Lender_Metrics!K6/1000000 | J22: =Lender_Metrics!L6/1000000 | ... L22: =Lender_Metrics!N6/1000000
B23: Debt service (SAR M) | C23: =Lender_Metrics!E7/1000000 | D23: =Lender_Metrics!F7/1000000 | E23: =Lender_Metrics!G7/1000000 | F23: =Lender_Metrics!H7/1000000 | G23: =Lender_Metrics!I7/1000000 | H23: =Lender_Metrics!J7/1000000 | I23: =Lender_Metrics!K7/1000000 | J23: =Lender_Metrics!L7/1000000 | ... L23: =Lender_Metrics!N7/1000000
B24: DSCR (x) | C24: =Lender_Metrics!E8 | D24: =Lender_Metrics!F8 | E24: =Lender_Metrics!G8 | F24: =Lender_Metrics!H8 | G24: =Lender_Metrics!I8 | H24: =Lender_Metrics!J8 | I24: =Lender_Metrics!K8 | J24: =Lender_Metrics!L8 | ... L24: =Lender_Metrics!N8
B25: Debt outstanding (SAR M) | C25: =Debt!E9/1000000 | D25: =Debt!F9/1000000 | E25: =Debt!G9/1000000 | F25: =Debt!H9/1000000 | G25: =Debt!I9/1000000 | H25: =Debt!J9/1000000 | I25: =Debt!K9/1000000 | J25: =Debt!L9/1000000 | ... L25: =Debt!N9/1000000
B26: LTV (vs market value at Y_t) | C26: =IFERROR(Debt!E9/(OpEx_CapEx!E9/(Assumptions!$D$51+0.01)),0) | D26: =IFERROR(Debt!F9/(OpEx_CapEx!F9/(Assumptions!$D$51+0.01)),0) | E26: =IFERROR(Debt!G9/(OpEx_CapEx!G9/(Assumptions!$D$51+0.01)),0) | F26: =IFERROR(Debt!H9/(OpEx_CapEx!H9/(Assumptions!$D$51+0.01)),0) | G26: =IFERROR(Debt!I9/(OpEx_CapEx!I9/(Assumptions!$D$51+0.01)),0) | H26: =IFERROR(Debt!J9/(OpEx_CapEx!J9/(Assumptions!$D$51+0.01)),0) | I26: =IFERROR(Debt!K9/(OpEx_CapEx!K9/(Assumptions!$D$51+0.01)),0) | J26: =IFERROR(Debt!L9/(OpEx_CapEx!L9/(Assumptions!$D$51+0.01)),0) | ... L26: =IFERROR(Debt!N9/(OpEx_CapEx!N9/(Assumptions!$D$51+0.01)),0)
B27: Debt yield (NOI / Debt) | C27: =Lender_Metrics!E13 | D27: =Lender_Metrics!F13 | E27: =Lender_Metrics!G13 | F27: =Lender_Metrics!H13 | G27: =Lender_Metrics!I13 | H27: =Lender_Metrics!J13 | I27: =Lender_Metrics!K13 | J27: =Lender_Metrics!L13 | ... L27: =Lender_Metrics!N13
B28: LLCR (x) | C28: =IFERROR(Lender_Metrics!E10,0) | D28: =IFERROR(Lender_Metrics!F10,0) | E28: =IFERROR(Lender_Metrics!G10,0) | F28: =IFERROR(Lender_Metrics!H10,0) | G28: =IFERROR(Lender_Metrics!I10,0) | H28: =IFERROR(Lender_Metrics!J10,0) | I28: =IFERROR(Lender_Metrics!K10,0) | J28: =IFERROR(Lender_Metrics!L10,0) | ... L28: =IFERROR(Lender_Metrics!N10,0)
B29: PLCR (x) | C29: =IFERROR(Lender_Metrics!E11,0) | D29: =IFERROR(Lender_Metrics!F11,0) | E29: =IFERROR(Lender_Metrics!G11,0) | F29: =IFERROR(Lender_Metrics!H11,0) | G29: =IFERROR(Lender_Metrics!I11,0) | H29: =IFERROR(Lender_Metrics!J11,0) | I29: =IFERROR(Lender_Metrics!K11,0) | J29: =IFERROR(Lender_Metrics!L11,0) | ... L29: =IFERROR(Lender_Metrics!N11,0)
B30: Break-even occupancy | C30: =IFERROR(Lender_Metrics!E14,0) | D30: =IFERROR(Lender_Metrics!F14,0) | E30: =IFERROR(Lender_Metrics!G14,0) | F30: =IFERROR(Lender_Metrics!H14,0) | G30: =IFERROR(Lender_Metrics!I14,0) | H30: =IFERROR(Lender_Metrics!J14,0) | I30: =IFERROR(Lender_Metrics!K14,0) | J30: =IFERROR(Lender_Metrics!L14,0) | ... L30: =IFERROR(Lender_Metrics!N14,0)
B33: HEADLINE CREDIT METRICS
B34: Metric | C34: Value | D34: Threshold
B35: Min DSCR (excl. bullet year) | C35: =Lender_Metrics!$D$20 | D35: ≥ 1.35x
B36: Avg DSCR (excl. bullet year) | C36: =Lender_Metrics!$D$19
B37: Min LLCR | C37: =Lender_Metrics!$D$21 | D37: ≥ 1.40x
B38: Min debt yield | C38: =Lender_Metrics!$D$22 | D38: ≥ Assumptions!$D$75
B39: Max break-even occupancy | C39: =Lender_Metrics!$D$23
B40: Initial LTV | C40: =Assumptions!$D$47/Assumptions!$D$11 | D40: ≤ Assumptions!$D$74
B41: Initial LTC | C41: =Assumptions!$D$47/Sources_Uses!$C$15 | D41: ≤ 65%
B42: Bankability score | C42: =Lender_Metrics!$D$24
B45: LENDER RECOMMENDATION
B46: =IF(AND(Lender_Metrics!$D$20>=Assumptions!$D$73,Lender_Metrics!$D$21>=1.4,Assumptions!$D$47/Assumptions!$D$11<=Assumptions!$D$74,Audit!$D$36=0),"APPROVE — meets all bank gates",IF(Lender_Metrics!$D$24="BANKABLE","CONDITIONAL APPROVAL — see term sheet conditions","REJECT — covenant breaches, restructure required"))

Sheet IC_Memo
B2: INVESTMENT COMMITTEE MEMO — Bin Amer Holding Investment Underwriting v5
B3: Date: as of issuance | Reviewer: Independent Institutional Underwriting
B5: 1. EXECUTIVE RECOMMENDATION
B6: REJECT (deal as-presented) — RESTRUCTURE REQUIRED to reach institutional bankability.
B7: The proposed transaction does not clear any of the four institutional gates: Project IRR < WACC (5.11% vs 8.50%); Equity IRR < hurdle (0.31% vs 10%); NPV negative at both project and equity levels (-SAR 47M / -SAR 61M); MOIC 1.03x vs 1.75x target. Six of sixteen audit checks fail. Deal is not financeable as structured.
B9: 2. KEY RED FLAGS
B10: (a) Negative spread between project IRR and WACC of -339 bps: the asset is being acquired ABOVE its risk-adjusted intrinsic value. Either renegotiate price or improve operations — the cap-rate gap cannot be closed by leverage alone.
B11: (b) Negative spread between equity IRR and hurdle of -969 bps: equity is destroying value vs the 10% hurdle. After zakat and WHT, equity returns approach zero. Levered IRR < unlevered IRR is a structural sign of overpriced debt or excessive non-deductible taxes.
B12: (c) Bullet repayment at maturity creates exit-year DSCR of 0.13x with no refinance plan modelled. This is unbankable: lenders will not underwrite a non-amortizing structure without a binding take-out.
B13: (d) Zakat charge in v4 is SAR 2.69M flat every year (2.5% × initial equity), absorbing ~22% of EBITDA. Under KSA practice the Zakat base for a property-holding SPV is largely sheltered by net book value; v5 applies an 80% shelter haircut (subject to Big-4 confirmation), which materially improves equity IRR.
B14: (e) Exit cap of 7.50% vs entry cap of 6.77% bakes in 75 bps of cap expansion over 10 years — plausible but compounds with low income growth (1.5% effective). The deal relies on terminal value: removing the exit value drops NPV by SAR 87M.
B15: (f) No reserve accounts (DSRA, OpEx, CapEx, contingency) — first cash shortfall or capex surprise forces an equity call.
... B54: All assumptions require third-party validation: market valuer, Big-4 tax (Zakat & WHT), legal counsel (KSA RETT, structure), and lender term sheet before financing close.

Sheet Dashboard
B2: EXECUTIVE DASHBOARD — Bin Amer Holding Investment Committee
B4: CREDIT METRICS
B5: Closing year (Y0) | D5: =Assumptions!$D$6
B6: Exit year (Y_exit) | D6: =Assumptions!$D$8
B7: Holding period | D7: =Assumptions!$D$7
B8: Asset purchase price | D8: =Assumptions!$D$11
B9: Total project cost | D9: =Assumptions!$D$16
B10: Equity required | D10: =Assumptions!$D$48
B11: Debt required | D11: =Assumptions!$D$47
B12: Initial LTV | D12: =Assumptions!$D$47/Assumptions!$D$16
B14: RETURN METRICS
B15: Project IRR (unlevered) | D15: =Returns!D5
B16: Equity IRR (levered, post-tax) | D16: =Returns!D6
B17: WACC | D17: =Assumptions!$D$68
B18: Hurdle rate | D18: =Assumptions!$D$71
B19: NPV @ WACC (Project) | D19: =DCF!D17
B20: NPV @ Ke (Equity) | D20: =DCF!D25
B21: MOIC | D21: =Returns!D17
B22: Payback period | D22: =Returns!D19
B23: Cash-on-Cash (Y1) | D23: =Returns!D22
B24: Yield on cost (Y1) | D24: =Returns!D23
B26: CREDIT METRICS
B27: Min DSCR over life | D27: =Returns!D28
B28: Avg DSCR | D28: =Returns!D29
B29: Avg Debt Yield | D29: =Returns!D30
B30: Min Interest Coverage | D30: =Returns!D31
B31: Min DSCR threshold | D31: =Assumptions!$D$73
B32: Initial LTV vs Max LTV | D32: =Returns!D27 & " / " & TEXT(Assumptions!$D$74,"0.0%")
B34: AUDIT STATUS
B35: Number of audit checks passed | D35: =COUNTIF(Audit!E6:E25,"OK")
B36: Number of audit checks failed | D36: =COUNTIF(Audit!E6:E25,"ERROR")
B37: Checks requiring review | D37: =COUNTIF(Audit!E6:E25,"REVIEW")
B39: INVESTMENT COMMITTEE RECOMMENDATION
B40: Decision logic: Equity IRR ≥ Hurdle, NPV(Project) > 0, Min DSCR ≥ threshold, LTV ≤ Max, Audit clean
B41: RECOMMENDATION | D41: =IF(AND(Returns!D6>=Assumptions!$D$71,DCF!D17>0,Audit!E14="OK",Audit!E18="OK"),"PROCEED (base case meets all gates)",IF(D54="PASS","CONDITIONAL — Adopt Restructured Deal Terms (see Restructured_Deal sheet)","REJECT — Base case fails; Restructured Deal does not meet thresholds"))
B43: KEY DEAL DRIVERS (interpret with caution)
B44: • Outcome is most sensitive to: exit cap rate, Y1 vacancy, OpEx, cost of debt.
B45: • DSCR collapses at exit year if bullet repayment + interest exceed NOI — check Debt!N16.
B46: • Zakat & withholding tax reduce equity IRR by ~30–80 bps depending on structure.
B47: • Forward NOI used in exit value reflects 1-period escalation — verify with broker comps.
B48: • All shareholding, governance, and tax-residency assumptions require Big-4 / counsel sign-off.
B49: RESTRUCTURED DEAL SNAPSHOT (institutional view)
B50: Restructured Equity IRR | D50: =Restructured_Deal!D59
B51: Restructured MOIC | D51: =Restructured_Deal!D58
B52: Restructured Y1 DSCR (incl. amort) | D52: =Restructured_Deal!D20
B53: Restructured Project NPV @ WACC | D53: =Restructured_Deal!D62
B54: Restructured PASS (IRR & NPV) | D54: =IF(AND(Restructured_Deal!D61="PASS",Restructured_Deal!D63="POSITIVE"),"PASS","FAIL")

Sheet Sources_Uses
B2: SOURCES & USES OF FUNDS — closing day (Y0)
B3: All values in SAR. Tie-out must net to zero (sources = uses).
B5: USES | C5: SAR | D5: % of cost
B6: Asset purchase price | C6: =Assumptions!$D$11 | D6: =C6/$C$15
B7: RETT (Real Estate Transaction Tax) | C7: =Assumptions!$D$11*Assumptions!$D$12 | D7: =C7/$C$15
B8: Acquisition broker / agency | C8: =Assumptions!$D$11*Assumptions!$D$13 | D8: =C8/$C$15
B9: Acquisition / DD / legal fees | C9: =Assumptions!$D$11*Assumptions!$D$14 | D9: =C9/$C$15
B10: Debt arrangement fee | C10: =-Debt!$D$11 | D10: =C10/$C$15
B11: DSRA funded at closing | C11: =Reserves!$D$7 | D11: =C11/$C$15
B12: Operating reserve funded at closing | C12: =Reserves!$D$10 | D12: =C12/$C$15
B13: CapEx reserve funded at closing | C13: =Reserves!$D$12 | D13: =C13/$C$15
B14: Contingency reserve funded at closing | C14: =Reserves!$D$13 | D14: =C14/$C$15
B15: TOTAL USES | C15: =SUM(C6:C14)
B18: SOURCES | C18: SAR | D18: % of total
B19: Senior debt — initial draw | C19: =Assumptions!$D$47 | D19: =C19/$C$21
B20: Sponsor equity | C20: =C15-C19 | D20: =C20/$C$21
B21: TOTAL SOURCES | C21: =SUM(C19:C20)
B23: Sources − Uses (must equal 0) | C23: =C21-C15 | D23: =IF(ABS(C23)<10,"BALANCED","REVIEW")
B26: CAPITAL STACK SUMMARY
B27: Loan-to-Value (LTV) | C27: =Assumptions!$D$47/Assumptions!$D$11
B28: Loan-to-Cost (LTC) | C28: =Assumptions!$D$47/C15
B29: Senior debt / Equity (D/E) | C29: =Assumptions!$D$47/(C15-Assumptions!$D$47)
B30: Implied entry yield (Y1 NOI / price) | C30: =OpEx_CapEx!$E$9/Assumptions!$D$11
B31: Day-1 debt yield (Y1 NOI / debt) | C31: =OpEx_CapEx!$E$9/Assumptions!$D$47

Sheet Stress_Summary
B2: STRESS TEST SUMMARY — Bank format
B3: 5 scenarios. Base case must clear all 4 gates. Severe/Stress define downside protection.
B5: Metric | C5: Base | D5: Downside | E5: Severe | F5: Stress | G5: Upside
B6: NPV @ WACC (Project, SAR M) | C6: =Scenario_Engine!C17/1000000 | D6: =Scenario_Engine!D17/1000000 | E6: =Scenario_Engine!E17/1000000 | F6: =Scenario_Engine!F17/1000000 | G6: =Scenario_Engine!G17/1000000
B7: Equity IRR | C7: =Scenario_Engine!C18 | D7: =Scenario_Engine!D18 | E7: =Scenario_Engine!E18 | F7: =Scenario_Engine!F18 | G7: =Scenario_Engine!G18
B8: Equity MOIC | C8: =Scenario_Engine!C19 | D8: =Scenario_Engine!D19 | E8: =Scenario_Engine!E19 | F8: =Scenario_Engine!F19 | G8: =Scenario_Engine!G19
B9: Y1 DSCR | C9: =Scenario_Engine!C20 | D9: =Scenario_Engine!D20 | E9: =Scenario_Engine!E20 | F9: =Scenario_Engine!F20 | G9: =Scenario_Engine!G20
B10: Exit value (SAR M) | C10: =Scenario_Engine!C21/1000000 | D10: =Scenario_Engine!D21/1000000 | E10: =Scenario_Engine!E21/1000000 | F10: =Scenario_Engine!F21/1000000 | G10: =Scenario_Engine!G21/1000000
B11: Investment verdict | C11: =Scenario_Engine!C22 | D11: =Scenario_Engine!D22 | E11: =Scenario_Engine!E22 | F11: =Scenario_Engine!F22 | G11: =Scenario_Engine!G22
B14: BANK GATES (must clear in Base AND Downside)
B15: Gate | C15: Base | D15: Downside | E15: Pass?
B16: Y1 DSCR ≥ 1.35x | C16: =Stress_Summary!C9 | D16: =Stress_Summary!D9 | E16: =IF(AND(C16>=1.35,D16>=1.35),"PASS","FAIL")
B17: NPV @ WACC ≥ 0 | C17: =Stress_Summary!C6 | D17: =Stress_Summary!D6 | E17: =IF(AND(C17>=0,D17>=0),"PASS","FAIL")
B18: Equity IRR ≥ 12% | C18: =Stress_Summary!C7 | D18: =Stress_Summary!D7 | E18: =IF(AND(C18>=0.12,D18>=0.12),"PASS","FAIL")
B19: Verdict ≠ REJECT | C19: =Stress_Summary!C11 | D19: =Stress_Summary!D11 | E19: =IF(AND(C19<>"REJECT",D19<>"REJECT"),"PASS","FAIL")
B22: OVERALL STRESS TEST OUTCOME
B23: Number of gates passed (of 4) | C23: =COUNTIF(E16:E19,"PASS")
B24: Recommendation | C24: =IF(C23=4,"APPROVE",IF(C23>=2,"CONDITIONAL — Restructure","REJECT"))

Sheet Covenant_Test
B2: COVENANT COMPLIANCE — annual + cushion test
B3: Test bank covenants every year. Cushion = (actual − threshold). Negative cushion = breach. Cash sweep above 1.45x.
B5: Covenant | C5: Y1 | D5: Y2 | E5: Y3 | F5: Y4 | G5: Y5 | H5: Y6 | I5: Y7 | J5: Y8 | K5: Y9 | L5: Y10
B6: DSCR (CFADS / DS) | C6: =Lender_Metrics!E8 | D6: =Lender_Metrics!F8 | E6: =Lender_Metrics!G8 | F6: =Lender_Metrics!H8 | G6: =Lender_Metrics!I8 | H6: =Lender_Metrics!J8 | I6: =Lender_Metrics!K8 | J6: =Lender_Metrics!L8 | ... L6: =Lender_Metrics!N8
B7: DSCR cushion vs 1.35x | C7: =IFERROR(C6-Assumptions!$D$73,0) | D7: =IFERROR(D6-Assumptions!$D$73,0) | E7: =IFERROR(E6-Assumptions!$D$73,0) | F7: =IFERROR(F6-Assumptions!$D$73,0) | G7: =IFERROR(G6-Assumptions!$D$73,0) | H7: =IFERROR(H6-Assumptions!$D$73,0) | I7: =IFERROR(I6-Assumptions!$D$73,0) | J7: =IFERROR(J6-Assumptions!$D$73,0) | ... L7: =IFERROR(L6-Assumptions!$D$73,0)
B8: DSCR compliance | C8: =IF(C6>=Assumptions!$D$73,"PASS","BREACH") | D8: =IF(D6>=Assumptions!$D$73,"PASS","BREACH") | E8: =IF(E6>=Assumptions!$D$73,"PASS","BREACH") | F8: =IF(F6>=Assumptions!$D$73,"PASS","BREACH") | G8: =IF(G6>=Assumptions!$D$73,"PASS","BREACH") | H8: =IF(H6>=Assumptions!$D$73,"PASS","BREACH") | I8: =IF(I6>=Assumptions!$D$73,"PASS","BREACH") | J8: =IF(J6>=Assumptions!$D$73,"PASS","BREACH") | ... L8: =IF(L6>=Assumptions!$D$73,"PASS","BREACH")
B9: Cash sweep trigger (DSCR < 1.45x) | C9: =IF(C6<1.45,"SWEEP","FREE CASH") | D9: =IF(D6<1.45,"SWEEP","FREE CASH") | E9: =IF(E6<1.45,"SWEEP","FREE CASH") | F9: =IF(F6<1.45,"SWEEP","FREE CASH") | G9: =IF(G6<1.45,"SWEEP","FREE CASH") | H9: =IF(H6<1.45,"SWEEP","FREE CASH") | I9: =IF(I6<1.45,"SWEEP","FREE CASH") | J9: =IF(J6<1.45,"SWEEP","FREE CASH") | ... L9: =IF(L6<1.45,"SWEEP","FREE CASH")
B11: LLCR (PV CFADS / Debt) | C11: =IFERROR(Lender_Metrics!E10,0) | D11: =IFERROR(Lender_Metrics!F10,0) | E11: =IFERROR(Lender_Metrics!G10,0) | F11: =IFERROR(Lender_Metrics!H10,0) | G11: =IFERROR(Lender_Metrics!I10,0) | H11: =IFERROR(Lender_Metrics!J10,0) | I11: =IFERROR(Lender_Metrics!K10,0) | J11: =IFERROR(Lender_Metrics!L10,0) | ... L11: =IFERROR(Lender_Metrics!N10,0)
B12: LLCR compliance (≥ 1.40x) | C12: =IF(C11>=1.4,"PASS","BREACH") | D12: =IF(D11>=1.4,"PASS","BREACH") | E12: =IF(E11>=1.4,"PASS","BREACH") | F12: =IF(F11>=1.4,"PASS","BREACH") | G12: =IF(G11>=1.4,"PASS","BREACH") | H12: =IF(H11>=1.4,"PASS","BREACH") | I12: =IF(I11>=1.4,"PASS","BREACH") | J12: =IF(J11>=1.4,"PASS","BREACH") | ... L12: =IF(L11>=1.4,"PASS","BREACH")
B14: Debt yield (NOI / Debt) | C14: =IFERROR(Lender_Metrics!E13,0) | D14: =IFERROR(Lender_Metrics!F13,0) | E14: =IFERROR(Lender_Metrics!G13,0) | F14: =IFERROR(Lender_Metrics!H13,0) | G14: =IFERROR(Lender_Metrics!I13,0) | H14: =IFERROR(Lender_Metrics!J13,0) | I14: =IFERROR(Lender_Metrics!K13,0) | J14: =IFERROR(Lender_Metrics!L13,0) | ... L14: =IFERROR(Lender_Metrics!N13,0)
B15: DY compliance (≥ 10%) | C15: =IF(C14>=Assumptions!$D$75,"PASS","BREACH") | D15: =IF(D14>=Assumptions!$D$75,"PASS","BREACH") | E15: =IF(E14>=Assumptions!$D$75,"PASS","BREACH") | F15: =IF(F14>=Assumptions!$D$75,"PASS","BREACH") | G15: =IF(G14>=Assumptions!$D$75,"PASS","BREACH") | H15: =IF(H14>=Assumptions!$D$75,"PASS","BREACH") | I15: =IF(I14>=Assumptions!$D$75,"PASS","BREACH") | J15: =IF(J14>=Assumptions!$D$75,"PASS","BREACH") | ... L15: =IF(L14>=Assumptions!$D$75,"PASS","BREACH")
B17: LTV (Debt / implied market value) | C17: =IFERROR(Debt!E9/(OpEx_CapEx!E9/Assumptions!$D$51),0) | D17: =IFERROR(Debt!F9/(OpEx_CapEx!F9/Assumptions!$D$51),0) | E17: =IFERROR(Debt!G9/(OpEx_CapEx!G9/Assumptions!$D$51),0) | F17: =IFERROR(Debt!H9/(OpEx_CapEx!H9/Assumptions!$D$51),0) | G17: =IFERROR(Debt!I9/(OpEx_CapEx!I9/Assumptions!$D$51),0) | H17: =IFERROR(Debt!J9/(OpEx_CapEx!J9/Assumptions!$D$51),0) | I17: =IFERROR(Debt!K9/(OpEx_CapEx!K9/Assumptions!$D$51),0) | J17: =IFERROR(Debt!L9/(OpEx_CapEx!L9/Assumptions!$D$51),0) | ... L17: =IFERROR(Debt!N9/(OpEx_CapEx!N9/Assumptions!$D$51),0)
B18: LTV compliance (≤ 60%) | C18: =IF(C17<=0.60,"PASS","BREACH") | D18: =IF(D17<=0.60,"PASS","BREACH") | E18: =IF(E17<=0.60,"PASS","BREACH") | F18: =IF(F17<=0.60,"PASS","BREACH") | G18: =IF(G17<=0.60,"PASS","BREACH") | H18: =IF(H17<=0.60,"PASS","BREACH") | I18: =IF(I17<=0.60,"PASS","BREACH") | J18: =IF(J17<=0.60,"PASS","BREACH") | ... L18: =IF(L17<=0.60,"PASS","BREACH")
B20: COMPLIANCE SUMMARY
B21: Total breaches over hold | C21: =COUNTIF(C8:L8,"BREACH")+COUNTIF(C12:L12,"BREACH")+COUNTIF(C15:L15,"BREACH")+COUNTIF(C18:L18,"BREACH")
B22: Quarters in cash sweep | C22: =COUNTIF(C9:L9,"SWEEP")
B23: Verdict | C23: =IF(C21=0,"FULL COMPLIANCE",IF(C21<=2,"MARGINAL — ACCEPTABLE","NON-COMPLIANT"))

Sheet Assumptions
B2: ASSUMPTIONS — Bank-Ready (v5.1 Conservative)
B3: Blue = input. Yellow fill = high-impact assumption. All cells outside the input column should be empty or formula-driven.
B5: 1. PROJECT TIMELINE
B6: Investment closing year (Y0) | D6: 2025 | E6: year | F6: Capital deployed at start of this year
B7: Holding period (operating years) | D7: 10 | E7: yrs | F7: Y1..Y_hold years of operation
B8: Exit calendar year | D8: =Assumptions!$D$6+Assumptions!$D$7 | E8: year | F8: Calculated
B10: 2. PROJECT COST & ACQUISITION
B11: Asset purchase price | D11: 170000000 | E11: SAR | F11: Pre-fee asset price
B12: RETT (Real Estate Transaction Tax) | D12: 0.05 | E12: % | F12: Saudi RETT — confirm current rate
B13: Acquisition broker / agency | D13: 0.025 | E13: % | F13: % of purchase price
B14: Acquisition / DD / legal fee | D14: 0.0025 | E14: % | F14: Advisory + legal
B15: Sum of acquisition costs (%) | D15: =Assumptions!$D$12+Assumptions!$D$13+Assumptions!$D$14 | E15: % | F15: Calculated
B16: Total project cost (incl. fees) | D16: =Assumptions!$D$11*(1+Assumptions!$D$15) | E16: SAR | F16: Calculated
B18: 3. REVENUE
B19: Year 1 gross revenue (stabilised) | D19: 14280000 | E19: SAR | F19: First full operating year revenue
B20: Revenue growth rate (annualised) | D20: 0.025 | E20: % | F20: Effective annual growth
B21: Escalation frequency | D21: 1 | E21: yrs | F21: 1 = annual; 2 = biennial; etc.
B22: Vacancy / collection loss | D22: 0.08 | E22: % | F22: % of gross revenue lost; v3 used 0% — institutional minimum 3-5%
B24: 4. OPERATING EXPENSES (asset level)
B25: OpEx (% of EGI) | D25: 0.08 | E25: % | F25: True asset operating costs — maintenance, utilities, insurance, sec.
B26: Property / municipal tax | D26: 0 | E26: % | F26: % of EGI — adjust to local regime
B27: OpEx inflation | D27: 0.025 | E27: % | F27: Annual cost inflation
B29: 5. CORPORATE / FUND COSTS (below NOI)
B30: Asset management fee (% NAV) | D30: 0.003 | E30: % | F30: 0 if self-managed; NAV-based
B31: Custodian fee (% NAV) | D31: 0.0004 | E31: % | F31: Third-party custody
B32: Fund admin fee (% NAV) | D32: 0.0005 | E32: % | F32: Accounting/admin
B33: Other fixed annual expenses | D33: 285000 | E33: SAR | F33: Audit, legal, board
B35: 6. CAPITAL EXPENDITURE
B36: Maintenance CapEx (% of EGI) | D36: 0.02 | E36: % | F36: Institutional norm 1-2% for stabilized assets — v3 used 0%
B37: Major refurbishment amount | D37: 3000000 | E37: SAR | F37: Cyclical major refurb (one-off)
B38: Refurbishment year (Yn) | D38: 5 | E38: Yn | F38: Year of major refurb
B40: 7. FINANCING / DEBT
B41: Debt ratio (% of total cost) | D41: 0.5 | E41: % | F41: Set 0% for all-equity
B42: Cost of debt (annual) | D42: 0.075 | E42: % | F42: All-in rate
B43: Debt arrangement fee (one-off) | D43: 0.0025 | E43: % | F43: % of debt; paid Y0
B44: Amortization (1=AMORT, 0=BULLET) | D44: 0 | E44: flag | F44: 1 = amortizing over tenor; 0 = bullet at exit
B45: Debt tenor (years) | D45: 10 | E45: yrs | F45: Amortization tenor
B46: Grace period (years, interest-only) | D46: 1 | E46: yrs | F46: Interest-only years
B47: Debt amount | D47: =Assumptions!$D$16*Assumptions!$D$41 | E47: SAR | F47: Calculated
B48: Equity required | D48: =Assumptions!$D$16*(1-Assumptions!$D$41) | E48: SAR | F48: Calculated
B50: 8. EXIT / DISPOSAL
B51: Exit cap rate | D51: 0.085 | E51: % | F51: Higher = lower exit price
B52: Exit broker commission | D52: 0.025 | E52: % | F52: % of sale price
B53: Exit legal / advisory | D53: 0.0075 | E53: % | F53: % of sale price
B54: Other disposal costs | D54: 0.0025 | E54: % | F54: % of sale price
B56: 9. TAX (Saudi regime)
B57: Zakat (% on equity-base) | D57: 0.025 | E57: % | F57: 2.5% on adjusted zakat base — confirm structure
B58: Corporate tax (foreign-owned share) | D58: 0 | E58: % | F58: 20% for non-Saudi shareholders; set 0 if 100% Saudi-owned
B59: Withholding tax on distributions | D59: 0.05 | E59: % | F59: 5% WHT on dividends to non-residents (treaty may reduce)
B60: Tax on capital gain at exit | D60: 0 | E60: % | F60: KSA: 0% for resident corporates; 20% for non-resident WHT may apply
B62: 10. DISCOUNT RATE / WACC
B63: Risk-free rate (KSA 10Y sovereign) | D63: 0.05 | E63: % | F63: Sovereign benchmark
B64: Market risk premium | D64: 0.05 | E64: % | F64: 4-7% range typical
B65: Beta (levered) | D65: 1 | E65: x | F65: 1 = market
B66: Cost of equity (Ke) | D66: =Assumptions!$D$63+Assumptions!$D$65*Assumptions!$D$64 | E66: % | F66: CAPM
B67: After-tax cost of debt | D67: =Assumptions!$D$42*(1-Assumptions!$D$58) | E67: % | F67: Kd*(1-t)
B68: WACC | D68: =Assumptions!$D$66*(1-Assumptions!$D$41)+Assumptions!$D$67*Assumptions!$D$41 | E68: % | F68: Calculated
B70: 11. RISK / HURDLES
B71: Hurdle rate (min IRR) | D71: 0.12 | E71: % | F71: Equity IRR floor — v3 used 8% which equals WACC (too low)
B72: MOIC target | D72: 1.6 | E72: x | F72: Equity multiple floor for 10-yr hold
B73: Minimum DSCR (per year) | D73: 1.35 | E73: x | F73: Bank covenant
B74: Maximum LTV | D74: 0.55 | E74: % | F74: Bank LTV ceiling
B75: Minimum debt yield (NOI/Debt) | D75: 0.1 | E75: % | F75: Bank debt yield floor
B76: Zakat base haircut (% of property absorbed) | D76: 0.7 | E76: % | F76: Property book value sheltering zakat base; KSA norm 70–90%
B77: Effective Zakat base (calculated) | D77: =MAX(0,Assumptions!$D$48*(1-Assumptions!$D$76)) | E77: SAR | F77: Equity less property shelter
B78: 12. REFINANCING
B79: Refinance switch (1=ON, 0=OFF) | D79: 1 | E79: flag | F79: Models a single refi during hold period
B80: Refinance year (Yn) | D80: 5 | E80: Yn | F80: Year in which existing debt is replaced
B81: Refinanced LTV (% of property value at refi) | D81: 0.55 | E81: % | F81: Bank refi LTV; institutional ceiling 55–60%
B82: Refinanced cost of debt | D82: 0.085 | E82: % | F82: Forward curve assumption; v4 was 7%
B83: Refinanced tenor (years from refi) | D83: 5 | E83: yrs | F83: Remaining life to exit
B84: Refinanced amortization (1=AMORT, 0=BULLET) | D84: 1 | E84: flag | F84: Post-refi amortization preferred
B85: Refinance fee (% of new debt) | D85: 0.0075 | E85: % | F85: Bank arrangement + legal
B86: Property value at refi (per appraisal proxy) | D86: =OpEx_CapEx!I9/Assumptions!$D$51 | E86: SAR | F86: Cap-rate valuation of Y(refi) NOI
B88: 13. INSTITUTIONAL RESERVES
B89: DSRA — Debt Service Reserve (months of DS) | D89: 9 | E89: mths | F89: Bank covenant typical 6 months
B90: Operating reserve (months of OpEx) | D90: 3 | E90: mths | F90: Working-capital buffer
B91: CapEx reserve (months of CapEx run-rate) | D91: 12 | E91: mths | F91: Forward-funded CapEx pool
B92: Contingency reserve (% of total cost) | D92: 0.015 | E92: % | F92: Unallocated
B93: Min cash on balance sheet (SAR) | D93: 3000000 | E93: SAR | F93: Hard floor
B95: 14. STRESS / SCENARIO SHOCK INPUTS
B96: Scenario_Engine reads from these; do not edit the engine itself.
B97: Driver | C97: Base | D97: Downside | E97: Severe | F97: Stress | G97: Upside
B98: Revenue growth shock (Δpp) | C98: 0 | D98: -0.01 | E98: -0.02 | F98: -0.03 | G98: 0.01
B99: Vacancy shock (Δpp added to base) | C99: 0 | D99: 0.05 | E99: 0.1 | F99: 0.2 | G99: -0.02
B100: OpEx multiplier (× base) | C100: 1 | D100: 1.1 | E100: 1.2 | F100: 1.35 | G100: 0.95
B101: Exit cap shock (Δbps) | C101: 0 | D101: 50 | E101: 150 | F101: 250 | G101: -25
B102: Cost-of-debt shock (Δbps) | C102: 0 | D102: 100 | E102: 200 | F102: 350 | G102: -25
B103: Refi failure flag (1=fail) | C103: 0 | D103: 0 | E103: 0 | F103: 1 | G103: 0
B104: Delayed stabilisation (years) | C104: 0 | D104: 1 | E104: 2 | F104: 3 | G104: 0
B105: Construction / acquisition overrun (% cost) | C105: 0 | D105: 0.02 | E105: 0.05 | F105: 0.1 | G105: 0
B107: ACTIVE SCENARIO (1=Base 2=Down 3=Severe 4=Stress 5=Up) | D107: 1 | E107: switch | F107: Drives Scenario_Engine outputs; does NOT alter base model.
B109: 15. RESTRUCTURED-DEAL ALTERNATIVE (institutional target)
B110: Target acquisition price (negotiated) | D110: 145000000 | E110: SAR | F110: Renegotiated lower entry basis
B111: Target Year-1 NOI uplift (% above base) | D111: 0.05 | E111: % | F111: From repositioning, lease-up, OpEx cuts
B112: Target LTV | D112: 0.55 | E112: % | F112: Disciplined leverage
B113: Target cost of debt | D113: 0.075 | E113: % | F113: Sized to current SAIBOR + spread
B114: Target amortization (1=yes) | D114: 1 | E114: flag | F114: Mandatory amortizing structure
B115: Target exit cap (conservative) | D115: 0.08 | E115: % | F115: Reflects 5y forward + risk premium
B116: Target equity IRR floor | D116: 0.12 | E116: % | F116: Institutional minimum given risk
...

Sheet Timeline
B2: TIMELINE & PERIOD FLAGS
B3: Period | D3: 0 | E3: 1 | F3: 2 | G3: 3 | H3: 4 | I3: 5 | J3: 6 | K3: 7 | L3: 8 | M3: 9 | N3: 10
B4: Year | D4: =Assumptions!$D$6+0 | E4: =Assumptions!$D$6+1 | F4: =Assumptions!$D$6+2 | G4: =Assumptions!$D$6+3 | H4: =Assumptions!$D$6+4 | I4: =Assumptions!$D$6+5 | J4: =Assumptions!$D$6+6 | K4: =Assumptions!$D$6+7 | L4: =Assumptions!$D$6+8 | M4: =Assumptions!$D$6+9 | N4: =Assumptions!$D$6+10
B5: Operating year flag | D5: 0 | E5: =IF(1<=Assumptions!$D$7,1,0) | F5: =IF(2<=Assumptions!$D$7,1,0) | G5: =IF(3<=Assumptions!$D$7,1,0) | H5: =IF(4<=Assumptions!$D$7,1,0) | I5: =IF(5<=Assumptions!$D$7,1,0) | J5: =IF(6<=Assumptions!$D$7,1,0) | K5: =IF(7<=Assumptions!$D$7,1,0) | L5: =IF(8<=Assumptions!$D$7,1,0) | M5: =IF(9<=Assumptions!$D$7,1,0) | N5: =IF(10<=Assumptions!$D$7,1,0)
B6: Exit year flag | D6: =IF(0=Assumptions!$D$7,1,0) | E6: =IF(1=Assumptions!$D$7,1,0) | F6: =IF(2=Assumptions!$D$7,1,0) | G6: =IF(3=Assumptions!$D$7,1,0) | H6: =IF(4=Assumptions!$D$7,1,0) | I6: =IF(5=Assumptions!$D$7,1,0) | J6: =IF(6=Assumptions!$D$7,1,0) | K6: =IF(7=Assumptions!$D$7,1,0) | L6: =IF(8=Assumptions!$D$7,1,0) | M6: =IF(9=Assumptions!$D$7,1,0) | N6: =IF(10=Assumptions!$D$7,1,0)
B7: Escalation step flag (0/1) | D7: 0 | E7: 0 | F7: =IF(Assumptions!$D$21=0,0,IF(MOD(2-1,Assumptions!$D$21)=0,1,0)) | G7: =IF(Assumptions!$D$21=0,0,IF(MOD(3-1,Assumptions!$D$21)=0,1,0)) | H7: =IF(Assumptions!$D$21=0,0,IF(MOD(4-1,Assumptions!$D$21)=0,1,0)) | I7: =IF(Assumptions!$D$21=0,0,IF(MOD(5-1,Assumptions!$D$21)=0,1,0)) | J7: =IF(Assumptions!$D$21=0,0,IF(MOD(6-1,Assumptions!$D$21)=0,1,0)) | K7: =IF(Assumptions!$D$21=0,0,IF(MOD(7-1,Assumptions!$D$21)=0,1,0)) | L7: =IF(Assumptions!$D$21=0,0,IF(MOD(8-1,Assumptions!$D$21)=0,1,0)) | M7: =IF(Assumptions!$D$21=0,0,IF(MOD(9-1,Assumptions!$D$21)=0,1,0)) | N7: =IF(Assumptions!$D$21=0,0,IF(MOD(10-1,Assumptions!$D$21)=0,1,0))
B8: Cumulative escalation factor | D8: 1 | E8: 1 | F8: =E8*(1+F7*Assumptions!$D$20) | G8: =F8*(1+G7*Assumptions!$D$20) | H8: =G8*(1+H7*Assumptions!$D$20) | I8: =H8*(1+I7*Assumptions!$D$20) | J8: =I8*(1+J7*Assumptions!$D$20) | K8: =J8*(1+K7*Assumptions!$D$20) | L8: =K8*(1+L7*Assumptions!$D$20) | M8: =L8*(1+M7*Assumptions!$D$20) | N8: =M8*(1+N7*Assumptions!$D$20)
B9: OpEx inflation factor | D9: 1 | E9: 1 | F9: =E9*(1+Assumptions!$D$27) | G9: =F9*(1+Assumptions!$D$27) | H9: =G9*(1+Assumptions!$D$27) | I9: =H9*(1+Assumptions!$D$27) | J9: =I9*(1+Assumptions!$D$27) | K9: =J9*(1+Assumptions!$D$27) | L9: =K9*(1+Assumptions!$D$27) | M9: =L9*(1+Assumptions!$D$27) | N9: =M9*(1+Assumptions!$D$27)

Sheet Revenue
B2: REVENUE BUILD
B3: Period | D3: 0 | E3: 1 | F3: 2 | G3: 3 | H3: 4 | I3: 5 | J3: 6 | K3: 7 | L3: 8 | M3: 9 | N3: 10
B4: Year | D4: =Assumptions!$D$6+0 | E4: =Assumptions!$D$6+1 | F4: =Assumptions!$D$6+2 | G4: =Assumptions!$D$6+3 | H4: =Assumptions!$D$6+4 | I4: =Assumptions!$D$6+5 | J4: =Assumptions!$D$6+6 | K4: =Assumptions!$D$6+7 | L4: =Assumptions!$D$6+8 | M4: =Assumptions!$D$6+9 | N4: =Assumptions!$D$6+10
B5: Gross potential revenue | D5: =Assumptions!$D$19*Timeline!D8*Timeline!D5 | E5: =Assumptions!$D$19*Timeline!E8*Timeline!E5 | F5: =Assumptions!$D$19*Timeline!F8*Timeline!F5 | G5: =Assumptions!$D$19*Timeline!G8*Timeline!G5 | H5: =Assumptions!$D$19*Timeline!H8*Timeline!H5 | I5: =Assumptions!$D$19*Timeline!I8*Timeline!I5 | J5: =Assumptions!$D$19*Timeline!J8*Timeline!J5 | K5: =Assumptions!$D$19*Timeline!K8*Timeline!K5 | ... N5: =Assumptions!$D$19*Timeline!N8*Timeline!N5
B6: Vacancy / collection loss | D6: =-D5*Assumptions!$D$22 | E6: =-E5*Assumptions!$D$22 | F6: =-F5*Assumptions!$D$22 | G6: =-G5*Assumptions!$D$22 | H6: =-H5*Assumptions!$D$22 | I6: =-I5*Assumptions!$D$22 | J6: =-J5*Assumptions!$D$22 | K6: =-K5*Assumptions!$D$22 | ... N6: =-N5*Assumptions!$D$22
B7: EFFECTIVE GROSS INCOME (EGI) | D7: =D5+D6 | E7: =E5+E6 | F7: =F5+F6 | G7: =G5+G6 | H7: =H5+H6 | I7: =I5+I6 | J7: =J5+J6 | K7: =K5+K6 | ... N7: =N5+N6
B8: YoY EGI growth | E8: =IFERROR(IF(D7=0,0,E7/D7-1),0) | F8: =IFERROR(IF(E7=0,0,F7/E7-1),0) | G8: =IFERROR(IF(F7=0,0,G7/F7-1),0) | H8: =IFERROR(IF(G7=0,0,H7/G7-1),0) | I8: =IFERROR(IF(H7=0,0,I7/H7-1),0) | J8: =IFERROR(IF(I7=0,0,J7/I7-1),0) | K8: =IFERROR(IF(J7=0,0,K7/J7-1),0) | L8: =IFERROR(IF(K7=0,0,L7/K7-1),0) | ... N8: =IFERROR(IF(M7=0,0,N7/M7-1),0)

Sheet OpEx_CapEx
B2: OPERATING EXPENSES & CAPITAL EXPENDITURE
B3: Period | D3: 0 | E3: 1 | F3: 2 | G3: 3 | H3: 4 | I3: 5 | J3: 6 | K3: 7 | L3: 8 | M3: 9 | N3: 10
B4: Year | D4: =Assumptions!$D$6+0 | E4: =Assumptions!$D$6+1 | F4: =Assumptions!$D$6+2 | G4: =Assumptions!$D$6+3 | H4: =Assumptions!$D$6+4 | I4: =Assumptions!$D$6+5 | J4: =Assumptions!$D$6+6 | K4: =Assumptions!$D$6+7 | L4: =Assumptions!$D$6+8 | M4: =Assumptions!$D$6+9 | N4: =Assumptions!$D$6+10
B5: ASSET-LEVEL OPERATING EXPENSES
B6: Operating expenses (OpEx) | D6: =-Revenue!D7*Assumptions!$D$25*Timeline!D9/Timeline!E9 | E6: =-Revenue!E7*Assumptions!$D$25*Timeline!E9/Timeline!E9 | F6: =-Revenue!F7*Assumptions!$D$25*Timeline!F9/Timeline!E9 | G6: =-Revenue!G7*Assumptions!$D$25*Timeline!G9/Timeline!E9 | H6: =-Revenue!H7*Assumptions!$D$25*Timeline!H9/Timeline!E9 | I6: =-Revenue!I7*Assumptions!$D$25*Timeline!I9/Timeline!E9 | J6: =-Revenue!J7*Assumptions!$D$25*Timeline!J9/Timeline!E9 | K6: =-Revenue!K7*Assumptions!$D$25*Timeline!K9/Timeline!E9 | L6: =-Revenue!L7*Assumptions!$D$25*Timeline!L9/Timeline!E9 | M6: =-Revenue!M7*Assumptions!$D$25*Timeline!M9/Timeline!E9 | N6: =-Revenue!N7*Assumptions!$D$25*Timeline!N9/Timeline!E9
B7: Property / municipal tax | D7: =-Revenue!D7*Assumptions!$D$26 | E7: =-Revenue!E7*Assumptions!$D$26 | F7: =-Revenue!F7*Assumptions!$D$26 | G7: =-Revenue!G7*Assumptions!$D$26 | H7: =-Revenue!H7*Assumptions!$D$26 | I7: =-Revenue!I7*Assumptions!$D$26 | J7: =-Revenue!J7*Assumptions!$D$26 | K7: =-Revenue!K7*Assumptions!$D$26 | ... N7: =-Revenue!N7*Assumptions!$D$26
B8: TOTAL ASSET OPERATING EXPENSES | D8: =D6+D7 | E8: =E6+E7 | F8: =F6+F7 | G8: =G6+G7 | H8: =H6+H7 | I8: =I6+I7 | J8: =J6+J7 | K8: =K6+K7 | ... N8: =N6+N7
B9: NET OPERATING INCOME (NOI) | D9: =Revenue!D7+D8 | E9: =Revenue!E7+E8 | F9: =Revenue!F7+F8 | G9: =Revenue!G7+G8 | H9: =Revenue!H7+H8 | I9: =Revenue!I7+I8 | J9: =Revenue!J7+J8 | K9: =Revenue!K7+K8 | ... N9: =Revenue!N7+N8
B10: NOI margin | D10: =IFERROR(IF(Revenue!D7=0,0,D9/Revenue!D7),0) | E10: =IFERROR(IF(Revenue!E7=0,0,E9/Revenue!E7),0) | F10: =IFERROR(IF(Revenue!F7=0,0,F9/Revenue!F7),0) | G10: =IFERROR(IF(Revenue!G7=0,0,G9/Revenue!G7),0) | H10: =IFERROR(IF(Revenue!H7=0,0,H9/Revenue!H7),0) | I10: =IFERROR(IF(Revenue!I7=0,0,I9/Revenue!I7),0) | J10: =IFERROR(IF(Revenue!J7=0,0,J9/Revenue!J7),0) | K10: =IFERROR(IF(Revenue!K7=0,0,K9/Revenue!K7),0) | ... N10: =IFERROR(IF(Revenue!N7=0,0,N9/Revenue!N7),0)
B12: CORPORATE / FUND-LEVEL COSTS (below NOI)
B13: Management fee (% NAV proxy: total cost) | D13: =-Assumptions!$D$16*Assumptions!$D$30*Timeline!D5 | E13: =-Assumptions!$D$16*Assumptions!$D$30*Timeline!E5 | F13: =-Assumptions!$D$16*Assumptions!$D$30*Timeline!F5 | G13: =-Assumptions!$D$16*Assumptions!$D$30*Timeline!G5 | H13: =-Assumptions!$D$16*Assumptions!$D$30*Timeline!H5 | I13: =-Assumptions!$D$16*Assumptions!$D$30*Timeline!I5 | J13: =-Assumptions!$D$16*Assumptions!$D$30*Timeline!J5 | K13: =-Assumptions!$D$16*Assumptions!$D$30*Timeline!K5 | ... N13: =-Assumptions!$D$16*Assumptions!$D$30*Timeline!N5
B14: Custodian fee | D14: =-Assumptions!$D$16*Assumptions!$D$31*Timeline!D5 | E14: =-Assumptions!$D$16*Assumptions!$D$31*Timeline!E5 | F14: =-Assumptions!$D$16*Assumptions!$D$31*Timeline!F5 | G14: =-Assumptions!$D$16*Assumptions!$D$31*Timeline!G5 | H14: =-Assumptions!$D$16*Assumptions!$D$31*Timeline!H5 | I14: =-Assumptions!$D$16*Assumptions!$D$31*Timeline!I5 | J14: =-Assumptions!$D$16*Assumptions!$D$31*Timeline!J5 | K14: =-Assumptions!$D$16*Assumptions!$D$31*Timeline!K5 | ... N14: =-Assumptions!$D$16*Assumptions!$D$31*Timeline!N5
B15: Fund admin fee | D15: =-Assumptions!$D$16*Assumptions!$D$32*Timeline!D5 | E15: =-Assumptions!$D$16*Assumptions!$D$32*Timeline!E5 | F15: =-Assumptions!$D$16*Assumptions!$D$32*Timeline!F5 | G15: =-Assumptions!$D$16*Assumptions!$D$32*Timeline!G5 | H15: =-Assumptions!$D$16*Assumptions!$D$32*Timeline!H5 | I15: =-Assumptions!$D$16*Assumptions!$D$32*Timeline!I5 | J15: =-Assumptions!$D$16*Assumptions!$D$32*Timeline!J5 | K15: =-Assumptions!$D$16*Assumptions!$D$32*Timeline!K5 | ... N15: =-Assumptions!$D$16*Assumptions!$D$32*Timeline!N5
B16: Other fixed annual expenses | D16: =-Assumptions!$D$33*Timeline!D9*Timeline!D5 | E16: =-Assumptions!$D$33*Timeline!E9*Timeline!E5 | F16: =-Assumptions!$D$33*Timeline!F9*Timeline!F5 | G16: =-Assumptions!$D$33*Timeline!G9*Timeline!G5 | H16: =-Assumptions!$D$33*Timeline!H9*Timeline!H5 | I16: =-Assumptions!$D$33*Timeline!I9*Timeline!I5 | J16: =-Assumptions!$D$33*Timeline!J9*Timeline!J5 | K16: =-Assumptions!$D$33*Timeline!K9*Timeline!K5 | ... N16: =-Assumptions!$D$33*Timeline!N9*Timeline!N5
B17: TOTAL CORPORATE COSTS | D17: =SUM(D13:D16) | E17: =SUM(E13:E16) | F17: =SUM(F13:F16) | G17: =SUM(G13:G16) | H17: =SUM(H13:H16) | I17: =SUM(I13:I16) | J17: =SUM(J13:J16) | K17: =SUM(K13:K16) | ... N17: =SUM(N13:N16)
B18: EBITDA (NOI − Corporate costs) | D18: =D9+D17 | E18: =E9+E17 | F18: =F9+F17 | G18: =G9+G17 | H18: =H9+H17 | I18: =I9+I17 | J18: =J9+J17 | K18: =K9+K17 | ... N18: =N9+N17
B20: CAPITAL EXPENDITURE
B21: Maintenance CapEx (% EGI) | D21: =-Revenue!D7*Assumptions!$D$36 | E21: =-Revenue!E7*Assumptions!$D$36 | F21: =-Revenue!F7*Assumptions!$D$36 | G21: =-Revenue!G7*Assumptions!$D$36 | H21: =-Revenue!H7*Assumptions!$D$36 | I21: =-Revenue!I7*Assumptions!$D$36 | J21: =-Revenue!J7*Assumptions!$D$36 | K21: =-Revenue!K7*Assumptions!$D$36 | ... N21: =-Revenue!N7*Assumptions!$D$36
B22: Major refurbishment | D22: =IF(0=Assumptions!$D$38,-Assumptions!$D$37,0) | E22: =IF(1=Assumptions!$D$38,-Assumptions!$D$37,0) | F22: =IF(2=Assumptions!$D$38,-Assumptions!$D$37,0) | G22: =IF(3=Assumptions!$D$38,-Assumptions!$D$37,0) | H22: =IF(4=Assumptions!$D$38,-Assumptions!$D$37,0) | I22: =IF(5=Assumptions!$D$38,-Assumptions!$D$37,0) | J22: =IF(6=Assumptions!$D$38,-Assumptions!$D$37,0) | K22: =IF(7=Assumptions!$D$38,-Assumptions!$D$37,0) | L22: =IF(8=Assumptions!$D$38,-Assumptions!$D$37,0) | M22: =IF(9=Assumptions!$D$38,-Assumptions!$D$37,0) | N22: =IF(10=Assumptions!$D$38,-Assumptions!$D$37,0)
B23: TOTAL CAPEX | D23: =D21+D22 | E23: =E21+E22 | F23: =F21+F22 | G23: =G21+G22 | H23: =H21+H22 | I23: =I21+I22 | J23: =J21+J22 | K23: =K21+K22 | ... N23: =N21+N22

Sheet Debt
B2: DEBT SCHEDULE
B3: Period | D3: 0 | E3: 1 | F3: 2 | G3: 3 | H3: 4 | I3: 5 | J3: 6 | K3: 7 | L3: 8 | M3: 9 | N3: 10
B4: Year | D4: =Assumptions!$D$6+0 | E4: =Assumptions!$D$6+1 | F4: =Assumptions!$D$6+2 | G4: =Assumptions!$D$6+3 | H4: =Assumptions!$D$6+4 | I4: =Assumptions!$D$6+5 | J4: =Assumptions!$D$6+6 | K4: =Assumptions!$D$6+7 | L4: =Assumptions!$D$6+8 | M4: =Assumptions!$D$6+9 | N4: =Assumptions!$D$6+10
B5: Opening balance | D5: 0 | E5: =D9 | F5: =E9 | G5: =F9 | H5: =G9 | I5: =H9 | J5: =I9 | K5: =J9 | L5: =K9 | ... N5: =M9
B6: Drawdown | D6: =Assumptions!$D$47 | E6: 0 | F6: 0 | G6: 0 | H6: 0 | I6: 0 | J6: 0 | K6: 0 | L6: 0 | M6: 0 | N6: 0
B7: Scheduled principal repayment | D7: 0 | E7: =-IF(AND(Assumptions!$D$44=1,1>Assumptions!$D$46,1<Assumptions!$D$7,Assumptions!$D$45-Assumptions!$D$46>0),Assumptions!$D$47/(Assumptions!$D$45-Assumptions!$D$46),0) | F7: =-IF(AND(Assumptions!$D$44=1,2>Assumptions!$D$46,2<Assumptions!$D$7,Assumptions!$D$45-Assumptions!$D$46>0),Assumptions!$D$47/(Assumptions!$D$45-Assumptions!$D$46),0) | G7: =-IF(AND(Assumptions!$D$44=1,3>Assumptions!$D$46,3<Assumptions!$D$7,Assumptions!$D$45-Assumptions!$D$46>0),Assumptions!$D$47/(Assumptions!$D$45-Assumptions!$D$46),0) | H7: =-IF(AND(Assumptions!$D$44=1,4>Assumptions!$D$46,4<Assumptions!$D$7,Assumptions!$D$45-Assumptions!$D$46>0),Assumptions!$D$47/(Assumptions!$D$45-Assumptions!$D$46),0) | I7: =-IF(AND(Assumptions!$D$44=1,5>Assumptions!$D$46,5<Assumptions!$D$7,Assumptions!$D$45-Assumptions!$D$46>0),Assumptions!$D$47/(Assumptions!$D$45-Assumptions!$D$46),0) | J7: =-IF(AND(Assumptions!$D$44=1,6>Assumptions!$D$46,6<Assumptions!$D$7,Assumptions!$D$45-Assumptions!$D$46>0),Assumptions!$D$47/(Assumptions!$D$45-Assumptions!$D$46),0) | K7: =-IF(AND(Assumptions!$D$44=1,7>Assumptions!$D$46,7<Assumptions!$D$7,Assumptions!$D$45-Assumptions!$D$46>0),Assumptions!$D$47/(Assumptions!$D$45-Assumptions!$D$46),0) | L7: =-IF(AND(Assumptions!$D$44=1,8>Assumptions!$D$46,8<Assumptions!$D$7,Assumptions!$D$45-Assumptions!$D$46>0),Assumptions!$D$47/(Assumptions!$D$45-Assumptions!$D$46),0) | M7: =-IF(AND(Assumptions!$D$44=1,9>Assumptions!$D$46,9<Assumptions!$D$7,Assumptions!$D$45-Assumptions!$D$46>0),Assumptions!$D$47/(Assumptions!$D$45-Assumptions!$D$46),0) | N7: =-IF(AND(Assumptions!$D$44=1,10>Assumptions!$D$46,10<Assumptions!$D$7,Assumptions!$D$45-Assumptions!$D$46>0),Assumptions!$D$47/(Assumptions!$D$45-Assumptions!$D$46),0)
B8: Bullet repayment at exit | D8: 0 | E8: =-IF(1=Assumptions!$D$7,E5+E6+E7,0) | F8: =-IF(2=Assumptions!$D$7,F5+F6+F7,0) | G8: =-IF(3=Assumptions!$D$7,G5+G6+G7,0) | H8: =-IF(4=Assumptions!$D$7,H5+H6+H7,0) | I8: =-IF(5=Assumptions!$D$7,I5+I6+I7,0) | J8: =-IF(6=Assumptions!$D$7,J5+J6+J7,0) | K8: =-IF(7=Assumptions!$D$7,K5+K6+K7,0) | L8: =-IF(8=Assumptions!$D$7,L5+L6+L7,0) | M8: =-IF(9=Assumptions!$D$7,M5+M6+M7,0) | N8: =-IF(10=Assumptions!$D$7,N5+N6+N7,0)
B9: CLOSING BALANCE | D9: =D5+D6+D7+D8 | E9: =E5+E6+E7+E8 | F9: =F5+F6+F7+F8 | G9: =G5+G6+G7+G8 | H9: =H5+H6+H7+H8 | I9: =I5+I6+I7+I8 | J9: =J5+J6+J7+J8 | K9: =K5+K6+K7+K8 | ... N9: =N5+N6+N7+N8
B10: Interest expense | D10: 0 | E10: =-E5*Assumptions!$D$42*Timeline!E5 | F10: =-F5*Assumptions!$D$42*Timeline!F5 | G10: =-G5*Assumptions!$D$42*Timeline!G5 | H10: =-H5*Assumptions!$D$42*Timeline!H5 | I10: =-I5*Assumptions!$D$42*Timeline!I5 | J10: =-J5*Assumptions!$D$42*Timeline!J5 | K10: =-K5*Assumptions!$D$42*Timeline!K5 | L10: =-L5*Assumptions!$D$42*Timeline!L5 | ... N10: =-N5*Assumptions!$D$42*Timeline!N5
B11: Arrangement fee (one-off) | D11: =-Assumptions!$D$47*Assumptions!$D$43 | E11: 0 | F11: 0 | G11: 0 | H11: 0 | I11: 0 | J11: 0 | K11: 0 | L11: 0 | M11: 0 | N11: 0
B12: TOTAL DEBT SERVICE (interest + principal) | D12: =D7+D8+D10+D11 | E12: =E7+E8+E10+E11 | F12: =F7+F8+F10+F11 | G12: =G7+G8+G10+G11 | H12: =H7+H8+H10+H11 | I12: =I7+I8+I10+I11 | J12: =J7+J8+J10+J11 | K12: =K7+K8+K10+K11 | ... N12: =N7+N8+N10+N11
B14: COVERAGE RATIOS (per year)
B15: Interest Coverage (NOI / |Interest|) | D15: =IFERROR(IF(D10=0,999,OpEx_CapEx!D9/ABS(D10)),999) | E15: =IFERROR(IF(E10=0,999,OpEx_CapEx!E9/ABS(E10)),999) | F15: =IFERROR(IF(F10=0,999,OpEx_CapEx!F9/ABS(F10)),999) | G15: =IFERROR(IF(G10=0,999,OpEx_CapEx!G9/ABS(G10)),999) | H15: =IFERROR(IF(H10=0,999,OpEx_CapEx!H9/ABS(H10)),999) | I15: =IFERROR(IF(I10=0,999,OpEx_CapEx!I9/ABS(I10)),999) | J15: =IFERROR(IF(J10=0,999,OpEx_CapEx!J9/ABS(J10)),999) | K15: =IFERROR(IF(K10=0,999,OpEx_CapEx!K9/ABS(K10)),999) | ... N15: =IFERROR(IF(N10=0,999,OpEx_CapEx!N9/ABS(N10)),999)
B16: DSCR (NOI / (|Interest|+|Principal|+|Bullet|)) | D16: =IFERROR(IF(ABS(D10)+ABS(D7)+ABS(D8)=0,999,OpEx_CapEx!D9/(ABS(D10)+ABS(D7)+ABS(D8))),999) | E16: =IFERROR(IF(ABS(E10)+ABS(E7)+ABS(E8)=0,999,OpEx_CapEx!E9/(ABS(E10)+ABS(E7)+ABS(E8))),999) | F16: =IFERROR(IF(ABS(F10)+ABS(F7)+ABS(F8)=0,999,OpEx_CapEx!F9/(ABS(F10)+ABS(F7)+ABS(F8))),999) | G16: =IFERROR(IF(ABS(G10)+ABS(G7)+ABS(G8)=0,999,OpEx_CapEx!G9/(ABS(G10)+ABS(G7)+ABS(G8))),999) | H16: =IFERROR(IF(ABS(H10)+ABS(H7)+ABS(H8)=0,999,OpEx_CapEx!H9/(ABS(H10)+ABS(H7)+ABS(H8))),999) | I16: =IFERROR(IF(ABS(I10)+ABS(I7)+ABS(I8)=0,999,OpEx_CapEx!I9/(ABS(I10)+ABS(I7)+ABS(I8))),999) | J16: =IFERROR(IF(ABS(J10)+ABS(J7)+ABS(J8)=0,999,OpEx_CapEx!J9/(ABS(J10)+ABS(J7)+ABS(J8))),999) | K16: =IFERROR(IF(ABS(K10)+ABS(K7)+ABS(K8)=0,999,OpEx_CapEx!K9/(ABS(K10)+ABS(K7)+ABS(K8))),999) | ... N16: =IFERROR(IF(ABS(N10)+ABS(N7)+ABS(N8)=0,999,OpEx_CapEx!N9/(ABS(N10)+ABS(N7)+ABS(N8))),999)
B17: LTV (Debt / Asset Value at acquisition) | D17: =IFERROR(IF(Assumptions!$D$16=0,0,D9/Assumptions!$D$16),0) | E17: =IFERROR(IF(Assumptions!$D$16=0,0,E9/Assumptions!$D$16),0) | F17: =IFERROR(IF(Assumptions!$D$16=0,0,F9/Assumptions!$D$16),0) | G17: =IFERROR(IF(Assumptions!$D$16=0,0,G9/Assumptions!$D$16),0) | H17: =IFERROR(IF(Assumptions!$D$16=0,0,H9/Assumptions!$D$16),0) | I17: =IFERROR(IF(Assumptions!$D$16=0,0,I9/Assumptions!$D$16),0) | J17: =IFERROR(IF(Assumptions!$D$16=0,0,J9/Assumptions!$D$16),0) | K17: =IFERROR(IF(Assumptions!$D$16=0,0,K9/Assumptions!$D$16),0) | ... N17: =IFERROR(IF(Assumptions!$D$16=0,0,N9/Assumptions!$D$16),0)
B18: Debt yield (NOI / Debt outstanding) | D18: =IFERROR(IF(D9=0,"",OpEx_CapEx!D9/D9),"") | E18: =IFERROR(IF(E9=0,"",OpEx_CapEx!E9/E9),"") | F18: =IFERROR(IF(F9=0,"",OpEx_CapEx!F9/F9),"") | G18: =IFERROR(IF(G9=0,"",OpEx_CapEx!G9/G9),"") | H18: =IFERROR(IF(H9=0,"",OpEx_CapEx!H9/H9),"") | I18: =IFERROR(IF(I9=0,"",OpEx_CapEx!I9/I9),"") | J18: =IFERROR(IF(J9=0,"",OpEx_CapEx!J9/J9),"") | K18: =IFERROR(IF(K9=0,"",OpEx_CapEx!K9/K9),"") | ... N18: =IFERROR(IF(N9=0,"",OpEx_CapEx!N9/N9),"")
B19: Operating DSCR (interest + scheduled principal only) | D19: =IFERROR(IF(ABS(D10)+ABS(D7)=0,999,OpEx_CapEx!D9/(ABS(D10)+ABS(D7))),999) | E19: =IFERROR(IF(ABS(E10)+ABS(E7)=0,999,OpEx_CapEx!E9/(ABS(E10)+ABS(E7))),999) | F19: =IFERROR(IF(ABS(F10)+ABS(F7)=0,999,OpEx_CapEx!F9/(ABS(F10)+ABS(F7))),999) | G19: =IFERROR(IF(ABS(G10)+ABS(G7)=0,999,OpEx_CapEx!G9/(ABS(G10)+ABS(G7))),999) | H19: =IFERROR(IF(ABS(H10)+ABS(H7)=0,999,OpEx_CapEx!H9/(ABS(H10)+ABS(H7))),999) | I19: =IFERROR(IF(ABS(I10)+ABS(I7)=0,999,OpEx_CapEx!I9/(ABS(I10)+ABS(I7))),999) | J19: =IFERROR(IF(ABS(J10)+ABS(J7)=0,999,OpEx_CapEx!J9/(ABS(J10)+ABS(J7))),999) | K19: =IFERROR(IF(ABS(K10)+ABS(K7)=0,999,OpEx_CapEx!K9/(ABS(K10)+ABS(K7))),999) | ... N19: =IFERROR(IF(ABS(N10)+ABS(N7)=0,999,OpEx_CapEx!N9/(ABS(N10)+ABS(N7))),999)

Sheet QtrDebt
B2: QUARTERLY DEBT SERVICE — covenant & DSCR testing (40 quarters)
B3: Mirrors annual debt schedule at quarterly granularity. NOI approximated as annual / 4 (assumes flat intra-year).
B5: Quarter | C5: Q0 | D5: Q1 | E5: Q2 | F5: Q3 | G5: Q4 | H5: Q5 | I5: Q6 | J5: Q7 | K5: Q8 | L5: Q9 | M5: Q10 | N5: Q11 | O5: Q12 | P5: Q13 | Q5: Q14 | R5: Q15 | S5: Q16 | T5: Q17 | U5: Q18 | V5: Q19 | W5: Q20 | X5: Q21 | Y5: Q22 | Z5: Q23 | AA5: Q24 | AB5: Q25 | AC5: Q26 | AD5: Q27 | AE5: Q28 | AF5: Q29 | AG5: Q30 | AH5: Q31 | AI5: Q32 | AJ5: Q33 | AK5: Q34 | AL5: Q35 | AM5: Q36 | AN5: Q37 | AO5: Q38 | AP5: Q39 | AQ5: Q40
B6: Calendar year | C6: =Assumptions!$D$6+0 | D6: =Assumptions!$D$6+0 | E6: =Assumptions!$D$6+0 | F6: =Assumptions!$D$6+0 | G6: =Assumptions!$D$6+1 | H6: =Assumptions!$D$6+1 | I6: =Assumptions!$D$6+1 | J6: =Assumptions!$D$6+1 | K6: =Assumptions!$D$6+2 | L6: =Assumptions!$D$6+2 | M6: =Assumptions!$D$6+2 | N6: =Assumptions!$D$6+2 | O6: =Assumptions!$D$6+3 | P6: =Assumptions!$D$6+3 | Q6: =Assumptions!$D$6+3 | R6: =Assumptions!$D$6+3 | S6: =Assumptions!$D$6+4 | T6: =Assumptions!$D$6+4 | U6: =Assumptions!$D$6+4 | V6: =Assumptions!$D$6+4 | W6: =Assumptions!$D$6+5 | X6: =Assumptions!$D$6+5 | Y6: =Assumptions!$D$6+5 | Z6: =Assumptions!$D$6+5 | AA6: =Assumptions!$D$6+6 | AB6: =Assumptions!$D$6+6 | AC6: =Assumptions!$D$6+6 | AD6: =Assumptions!$D$6+6 | AE6: =Assumptions!$D$6+7 | AF6: =Assumptions!$D$6+7 | AG6: =Assumptions!$D$6+7 | AH6: =Assumptions!$D$6+7 | AI6: =Assumptions!$D$6+8 | AJ6: =Assumptions!$D$6+8 | AK6: =Assumptions!$D$6+8 | AL6: =Assumptions!$D$6+8 | AM6: =Assumptions!$D$6+9 | AN6: =Assumptions!$D$6+9 | AO6: =Assumptions!$D$6+9 | AP6: =Assumptions!$D$6+9 | AQ6: =Assumptions!$D$6+10
B7: Operating flag | C7: =IF(AND(0>=1,0<=Assumptions!$D$7),1,0) | D7: =IF(AND(0>=1,0<=Assumptions!$D$7),1,0) | E7: =IF(AND(0>=1,0<=Assumptions!$D$7),1,0) | F7: =IF(AND(0>=1,0<=Assumptions!$D$7),1,0) | G7: =IF(AND(1>=1,1<=Assumptions!$D$7),1,0) | H7: =IF(AND(1>=1,1<=Assumptions!$D$7),1,0) | I7: =IF(AND(1>=1,1<=Assumptions!$D$7),1,0) | J7: =IF(AND(1>=1,1<=Assumptions!$D$7),1,0) | K7: =IF(AND(2>=1,2<=Assumptions!$D$7),1,0) | L7: =IF(AND(2>=1,2<=Assumptions!$D$7),1,0) | M7: =IF(AND(2>=1,2<=Assumptions!$D$7),1,0) | N7: =IF(AND(2>=1,2<=Assumptions!$D$7),1,0) | O7: =IF(AND(3>=1,3<=Assumptions!$D$7),1,0) | P7: =IF(AND(3>=1,3<=Assumptions!$D$7),1,0) | Q7: =IF(AND(3>=1,3<=Assumptions!$D$7),1,0) | R7: =IF(AND(3>=1,3<=Assumptions!$D$7),1,0) | S7: =IF(AND(4>=1,4<=Assumptions!$D$7),1,0) | T7: =IF(AND(4>=1,4<=Assumptions!$D$7),1,0) | U7: =IF(AND(4>=1,4<=Assumptions!$D$7),1,0) | V7: =IF(AND(4>=1,4<=Assumptions!$D$7),1,0) | W7: =IF(AND(5>=1,5<=Assumptions!$D$7),1,0) | X7: =IF(AND(5>=1,5<=Assumptions!$D$7),1,0) | Y7: =IF(AND(5>=1,5<=Assumptions!$D$7),1,0) | Z7: =IF(AND(5>=1,5<=Assumptions!$D$7),1,0) | AA7: =IF(AND(6>=1,6<=Assumptions!$D$7),1,0) | AB7: =IF(AND(6>=1,6<=Assumptions!$D$7),1,0) | AC7: =IF(AND(6>=1,6<=Assumptions!$D$7),1,0) | AD7: =IF(AND(6>=1,6<=Assumptions!$D$7),1,0) | AE7: =IF(AND(7>=1,7<=Assumptions!$D$7),1,0) | AF7: =IF(AND(7>=1,7<=Assumptions!$D$7),1,0) | AG7: =IF(AND(7>=1,7<=Assumptions!$D$7),1,0) | AH7: =IF(AND(7>=1,7<=Assumptions!$D$7),1,0) | AI7: =IF(AND(8>=1,8<=Assumptions!$D$7),1,0) | AJ7: =IF(AND(8>=1,8<=Assumptions!$D$7),1,0) | AK7: =IF(AND(8>=1,8<=Assumptions!$D$7),1,0) | AL7: =IF(AND(8>=1,8<=Assumptions!$D$7),1,0) | AM7: =IF(AND(9>=1,9<=Assumptions!$D$7),1,0) | AN7: =IF(AND(9>=1,9<=Assumptions!$D$7),1,0) | AO7: =IF(AND(9>=1,9<=Assumptions!$D$7),1,0) | AP7: =IF(AND(9>=1,9<=Assumptions!$D$7),1,0) | AQ7: =IF(AND(10>=1,10<=Assumptions!$D$7),1,0)
B9: Quarterly NOI | C9: =INDEX(OpEx_CapEx!$D$9:$N$9,1,1)/4*C7 | D9: =INDEX(OpEx_CapEx!$D$9:$N$9,1,1)/4*D7 | E9: =INDEX(OpEx_CapEx!$D$9:$N$9,1,1)/4*E7 | F9: =INDEX(OpEx_CapEx!$D$9:$N$9,1,1)/4*F7 | G9: =INDEX(OpEx_CapEx!$D$9:$N$9,1,2)/4*G7 | H9: =INDEX(OpEx_CapEx!$D$9:$N$9,1,2)/4*H7 | I9: =INDEX(OpEx_CapEx!$D$9:$N$9,1,2)/4*I7 | J9: =INDEX(OpEx_CapEx!$D$9:$N$9,1,2)/4*J7 | K9: =INDEX(OpEx_CapEx!$D$9:$N$9,1,3)/4*K7 | L9: =INDEX(OpEx_CapEx!$D$9:$N$9,1,3)/4*L7 | M9: =INDEX(OpEx_CapEx!$D$9:$N$9,1,3)/4*M7 | N9: =INDEX(OpEx_CapEx!$D$9:$N$9,1,3)/4*N7 | O9: =INDEX(OpEx_CapEx!$D$9:$N$9,1,4)/4*O7 | P9: =INDEX(OpEx_CapEx!$D$9:$N$9,1,4)/4*P7 | Q9: =INDEX(OpEx_CapEx!$D$9:$N$9,1,4)/4*Q7 | R9: =INDEX(OpEx_CapEx!$D$9:$N$9,1,4)/4*R7 | S9: =INDEX(OpEx_CapEx!$D$9:$N$9,1,5)/4*S7 | T9: =INDEX(OpEx_CapEx!$D$9:$N$9,1,5)/4*T7 | U9: =INDEX(OpEx_CapEx!$D$9:$N$9,1,5)/4*U7 | V9: =INDEX(OpEx_CapEx!$D$9:$N$9,1,5)/4*V7 | W9: =INDEX(OpEx_CapEx!$D$9:$N$9,1,6)/4*W7 | X9: =INDEX(OpEx_CapEx!$D$9:$N$9,1,6)/4*X7 | Y9: =INDEX(OpEx_CapEx!$D$9:$N$9,1,6)/4*Y7 | Z9: =INDEX(OpEx_CapEx!$D$9:$N$9,1,6)/4*Z7 | AA9: =INDEX(OpEx_CapEx!$D$9:$N$9,1,7)/4*AA7 | AB9: =INDEX(OpEx_CapEx!$D$9:$N$9,1,7)/4*AB7 | AC9: =INDEX(OpEx_CapEx!$D$9:$N$9,1,7)/4*AC7 | AD9: =INDEX(OpEx_CapEx!$D$9:$N$9,1,7)/4*AD7 | AE9: =INDEX(OpEx_CapEx!$D$9:$N$9,1,8)/4*AE7 | AF9: =INDEX(OpEx_CapEx!$D$9:$N$9,1,8)/4*AF7 | AG9: =INDEX(OpEx_CapEx!$D$9:$N$9,1,8)/4*AG7 | AH9: =INDEX(OpEx_CapEx!$D$9:$N$9,1,8)/4*AH7 | AI9: =INDEX(OpEx_CapEx!$D$9:$N$9,1,9)/4*AI7 | AJ9: =INDEX(OpEx_CapEx!$D$9:$N$9,1,9)/4*AJ7 | AK9: =INDEX(OpEx_CapEx!$D$9:$N$9,1,9)/4*AK7 | AL9: =INDEX(OpEx_CapEx!$D$9:$N$9,1,9)/4*AL7 | AM9: =INDEX(OpEx_CapEx!$D$9:$N$9,1,10)/4*AM7 | AN9: =INDEX(OpEx_CapEx!$D$9:$N$9,1,10)/4*AN7 | AO9: =INDEX(OpEx_CapEx!$D$9:$N$9,1,10)/4*AO7 | AP9: =INDEX(OpEx_CapEx!$D$9:$N$9,1,10)/4*AP7 | AQ9: =INDEX(OpEx_CapEx!$D$9:$N$9,1,11)/4*AQ7
B10: Debt balance (period-start) | C10: =INDEX(Debt!$D$5:$N$5,1,1) | D10: =INDEX(Debt!$D$5:$N$5,1,1) | E10: =INDEX(Debt!$D$5:$N$5,1,1) | F10: =INDEX(Debt!$D$5:$N$5,1,1) | G10: =INDEX(Debt!$D$5:$N$5,1,2) | H10: =INDEX(Debt!$D$5:$N$5,1,2) | I10: =INDEX(Debt!$D$5:$N$5,1,2) | J10: =INDEX(Debt!$D$5:$N$5,1,2) | K10: =INDEX(Debt!$D$5:$N$5,1,3) | L10: =INDEX(Debt!$D$5:$N$5,1,3) | M10: =INDEX(Debt!$D$5:$N$5,1,3) | N10: =INDEX(Debt!$D$5:$N$5,1,3) | O10: =INDEX(Debt!$D$5:$N$5,1,4) | P10: =INDEX(Debt!$D$5:$N$5,1,4) | Q10: =INDEX(Debt!$D$5:$N$5,1,4) | R10: =INDEX(Debt!$D$5:$N$5,1,4) | S10: =INDEX(Debt!$D$5:$N$5,1,5) | T10: =INDEX(Debt!$D$5:$N$5,1,5) | U10: =INDEX(Debt!$D$5:$N$5,1,5) | V10: =INDEX(Debt!$D$5:$N$5,1,5) | W10: =INDEX(Debt!$D$5:$N$5,1,6) | X10: =INDEX(Debt!$D$5:$N$5,1,6) | Y10: =INDEX(Debt!$D$5:$N$5,1,6) | Z10: =INDEX(Debt!$D$5:$N$5,1,6) | AA10: =INDEX(Debt!$D$5:$N$5,1,7) | AB10: =INDEX(Debt!$D$5:$N$5,1,7) | AC10: =INDEX(Debt!$D$5:$N$5,1,7) | AD10: =INDEX(Debt!$D$5:$N$5,1,7) | AE10: =INDEX(Debt!$D$5:$N$5,1,8) | AF10: =INDEX(Debt!$D$5:$N$5,1,8) | AG10: =INDEX(Debt!$D$5:$N$5,1,8) | AH10: =INDEX(Debt!$D$5:$N$5,1,8) | AI10: =INDEX(Debt!$D$5:$N$5,1,9) | AJ10: =INDEX(Debt!$D$5:$N$5,1,9) | AK10: =INDEX(Debt!$D$5:$N$5,1,9) | AL10: =INDEX(Debt!$D$5:$N$5,1,9) | AM10: =INDEX(Debt!$D$5:$N$5,1,10) | AN10: =INDEX(Debt!$D$5:$N$5,1,10) | AO10: =INDEX(Debt!$D$5:$N$5,1,10) | AP10: =INDEX(Debt!$D$5:$N$5,1,10) | AQ10: =INDEX(Debt!$D$5:$N$5,1,11)
B11: Quarterly interest | C11: =C10*Assumptions!$D$42/4*C7 | D11: =D10*Assumptions!$D$42/4*D7 | E11: =E10*Assumptions!$D$42/4*E7 | F11: =F10*Assumptions!$D$42/4*F7 | G11: =G10*Assumptions!$D$42/4*G7 | H11: =H10*Assumptions!$D$42/4*H7 | I11: =I10*Assumptions!$D$42/4*I7 | J11: =J10*Assumptions!$D$42/4*J7 | ... AQ11: =AQ10*Assumptions!$D$42/4*AQ7
B12: Quarterly principal (scheduled) | C12: =IFERROR(INDEX(Debt!$D$7:$N$7,1,1)/4,0)*C7 | D12: =IFERROR(INDEX(Debt!$D$7:$N$7,1,1)/4,0)*D7 | E12: =IFERROR(INDEX(Debt!$D$7:$N$7,1,1)/4,0)*E7 | F12: =IFERROR(INDEX(Debt!$D$7:$N$7,1,1)/4,0)*F7 | G12: =IFERROR(INDEX(Debt!$D$7:$N$7,1,2)/4,0)*G7 | H12: =IFERROR(INDEX(Debt!$D$7:$N$7,1,2)/4,0)*H7 | I12: =IFERROR(INDEX(Debt!$D$7:$N$7,1,2)/4,0)*I7 | J12: =IFERROR(INDEX(Debt!$D$7:$N$7,1,2)/4,0)*J7 | K12: =IFERROR(INDEX(Debt!$D$7:$N$7,1,3)/4,0)*K7 | L12: =IFERROR(INDEX(Debt!$D$7:$N$7,1,3)/4,0)*L7 | M12: =IFERROR(INDEX(Debt!$D$7:$N$7,1,3)/4,0)*M7 | N12: =IFERROR(INDEX(Debt!$D$7:$N$7,1,3)/4,0)*N7 | O12: =IFERROR(INDEX(Debt!$D$7:$N$7,1,4)/4,0)*O7 | P12: =IFERROR(INDEX(Debt!$D$7:$N$7,1,4)/4,0)*P7 | Q12: =IFERROR(INDEX(Debt!$D$7:$N$7,1,4)/4,0)*Q7 | R12: =IFERROR(INDEX(Debt!$D$7:$N$7,1,4)/4,0)*R7 | S12: =IFERROR(INDEX(Debt!$D$7:$N$7,1,5)/4,0)*S7 | T12: =IFERROR(INDEX(Debt!$D$7:$N$7,1,5)/4,0)*T7 | U12: =IFERROR(INDEX(Debt!$D$7:$N$7,1,5)/4,0)*U7 | V12: =IFERROR(INDEX(Debt!$D$7:$N$7,1,5)/4,0)*V7 | W12: =IFERROR(INDEX(Debt!$D$7:$N$7,1,6)/4,0)*W7 | X12: =IFERROR(INDEX(Debt!$D$7:$N$7,1,6)/4,0)*X7 | Y12: =IFERROR(INDEX(Debt!$D$7:$N$7,1,6)/4,0)*Y7 | Z12: =IFERROR(INDEX(Debt!$D$7:$N$7,1,6)/4,0)*Z7 | AA12: =IFERROR(INDEX(Debt!$D$7:$N$7,1,7)/4,0)*AA7 | AB12: =IFERROR(INDEX(Debt!$D$7:$N$7,1,7)/4,0)*AB7 | AC12: =IFERROR(INDEX(Debt!$D$7:$N$7,1,7)/4,0)*AC7 | AD12: =IFERROR(INDEX(Debt!$D$7:$N$7,1,7)/4,0)*AD7 | AE12: =IFERROR(INDEX(Debt!$D$7:$N$7,1,8)/4,0)*AE7 | AF12: =IFERROR(INDEX(Debt!$D$7:$N$7,1,8)/4,0)*AF7 | AG12: =IFERROR(INDEX(Debt!$D$7:$N$7,1,8)/4,0)*AG7 | AH12: =IFERROR(INDEX(Debt!$D$7:$N$7,1,8)/4,0)*AH7 | AI12: =IFERROR(INDEX(Debt!$D$7:$N$7,1,9)/4,0)*AI7 | AJ12: =IFERROR(INDEX(Debt!$D$7:$N$7,1,9)/4,0)*AJ7 | AK12: =IFERROR(INDEX(Debt!$D$7:$N$7,1,9)/4,0)*AK7 | AL12: =IFERROR(INDEX(Debt!$D$7:$N$7,1,9)/4,0)*AL7 | AM12: =IFERROR(INDEX(Debt!$D$7:$N$7,1,10)/4,0)*AM7 | AN12: =IFERROR(INDEX(Debt!$D$7:$N$7,1,10)/4,0)*AN7 | AO12: =IFERROR(INDEX(Debt!$D$7:$N$7,1,10)/4,0)*AO7 | AP12: =IFERROR(INDEX(Debt!$D$7:$N$7,1,10)/4,0)*AP7 | AQ12: =IFERROR(INDEX(Debt!$D$7:$N$7,1,11)/4,0)*AQ7
B13: Bullet repayment at exit | C13: 0 | D13: 0 | E13: 0 | F13: 0 | G13: 0 | H13: 0 | I13: 0 | J13: 0 | K13: 0 | L13: 0 | M13: 0 | N13: 0 | O13: 0 | P13: 0 | Q13: 0 | R13: 0 | S13: 0 | T13: 0 | U13: 0 | V13: 0 | W13: 0 | X13: 0 | Y13: 0 | Z13: 0 | AA13: 0 | AB13: 0 | AC13: 0 | AD13: 0 | AE13: 0 | AF13: 0 | AG13: 0 | AH13: 0 | AI13: 0 | AJ13: 0 | AK13: 0 | AL13: 0 | AM13: 0 | AN13: 0 | AO13: 0 | AP13: 0 | AQ13: =INDEX(Debt!$D$8:$N$8,1,Assumptions!$D$7+1)
B14: Total quarterly debt service | C14: =ABS(C11)+ABS(C12)+ABS(C13) | D14: =ABS(D11)+ABS(D12)+ABS(D13) | E14: =ABS(E11)+ABS(E12)+ABS(E13) | F14: =ABS(F11)+ABS(F12)+ABS(F13) | G14: =ABS(G11)+ABS(G12)+ABS(G13) | H14: =ABS(H11)+ABS(H12)+ABS(H13) | I14: =ABS(I11)+ABS(I12)+ABS(I13) | J14: =ABS(J11)+ABS(J12)+ABS(J13) | ... AQ14: =ABS(AQ11)+ABS(AQ12)+ABS(AQ13)
B16: Quarterly DSCR (excl. bullet) | C16: =IFERROR(IF(ABS(C11)+ABS(C12)=0,"-",C9/(ABS(C11)+ABS(C12))),"-") | D16: =IFERROR(IF(ABS(D11)+ABS(D12)=0,"-",D9/(ABS(D11)+ABS(D12))),"-") | E16: =IFERROR(IF(ABS(E11)+ABS(E12)=0,"-",E9/(ABS(E11)+ABS(E12))),"-") | F16: =IFERROR(IF(ABS(F11)+ABS(F12)=0,"-",F9/(ABS(F11)+ABS(F12))),"-") | G16: =IFERROR(IF(ABS(G11)+ABS(G12)=0,"-",G9/(ABS(G11)+ABS(G12))),"-") | H16: =IFERROR(IF(ABS(H11)+ABS(H12)=0,"-",H9/(ABS(H11)+ABS(H12))),"-") | I16: =IFERROR(IF(ABS(I11)+ABS(I12)=0,"-",I9/(ABS(I11)+ABS(I12))),"-") | J16: =IFERROR(IF(ABS(J11)+ABS(J12)=0,"-",J9/(ABS(J11)+ABS(J12))),"-") | ... AQ16: =IFERROR(IF(ABS(AQ11)+ABS(AQ12)=0,"-",AQ9/(ABS(AQ11)+ABS(AQ12))),"-")
B17: Quarterly covenant test (≥ 1.30x) | C17: =IFERROR(IF(C16="-","-",IF(C16>=Assumptions!$D$73,"PASS","BREACH")),"-") | D17: =IFERROR(IF(D16="-","-",IF(D16>=Assumptions!$D$73,"PASS","BREACH")),"-") | E17: =IFERROR(IF(E16="-","-",IF(E16>=Assumptions!$D$73,"PASS","BREACH")),"-") | F17: =IFERROR(IF(F16="-","-",IF(F16>=Assumptions!$D$73,"PASS","BREACH")),"-") | G17: =IFERROR(IF(G16="-","-",IF(G16>=Assumptions!$D$73,"PASS","BREACH")),"-") | H17: =IFERROR(IF(H16="-","-",IF(H16>=Assumptions!$D$73,"PASS","BREACH")),"-") | I17: =IFERROR(IF(I16="-","-",IF(I16>=Assumptions!$D$73,"PASS","BREACH")),"-") | J17: =IFERROR(IF(J16="-","-",IF(J16>=Assumptions!$D$73,"PASS","BREACH")),"-") | ... AQ17: =IFERROR(IF(AQ16="-","-",IF(AQ16>=Assumptions!$D$73,"PASS","BREACH")),"-")
B19: Min quarterly DSCR | C19: =MIN(C16:AQ16)
B20: Quarters in breach | C20: =COUNTIF(C17:AQ17,"BREACH")

Sheet Refinance
B2: REFINANCING MODULE — institutional treatment of bullet exit
B3: Models a single refinancing event during hold. When ON, bullet at original maturity is replaced by amortizing/bullet refi; remaining principal at exit is repaid from sale proceeds.
B5: Refi switch | D5: =Assumptions!$D$79
B6: Refi year (Yn) | D6: =Assumptions!$D$80
B7: Property value at refi (Y_refi NOI / exit cap proxy) | D7: =IFERROR(INDEX(OpEx_CapEx!E9:N9,1,Assumptions!$D$80)/Assumptions!$D$51,0)
B8: Refi LTV | D8: =Assumptions!$D$81
B9: New debt size | D9: =D7*D8
B10: Existing debt outstanding at refi | D10: =IFERROR(INDEX(Debt!D9:N9,1,Assumptions!$D$80+1),0)
B11: Refi cash inflow / (paydown) | D11: =IF(D5=1,D9-D10,0)
B12: Refi fee (one-off) | D12: =IF(D5=1,-D9*Assumptions!$D$85,0)
B13: Refi cost of debt | D13: =Assumptions!$D$82
B14: Refi tenor (yrs) | D14: =Assumptions!$D$83
B15: Refi amortization | D15: =IF(Assumptions!$D$84=1,"AMORT","BULLET")
B17: REFINANCED-LOAN ANNUAL SCHEDULE
B18: Metric | C18: Y0 | D18: Y1 | E18: Y2 | F18: Y3 | G18: Y4 | H18: Y5 | I18: Y6 | J18: Y7 | K18: Y8 | L18: Y9 | M18: Y10
D19: 0 | E19: =IF(D5=0,0,IF(1=D6,D9,IF(1>D6,MAX(0,D19+D21+D22),0))) | F19: =IF(D5=0,0,IF(2=D6,D9,IF(2>D6,MAX(0,E19+E21+E22),0))) | G19: =IF(D5=0,0,IF(3=D6,D9,IF(3>D6,MAX(0,F19+F21+F22),0))) | H19: =IF(D5=0,0,IF(4=D6,D9,IF(4>D6,MAX(0,G19+G21+G22),0))) | I19: =IF(D5=0,0,IF(5=D6,D9,IF(5>D6,MAX(0,H19+H21+H22),0))) | J19: =IF(D5=0,0,IF(6=D6,D9,IF(6>D6,MAX(0,I19+I21+I22),0))) | K19: =IF(D5=0,0,IF(7=D6,D9,IF(7>D6,MAX(0,J19+J21+J22),0))) | L19: =IF(D5=0,0,IF(8=D6,D9,IF(8>D6,MAX(0,K19+K21+K22),0))) | M19: =IF(D5=0,0,IF(9=D6,D9,IF(9>D6,MAX(0,L19+L21+L22),0))) | N19: =IF(D5=0,0,IF(10=D6,D9,IF(10>D6,MAX(0,M19+M21+M22),0)))
B20: Drawdown / (paydown) at refi | D20: =IF(AND(D5=1,0=D6),D9,0) | E20: =IF(AND(D5=1,1=D6),D9,0) | F20: =IF(AND(D5=1,2=D6),D9,0) | G20: =IF(AND(D5=1,3=D6),D9,0) | H20: =IF(AND(D5=1,4=D6),D9,0) | I20: =IF(AND(D5=1,5=D6),D9,0) | J20: =IF(AND(D5=1,6=D6),D9,0) | K20: =IF(AND(D5=1,7=D6),D9,0) | L20: =IF(AND(D5=1,8=D6),D9,0) | M20: =IF(AND(D5=1,9=D6),D9,0) | N20: =IF(AND(D5=1,10=D6),D9,0)
B21: Refi scheduled principal | D21: =IF(AND(D5=1,Assumptions!$D$84=1,0>D6,0<Assumptions!$D$7,D14>0),-D9/D14,0) | E21: =IF(AND(D5=1,Assumptions!$D$84=1,1>D6,1<Assumptions!$D$7,D14>0),-D9/D14,0) | F21: =IF(AND(D5=1,Assumptions!$D$84=1,2>D6,2<Assumptions!$D$7,D14>0),-D9/D14,0) | G21: =IF(AND(D5=1,Assumptions!$D$84=1,3>D6,3<Assumptions!$D$7,D14>0),-D9/D14,0) | H21: =IF(AND(D5=1,Assumptions!$D$84=1,4>D6,4<Assumptions!$D$7,D14>0),-D9/D14,0) | I21: =IF(AND(D5=1,Assumptions!$D$84=1,5>D6,5<Assumptions!$D$7,D14>0),-D9/D14,0) | J21: =IF(AND(D5=1,Assumptions!$D$84=1,6>D6,6<Assumptions!$D$7,D14>0),-D9/D14,0) | K21: =IF(AND(D5=1,Assumptions!$D$84=1,7>D6,7<Assumptions!$D$7,D14>0),-D9/D14,0) | L21: =IF(AND(D5=1,Assumptions!$D$84=1,8>D6,8<Assumptions!$D$7,D14>0),-D9/D14,0) | M21: =IF(AND(D5=1,Assumptions!$D$84=1,9>D6,9<Assumptions!$D$7,D14>0),-D9/D14,0) | N21: =IF(AND(D5=1,Assumptions!$D$84=1,10>D6,10<Assumptions!$D$7,D14>0),-D9/D14,0)
B22: Refi bullet at exit | D22: 0 | E22: =IF(AND(D5=1,1=Assumptions!$D$7),-MAX(0,D19+D20+D21),0) | F22: =IF(AND(D5=1,2=Assumptions!$D$7),-MAX(0,E19+E20+E21),0) | G22: =IF(AND(D5=1,3=Assumptions!$D$7),-MAX(0,F19+F20+F21),0) | H22: =IF(AND(D5=1,4=Assumptions!$D$7),-MAX(0,G19+G20+G21),0) | I22: =IF(AND(D5=1,5=Assumptions!$D$7),-MAX(0,H19+H20+H21),0) | J22: =IF(AND(D5=1,6=Assumptions!$D$7),-MAX(0,I19+I20+I21),0) | K22: =IF(AND(D5=1,7=Assumptions!$D$7),-MAX(0,J19+J20+J21),0) | L22: =IF(AND(D5=1,8=Assumptions!$D$7),-MAX(0,K19+K20+K21),0) | M22: =IF(AND(D5=1,9=Assumptions!$D$7),-MAX(0,L19+L20+L21),0) | N22: =IF(AND(D5=1,10=Assumptions!$D$7),-MAX(0,M19+M20+M21),0)
B23: Refi interest expense | D23: 0 | E23: =IF(D5=1,-D19*D13,0) | F23: =IF(D5=1,-E19*D13,0) | G23: =IF(D5=1,-F19*D13,0) | H23: =IF(D5=1,-G19*D13,0) | I23: =IF(D5=1,-H19*D13,0) | J23: =IF(D5=1,-I19*D13,0) | K23: =IF(D5=1,-J19*D13,0) | L23: =IF(D5=1,-K19*D13,0) | M23: =IF(D5=1,-L19*D13,0) | N23: =IF(D5=1,-M19*D13,0)
B25: REFINANCED-LOAN DSCR (NOI − CapEx) / |Refi debt service|
E26: =IFERROR(IF(D5=0,"-",IF(ABS(E23)+ABS(E21)=0,"-",(OpEx_CapEx!E9+OpEx_CapEx!E23)/(ABS(E23)+ABS(E21)))),"-") | F26: =IFERROR(IF(D5=0,"-",IF(ABS(F23)+ABS(F21)=0,"-",(OpEx_CapEx!F9+OpEx_CapEx!F23)/(ABS(F23)+ABS(F21)))),"-") | G26: =IFERROR(IF(D5=0,"-",IF(ABS(G23)+ABS(G21)=0,"-",(OpEx_CapEx!G9+OpEx_CapEx!G23)/(ABS(G23)+ABS(G21)))),"-") | H26: =IFERROR(IF(D5=0,"-",IF(ABS(H23)+ABS(H21)=0,"-",(OpEx_CapEx!H9+OpEx_CapEx!H23)/(ABS(H23)+ABS(H21)))),"-") | I26: =IFERROR(IF(D5=0,"-",IF(ABS(I23)+ABS(I21)=0,"-",(OpEx_CapEx!I9+OpEx_CapEx!I23)/(ABS(I23)+ABS(I21)))),"-") | J26: =IFERROR(IF(D5=0,"-",IF(ABS(J23)+ABS(J21)=0,"-",(OpEx_CapEx!J9+OpEx_CapEx!J23)/(ABS(J23)+ABS(J21)))),"-") | K26: =IFERROR(IF(D5=0,"-",IF(ABS(K23)+ABS(K21)=0,"-",(OpEx_CapEx!K9+OpEx_CapEx!K23)/(ABS(K23)+ABS(K21)))),"-") | L26: =IFERROR(IF(D5=0,"-",IF(ABS(L23)+ABS(L21)=0,"-",(OpEx_CapEx!L9+OpEx_CapEx!L23)/(ABS(L23)+ABS(L21)))),"-") | M26: =IFERROR(IF(D5=0,"-",IF(ABS(M23)+ABS(M21)=0,"-",(OpEx_CapEx!M9+OpEx_CapEx!M23)/(ABS(M23)+ABS(M21)))),"-") | N26: =IFERROR(IF(D5=0,"-",IF(ABS(N23)+ABS(N21)=0,"-",(OpEx_CapEx!N9+OpEx_CapEx!N23)/(ABS(N23)+ABS(N21)))),"-")
B27: Refi total debt service (cash out) | D27: =D23+D21+D22 | E27: =E23+E21+E22 | F27: =F23+F21+F22 | G27: =G23+G21+G22 | H27: =H23+H21+H22 | I27: =I23+I21+I22 | J27: =J23+J21+J22 | K27: =K23+K21+K22 | ... N27: =N23+N21+N22
B29: Net refi cash to equity (drawdown − paydown − fee) | D29: =IF(AND(D5=1,0=D6),D11+D12,0) | E29: =IF(AND(D5=1,1=D6),D11+D12,0) | F29: =IF(AND(D5=1,2=D6),D11+D12,0) | G29: =IF(AND(D5=1,3=D6),D11+D12,0) | H29: =IF(AND(D5=1,4=D6),D11+D12,0) | I29: =IF(AND(D5=1,5=D6),D11+D12,0) | J29: =IF(AND(D5=1,6=D6),D11+D12,0) | K29: =IF(AND(D5=1,7=D6),D11+D12,0) | L29: =IF(AND(D5=1,8=D6),D11+D12,0) | M29: =IF(AND(D5=1,9=D6),D11+D12,0) | N29: =IF(AND(D5=1,10=D6),D11+D12,0)

Sheet Reserves
B2: RESERVE ACCOUNTS — institutional liquidity stack
B3: Required liquidity at closing and minimum runway during operations.
B5: INITIAL FUNDING AT CLOSING (Y0)
B6: Annual debt service (Y1, approx) | D6: =ABS(Debt!E12)
B7: DSRA required (months × DS / 12) | D7: =Assumptions!$D$89/12*D6
B8: DSRA funded (assumed 100%) | D8: =D7
B9: Annual OpEx (Y1, approx) | D9: =ABS(OpEx_CapEx!E8)+ABS(OpEx_CapEx!E17)
B10: Operating reserve required | D10: =Assumptions!$D$90/12*D9
B11: Annual CapEx (Y1, approx) | D11: =ABS(OpEx_CapEx!E21)
B12: CapEx reserve required | D12: =Assumptions!$D$91/12*D11
B13: Contingency reserve | D13: =Assumptions!$D$92*Assumptions!$D$16
B14: TOTAL RESERVES AT CLOSING | D14: =D8+D10+D12+D13
B15: Incremental equity check vs base case | D15: =D14
B16: Total project cost (incl. reserves) | D16: =Assumptions!$D$16+D14
B18: MINIMUM LIQUIDITY THRESHOLDS
B19: Year | C19: Equity FCF (annual) | D19: Cumulative liquidity (incl reserves) | E19: Min cash floor | F19: Runway test
B20: 0 | C20: =Cash_Flow!D25 | D20: =D14+C20 | E20: =Assumptions!$D$93 | F20: =IF(D20>=E20,"OK","BREACH")
B21: 1 | C21: =Cash_Flow!E25 | D21: =D20+C21 | E21: =Assumptions!$D$93 | F21: =IF(D21>=E21,"OK","BREACH")
B22: 2 | C22: =Cash_Flow!F25 | D22: =D21+C22 | E22: =Assumptions!$D$93 | F22: =IF(D22>=E22,"OK","BREACH")
B23: 3 | C23: =Cash_Flow!G25 | D23: =D22+C23 | E23: =Assumptions!$D$93 | F23: =IF(D23>=E23,"OK","BREACH")
B24: 4 | C24: =Cash_Flow!H25 | D24: =D23+C24 | E24: =Assumptions!$D$93 | F24: =IF(D24>=E24,"OK","BREACH")
B25: 5 | C25: =Cash_Flow!I25 | D25: =D24+C25 | E25: =Assumptions!$D$93 | F25: =IF(D25>=E25,"OK","BREACH")
B26: 6 | C26: =Cash_Flow!J25 | D26: =D25+C26 | E26: =Assumptions!$D$93 | F26: =IF(D26>=E26,"OK","BREACH")
B27: 7 | C27: =Cash_Flow!K25 | D27: =D26+C27 | E27: =Assumptions!$D$93 | F27: =IF(D27>=E27,"OK","BREACH")
B28: 8 | C28: =Cash_Flow!L25 | D28: =D27+C28 | E28: =Assumptions!$D$93 | F28: =IF(D28>=E28,"OK","BREACH")
B29: 9 | C29: =Cash_Flow!M25 | D29: =D28+C29 | E29: =Assumptions!$D$93 | F29: =IF(D29>=E29,"OK","BREACH")
B30: 10 | C30: =Cash_Flow!N25 | D30: =D29+C30 | E30: =Assumptions!$D$93 | F30: =IF(D30>=E30,"OK","BREACH")
B32: Minimum liquidity over hold | D32: =MIN(D20:D30)
B33: Liquidity runway at trough (months of debt service) | D33: =D32/(D6/12)

Sheet Tax
B2: TAX SCHEDULE
B3: Period | D3: 0 | E3: 1 | F3: 2 | G3: 3 | H3: 4 | I3: 5 | J3: 6 | K3: 7 | L3: 8 | M3: 9 | N3: 10
B4: Year | D4: =Assumptions!$D$6+0 | E4: =Assumptions!$D$6+1 | F4: =Assumptions!$D$6+2 | G4: =Assumptions!$D$6+3 | H4: =Assumptions!$D$6+4 | I4: =Assumptions!$D$6+5 | J4: =Assumptions!$D$6+6 | K4: =Assumptions!$D$6+7 | L4: =Assumptions!$D$6+8 | M4: =Assumptions!$D$6+9 | N4: =Assumptions!$D$6+10
B5: EBITDA (from OpEx_CapEx) | D5: =OpEx_CapEx!D18 | E5: =OpEx_CapEx!E18 | F5: =OpEx_CapEx!F18 | G5: =OpEx_CapEx!G18 | H5: =OpEx_CapEx!H18 | I5: =OpEx_CapEx!I18 | J5: =OpEx_CapEx!J18 | K5: =OpEx_CapEx!K18 | ... N5: =OpEx_CapEx!N18
B6: Less: Interest expense | D6: =Debt!D10 | E6: =Debt!E10 | F6: =Debt!F10 | G6: =Debt!G10 | H6: =Debt!H10 | I6: =Debt!I10 | J6: =Debt!J10 | K6: =Debt!K10 | ... N6: =Debt!N10
B7: Less: Depreciation proxy (CapEx) | D7: =OpEx_CapEx!D23 | E7: =OpEx_CapEx!E23 | F7: =OpEx_CapEx!F23 | G7: =OpEx_CapEx!G23 | H7: =OpEx_CapEx!H23 | I7: =OpEx_CapEx!I23 | J7: =OpEx_CapEx!J23 | K7: =OpEx_CapEx!K23 | ... N7: =OpEx_CapEx!N23
B8: Earnings before tax (EBT) | D8: =D5+D6+D7 | E8: =E5+E6+E7 | F8: =F5+F6+F7 | G8: =G5+G6+G7 | H8: =H5+H6+H7 | I8: =I5+I6+I7 | J8: =J5+J6+J7 | K8: =K5+K6+K7 | ... N8: =N5+N6+N7
B9: Zakat (on shielded base = equity × (1−haircut)) | D9: =-Assumptions!$D$77*Assumptions!$D$57*Timeline!D5 | E9: =-Assumptions!$D$77*Assumptions!$D$57*Timeline!E5 | F9: =-Assumptions!$D$77*Assumptions!$D$57*Timeline!F5 | G9: =-Assumptions!$D$77*Assumptions!$D$57*Timeline!G5 | H9: =-Assumptions!$D$77*Assumptions!$D$57*Timeline!H5 | I9: =-Assumptions!$D$77*Assumptions!$D$57*Timeline!I5 | J9: =-Assumptions!$D$77*Assumptions!$D$57*Timeline!J5 | K9: =-Assumptions!$D$77*Assumptions!$D$57*Timeline!K5 | ... N9: =-Assumptions!$D$77*Assumptions!$D$57*Timeline!N5
B10: Corporate tax (on positive EBT) | D10: =-MAX(D8,0)*Assumptions!$D$58*Timeline!D5 | E10: =-MAX(E8,0)*Assumptions!$D$58*Timeline!E5 | F10: =-MAX(F8,0)*Assumptions!$D$58*Timeline!F5 | G10: =-MAX(G8,0)*Assumptions!$D$58*Timeline!G5 | H10: =-MAX(H8,0)*Assumptions!$D$58*Timeline!H5 | I10: =-MAX(I8,0)*Assumptions!$D$58*Timeline!I5 | J10: =-MAX(J8,0)*Assumptions!$D$58*Timeline!J5 | K10: =-MAX(K8,0)*Assumptions!$D$58*Timeline!K5 | ... N10: =-MAX(N8,0)*Assumptions!$D$58*Timeline!N5
B11: Withholding tax on equity distributions | D11: =-MAX(D8+D9+D10,0)*Assumptions!$D$59*Timeline!D5 | E11: =-MAX(E8+E9+E10,0)*Assumptions!$D$59*Timeline!E5 | F11: =-MAX(F8+F9+F10,0)*Assumptions!$D$59*Timeline!F5 | G11: =-MAX(G8+G9+G10,0)*Assumptions!$D$59*Timeline!G5 | H11: =-MAX(H8+H9+H10,0)*Assumptions!$D$59*Timeline!H5 | I11: =-MAX(I8+I9+I10,0)*Assumptions!$D$59*Timeline!I5 | J11: =-MAX(J8+J9+J10,0)*Assumptions!$D$59*Timeline!J5 | K11: =-MAX(K8+K9+K10,0)*Assumptions!$D$59*Timeline!K5 | ... N11: =-MAX(N8+N9+N10,0)*Assumptions!$D$59*Timeline!N5
B12: TOTAL TAX (negative = cash out) | D12: =D9+D10+D11 | E12: =E9+E10+E11 | F12: =F9+F10+F11 | G12: =G9+G10+G11 | H12: =H9+H10+H11 | I12: =I9+I10+I11 | J12: =J9+J10+J11 | K12: =K9+K10+K11 | ... N12: =N9+N10+N11
B13: Disposal tax (one-off at exit) | D13: =-DCF!D9*Assumptions!$D$60 | E13: =-DCF!E9*Assumptions!$D$60 | F13: =-DCF!F9*Assumptions!$D$60 | G13: =-DCF!G9*Assumptions!$D$60 | H13: =-DCF!H9*Assumptions!$D$60 | I13: =-DCF!I9*Assumptions!$D$60 | J13: =-DCF!J9*Assumptions!$D$60 | K13: =-DCF!K9*Assumptions!$D$60 | ... N13: =-DCF!N9*Assumptions!$D$60

Sheet Cash_Flow
B2: CASH FLOW STATEMENT (Project & Equity)
B3: Period | D3: 0 | E3: 1 | F3: 2 | G3: 3 | H3: 4 | I3: 5 | J3: 6 | K3: 7 | L3: 8 | M3: 9 | N3: 10
B4: Year | D4: =Assumptions!$D$6+0 | E4: =Assumptions!$D$6+1 | F4: =Assumptions!$D$6+2 | G4: =Assumptions!$D$6+3 | H4: =Assumptions!$D$6+4 | I4: =Assumptions!$D$6+5 | J4: =Assumptions!$D$6+6 | K4: =Assumptions!$D$6+7 | L4: =Assumptions!$D$6+8 | M4: =Assumptions!$D$6+9 | N4: =Assumptions!$D$6+10
B5: UNLEVERED (PROJECT) CASH FLOW
B6: Revenue (EGI) | D6: =Revenue!D7 | E6: =Revenue!E7 | F6: =Revenue!F7 | G6: =Revenue!G7 | H6: =Revenue!H7 | I6: =Revenue!I7 | J6: =Revenue!J7 | K6: =Revenue!K7 | ... N6: =Revenue!N7
B7: Operating expenses | D7: =OpEx_CapEx!D8 | E7: =OpEx_CapEx!E8 | F7: =OpEx_CapEx!F8 | G7: =OpEx_CapEx!G8 | H7: =OpEx_CapEx!H8 | I7: =OpEx_CapEx!I8 | J7: =OpEx_CapEx!J8 | K7: =OpEx_CapEx!K8 | ... N7: =OpEx_CapEx!N8
B8: NOI | D8: =OpEx_CapEx!D9 | E8: =OpEx_CapEx!E9 | F8: =OpEx_CapEx!F9 | G8: =OpEx_CapEx!G9 | H8: =OpEx_CapEx!H9 | I8: =OpEx_CapEx!I9 | J8: =OpEx_CapEx!J9 | K8: =OpEx_CapEx!K9 | ... N8: =OpEx_CapEx!N9
B9: Corporate costs | D9: =OpEx_CapEx!D17 | E9: =OpEx_CapEx!E17 | F9: =OpEx_CapEx!F17 | G9: =OpEx_CapEx!G17 | H9: =OpEx_CapEx!H17 | I9: =OpEx_CapEx!I17 | J9: =OpEx_CapEx!J17 | K9: =OpEx_CapEx!K17 | ... N9: =OpEx_CapEx!N17
B10: EBITDA | D10: =OpEx_CapEx!D18 | E10: =OpEx_CapEx!E18 | F10: =OpEx_CapEx!F18 | G10: =OpEx_CapEx!G18 | H10: =OpEx_CapEx!H18 | I10: =OpEx_CapEx!I18 | J10: =OpEx_CapEx!J18 | K10: =OpEx_CapEx!K18 | ... N10: =OpEx_CapEx!N18
B11: CapEx (maintenance + refurb) | D11: =OpEx_CapEx!D23 | E11: =OpEx_CapEx!E23 | F11: =OpEx_CapEx!F23 | G11: =OpEx_CapEx!G23 | H11: =OpEx_CapEx!H23 | I11: =OpEx_CapEx!I23 | J11: =OpEx_CapEx!J23 | K11: =OpEx_CapEx!K23 | ... N11: =OpEx_CapEx!N23
B12: Acquisition outflow (Y0) | D12: =-Assumptions!$D$16 | E12: 0 | F12: 0 | G12: 0 | H12: 0 | I12: 0 | J12: 0 | K12: 0 | L12: 0 | M12: 0 | N12: 0
B13: Exit value net of disposal costs (Y_exit) | D13: =IF(0=Assumptions!$D$7,DCF!D10,0) | E13: =IF(1=Assumptions!$D$7,DCF!E10,0) | F13: =IF(2=Assumptions!$D$7,DCF!F10,0) | G13: =IF(3=Assumptions!$D$7,DCF!G10,0) | H13: =IF(4=Assumptions!$D$7,DCF!H10,0) | I13: =IF(5=Assumptions!$D$7,DCF!I10,0) | J13: =IF(6=Assumptions!$D$7,DCF!J10,0) | K13: =IF(7=Assumptions!$D$7,DCF!K10,0) | L13: =IF(8=Assumptions!$D$7,DCF!L10,0) | M13: =IF(9=Assumptions!$D$7,DCF!M10,0) | N13: =IF(10=Assumptions!$D$7,DCF!N10,0)
B14: Disposal tax (Y_exit) | D14: =Tax!D13 | E14: =Tax!E13 | F14: =Tax!F13 | G14: =Tax!G13 | H14: =Tax!H13 | I14: =Tax!I13 | J14: =Tax!J13 | K14: =Tax!K13 | ... N14: =Tax!N13
B15: PROJECT FREE CASH FLOW (unlevered) | D15: =D10+D11+D12+D13+D14 | E15: =E10+E11+E12+E13+E14 | F15: =F10+F11+F12+F13+F14 | G15: =G10+G11+G12+G13+G14 | H15: =H10+H11+H12+H13+H14 | I15: =I10+I11+I12+I13+I14 | J15: =J10+J11+J12+J13+J14 | K15: =K10+K11+K12+K13+K14 | ... N15: =N10+N11+N12+N13+N14
B17: EQUITY (LEVERED) CASH FLOW
B18: Project FCF | D18: =D15 | E18: =E15 | F18: =F15 | G18: =G15 | H18: =H15 | I18: =I15 | J18: =J15 | K18: =K15 | ... N18: =N15
B19: Debt drawdown | D19: =Debt!D6 | E19: =Debt!E6 | F19: =Debt!F6 | G19: =Debt!G6 | H19: =Debt!H6 | I19: =Debt!I6 | J19: =Debt!J6 | K19: =Debt!K6 | ... N19: =Debt!N6
B20: Arrangement fee | D20: =Debt!D11 | E20: =Debt!E11 | F20: =Debt!F11 | G20: =Debt!G11 | H20: =Debt!H11 | I20: =Debt!I11 | J20: =Debt!J11 | K20: =Debt!K11 | ... N20: =Debt!N11
B21: Interest expense | D21: =Debt!D10 | E21: =Debt!E10 | F21: =Debt!F10 | G21: =Debt!G10 | H21: =Debt!H10 | I21: =Debt!I10 | J21: =Debt!J10 | K21: =Debt!K10 | ... N21: =Debt!N10
B22: Scheduled principal | D22: =Debt!D7 | E22: =Debt!E7 | F22: =Debt!F7 | G22: =Debt!G7 | H22: =Debt!H7 | I22: =Debt!I7 | J22: =Debt!J7 | K22: =Debt!K7 | ... N22: =Debt!N7
B23: Bullet repayment at exit | D23: =Debt!D8 | E23: =Debt!E8 | F23: =Debt!F8 | G23: =Debt!G8 | H23: =Debt!H8 | I23: =Debt!I8 | J23: =Debt!J8 | K23: =Debt!K8 | ... N23: =Debt!N8
B24: Income taxes (zakat + corp + WHT) | D24: =Tax!D12 | E24: =Tax!E12 | F24: =Tax!F12 | G24: =Tax!G12 | H24: =Tax!H12 | I24: =Tax!I12 | J24: =Tax!J12 | K24: =Tax!K12 | ... N24: =Tax!N12
B25: EQUITY FREE CASH FLOW | D25: =D18+D19+D20+D21+D22+D23+D24+Refinance!D29 | E25: =E18+E19+E20+E21+E22+E23+E24+Refinance!E29 | F25: =F18+F19+F20+F21+F22+F23+F24+Refinance!F29 | G25: =G18+G19+G20+G21+G22+G23+G24+Refinance!G29 | H25: =H18+H19+H20+H21+H22+H23+H24+Refinance!H29 | I25: =I18+I19+I20+I21+I22+I23+I24+Refinance!I29 | J25: =J18+J19+J20+J21+J22+J23+J24+Refinance!J29 | K25: =K18+K19+K20+K21+K22+K23+K24+Refinance!K29 | ... N25: =N18+N19+N20+N21+N22+N23+N24+Refinance!N29
B26: Cumulative equity FCF | D26: =D25 | E26: =D26+E25 | F26: =E26+F25 | G26: =F26+G25 | H26: =G26+H25 | I26: =H26+I25 | J26: =I26+J25 | K26: =J26+K25 | L26: =K26+L25 | ... N26: =M26+N25
B27: o/w refi cash (memo) | D27: =Refinance!D29 | E27: =Refinance!E29 | F27: =Refinance!F29 | G27: =Refinance!G29 | H27: =Refinance!H29 | I27: =Refinance!I29 | J27: =Refinance!J29 | K27: =Refinance!K29 | ... N27: =Refinance!N29

Sheet DCF
B2: DCF VALUATION (Unlevered) — Exit-Cap method, no double-count
B3: Period | D3: 0 | E3: 1 | F3: 2 | G3: 3 | H3: 4 | I3: 5 | J3: 6 | K3: 7 | L3: 8 | M3: 9 | N3: 10
B4: Year | D4: =Assumptions!$D$6+0 | E4: =Assumptions!$D$6+1 | F4: =Assumptions!$D$6+2 | G4: =Assumptions!$D$6+3 | H4: =Assumptions!$D$6+4 | I4: =Assumptions!$D$6+5 | J4: =Assumptions!$D$6+6 | K4: =Assumptions!$D$6+7 | L4: =Assumptions!$D$6+8 | M4: =Assumptions!$D$6+9 | N4: =Assumptions!$D$6+10
B5: EXIT VALUE BUILD (forward NOI method)
B6: Forward NOI (Y+1 of exit year) | D6: =IF(0=Assumptions!$D$7,OpEx_CapEx!D9*(1+Assumptions!$D$20/Assumptions!$D$21),0) | E6: =IF(1=Assumptions!$D$7,OpEx_CapEx!E9*(1+Assumptions!$D$20/Assumptions!$D$21),0) | F6: =IF(2=Assumptions!$D$7,OpEx_CapEx!F9*(1+Assumptions!$D$20/Assumptions!$D$21),0) | G6: =IF(3=Assumptions!$D$7,OpEx_CapEx!G9*(1+Assumptions!$D$20/Assumptions!$D$21),0) | H6: =IF(4=Assumptions!$D$7,OpEx_CapEx!H9*(1+Assumptions!$D$20/Assumptions!$D$21),0) | I6: =IF(5=Assumptions!$D$7,OpEx_CapEx!I9*(1+Assumptions!$D$20/Assumptions!$D$21),0) | J6: =IF(6=Assumptions!$D$7,OpEx_CapEx!J9*(1+Assumptions!$D$20/Assumptions!$D$21),0) | K6: =IF(7=Assumptions!$D$7,OpEx_CapEx!K9*(1+Assumptions!$D$20/Assumptions!$D$21),0) | L6: =IF(8=Assumptions!$D$7,OpEx_CapEx!L9*(1+Assumptions!$D$20/Assumptions!$D$21),0) | M6: =IF(9=Assumptions!$D$7,OpEx_CapEx!M9*(1+Assumptions!$D$20/Assumptions!$D$21),0) | N6: =IF(10=Assumptions!$D$7,OpEx_CapEx!N9*(1+Assumptions!$D$20/Assumptions!$D$21),0)
B7: Exit cap rate | D7: =IF(0=Assumptions!$D$7,Assumptions!$D$51,0) | E7: =IF(1=Assumptions!$D$7,Assumptions!$D$51,0) | F7: =IF(2=Assumptions!$D$7,Assumptions!$D$51,0) | G7: =IF(3=Assumptions!$D$7,Assumptions!$D$51,0) | H7: =IF(4=Assumptions!$D$7,Assumptions!$D$51,0) | I7: =IF(5=Assumptions!$D$7,Assumptions!$D$51,0) | J7: =IF(6=Assumptions!$D$7,Assumptions!$D$51,0) | K7: =IF(7=Assumptions!$D$7,Assumptions!$D$51,0) | L7: =IF(8=Assumptions!$D$7,Assumptions!$D$51,0) | M7: =IF(9=Assumptions!$D$7,Assumptions!$D$51,0) | N7: =IF(10=Assumptions!$D$7,Assumptions!$D$51,0)
B8: Disposal costs % (broker + legal + other) | D8: =IF(0=Assumptions!$D$7,Assumptions!$D$52+Assumptions!$D$53+Assumptions!$D$54,0) | E8: =IF(1=Assumptions!$D$7,Assumptions!$D$52+Assumptions!$D$53+Assumptions!$D$54,0) | F8: =IF(2=Assumptions!$D$7,Assumptions!$D$52+Assumptions!$D$53+Assumptions!$D$54,0) | G8: =IF(3=Assumptions!$D$7,Assumptions!$D$52+Assumptions!$D$53+Assumptions!$D$54,0) | H8: =IF(4=Assumptions!$D$7,Assumptions!$D$52+Assumptions!$D$53+Assumptions!$D$54,0) | I8: =IF(5=Assumptions!$D$7,Assumptions!$D$52+Assumptions!$D$53+Assumptions!$D$54,0) | J8: =IF(6=Assumptions!$D$7,Assumptions!$D$52+Assumptions!$D$53+Assumptions!$D$54,0) | K8: =IF(7=Assumptions!$D$7,Assumptions!$D$52+Assumptions!$D$53+Assumptions!$D$54,0) | L8: =IF(8=Assumptions!$D$7,Assumptions!$D$52+Assumptions!$D$53+Assumptions!$D$54,0) | M8: =IF(9=Assumptions!$D$7,Assumptions!$D$52+Assumptions!$D$53+Assumptions!$D$54,0) | N8: =IF(10=Assumptions!$D$7,Assumptions!$D$52+Assumptions!$D$53+Assumptions!$D$54,0)
B9: GROSS EXIT VALUE = Forward NOI / Exit Cap | D9: =IFERROR(IF(D7=0,0,D6/D7),0) | E9: =IFERROR(IF(E7=0,0,E6/E7),0) | F9: =IFERROR(IF(F7=0,0,F6/F7),0) | G9: =IFERROR(IF(G7=0,0,G6/G7),0) | H9: =IFERROR(IF(H7=0,0,H6/H7),0) | I9: =IFERROR(IF(I7=0,0,I6/I7),0) | J9: =IFERROR(IF(J7=0,0,J6/J7),0) | K9: =IFERROR(IF(K7=0,0,K6/K7),0) | ... N9: =IFERROR(IF(N7=0,0,N6/N7),0)
B10: NET EXIT VALUE (gross − disposal costs) | D10: =D9*(1-D8) | E10: =E9*(1-E8) | F10: =F9*(1-F8) | G10: =G9*(1-G8) | H10: =H9*(1-H8) | I10: =I9*(1-I8) | J10: =J9*(1-J8) | K10: =K9*(1-K8) | ... N10: =N9*(1-N8)
B12: UNLEVERED DCF — PROJECT LEVEL
B13: Project FCF (unlevered) | D13: =Cash_Flow!D15 | E13: =Cash_Flow!E15 | F13: =Cash_Flow!F15 | G13: =Cash_Flow!G15 | H13: =Cash_Flow!H15 | I13: =Cash_Flow!I15 | J13: =Cash_Flow!J15 | K13: =Cash_Flow!K15 | ... N13: =Cash_Flow!N15
B14: Discount factor @ WACC | D14: =1/(1+Assumptions!$D$68)^0 | E14: =1/(1+Assumptions!$D$68)^1 | F14: =1/(1+Assumptions!$D$68)^2 | G14: =1/(1+Assumptions!$D$68)^3 | H14: =1/(1+Assumptions!$D$68)^4 | I14: =1/(1+Assumptions!$D$68)^5 | J14: =1/(1+Assumptions!$D$68)^6 | K14: =1/(1+Assumptions!$D$68)^7 | L14: =1/(1+Assumptions!$D$68)^8 | M14: =1/(1+Assumptions!$D$68)^9 | N14: =1/(1+Assumptions!$D$68)^10
B15: PV of FCF | D15: =D13*D14 | E15: =E13*E14 | F15: =F13*F14 | G15: =G13*G14 | H15: =H13*H14 | I15: =I13*I14 | J15: =J13*J14 | K15: =K13*K14 | ... N15: =N13*N14
B17: NPV (Project) = Σ PV(Project FCF) | D17: =SUM(D15:N15)
B18: Enterprise Value (EV) = NPV + Initial Outflow Reversed | D18: =D17-Cash_Flow!D12 | F18: Note: EV here = sum of PV future cash flows excluding acquisition.
B20: LEVERED DCF — EQUITY LEVEL
B21: Equity FCF (levered) | D21: =Cash_Flow!D25 | E21: =Cash_Flow!E25 | F21: =Cash_Flow!F25 | G21: =Cash_Flow!G25 | H21: =Cash_Flow!H25 | I21: =Cash_Flow!I25 | J21: =Cash_Flow!J25 | K21: =Cash_Flow!K25 | ... N21: =Cash_Flow!N25
B22: Discount factor @ Cost of Equity | D22: =1/(1+Assumptions!$D$66)^0 | E22: =1/(1+Assumptions!$D$66)^1 | F22: =1/(1+Assumptions!$D$66)^2 | G22: =1/(1+Assumptions!$D$66)^3 | H22: =1/(1+Assumptions!$D$66)^4 | I22: =1/(1+Assumptions!$D$66)^5 | J22: =1/(1+Assumptions!$D$66)^6 | K22: =1/(1+Assumptions!$D$66)^7 | L22: =1/(1+Assumptions!$D$66)^8 | M22: =1/(1+Assumptions!$D$66)^9 | N22: =1/(1+Assumptions!$D$66)^10
B23: PV of Equity FCF | D23: =D21*D22 | E23: =E21*E22 | F23: =F21*F22 | G23: =G21*G22 | H23: =H21*H22 | I23: =I21*I22 | J23: =J21*J22 | K23: =K21*K22 | ... N23: =N21*N22
B25: NPV (Equity) = Σ PV(Equity FCF) | D25: =SUM(D23:N23)

Sheet Returns
B2: RETURN METRICS
B4: PROFITABILITY
B5: Project IRR (unlevered) | D5: =IFERROR(IRR(Cash_Flow!D15:N15),0)
B6: Equity IRR (levered, post-tax) | D6: =IFERROR(IRR(Cash_Flow!D25:N25),0)
B7: WACC (hurdle for project) | D7: =Assumptions!$D$68
B8: Hurdle rate (equity) | D8: =Assumptions!$D$71
B9: Project IRR vs WACC (gap) | D9: =D5-D7
B10: Equity IRR vs Hurdle (gap) | D10: =D6-D8
B11: NPV @ WACC (Project) | D11: =DCF!D17
B12: NPV @ Ke (Equity) | D12: =DCF!D25
B14: EQUITY MULTIPLES & PAYBACK
B15: Initial equity invested (Y0 only) | D15: =ABS(Cash_Flow!D25)
B16: Sum of all positive equity distributions (Y0 excluded) | D16: =SUMIF(Cash_Flow!D25:N25,">0")
B17: Distributions MOIC (positive CFs / initial equity) | D17: =IFERROR(D16/D15,0)
B18: MOIC target | D18: =Assumptions!$D$72
B19: Payback period (years until cumul. equity FCF ≥ 0) | D19: =IFERROR(MATCH(TRUE(),INDEX(Cash_Flow!E26:N26>=0,0),0),"Beyond exit")
B21: CURRENT-YEAR METRICS (Year 1)
B22: Cash-on-Cash (Y1 equity FCF ex arrangement fee / equity) | D22: =IFERROR((Cash_Flow!E25-Debt!E11)/Assumptions!$D$48,0)
B23: Yield on cost (Y1 NOI / Total Cost) | D23: =IFERROR(OpEx_CapEx!E9/Assumptions!$D$16,0)
B24: Entry cap rate implied (Y1 NOI / Purchase price) | D24: =IFERROR(OpEx_CapEx!E9/Assumptions!$D$11,0)
B26: CREDIT METRICS
B27: Initial LTV (Debt / Total cost) | D27: =Assumptions!$D$47/Assumptions!$D$16
B28: Min DSCR over life | D28: =IFERROR(MIN(Debt!E16:N16),0)
B29: Avg DSCR | D29: =IFERROR(AVERAGE(Debt!E16:M16),0)
B30: Avg debt yield (NOI / Debt outstanding) | D30: =IFERROR(AVERAGE(Debt!E18:M18),0)
B31: Min Interest Coverage | D31: =IFERROR(MIN(Debt!E15:N15),0)
B33: BREAK-EVEN ANALYSIS
B34: Break-even vacancy (NOI covers debt service) | D34: =IFERROR(1-ABS(Debt!E12)/(Assumptions!$D$19*(1-Assumptions!$D$25-Assumptions!$D$26)),0)
B35: NOI cushion vs debt service (Y1) | D35: =OpEx_CapEx!E9-ABS(Debt!E12)
B36: Min DSCR excl. bullet year (Y1–Y9) | D36: =MIN(Debt!E16:M16)

Sheet Scenarios
B2: SCENARIO ANALYSIS — Base / Downside / Severe / Upside
B3: Scenarios shock key drivers vs base. Compare equity IRR, NPV, DSCR, MOIC.
B5: Driver | C5: Base | D5: Downside | E5: Severe | F5: Upside
B6: Revenue growth (Δ pp) | C6: 0 | D6: -0.01 | E6: -0.03 | F6: 0.01
B7: Y1 vacancy (Δ pp) | C7: 0 | D7: 0.05 | E7: 0.15 | F7: -0.03
B8: OpEx (Δ % multiplier) | C8: 0 | D8: 0.1 | E8: 0.25 | F8: -0.05
B9: Exit cap rate (Δ bps) | C9: 0 | D9: 50 | E9: 150 | F9: -25
B10: Cost of debt (Δ bps) | C10: 0 | D10: 100 | E10: 250 | F10: -25
B12: SCENARIO IMPACT (estimated, using single-factor shocks via Sensitivity sheet)
B13: See Sensitivity sheet for two-way matrices on each driver.
B14: For full multi-factor scenarios, copy the workbook, change the BLUE inputs on Assumptions, and re-read Returns.
B16: Scenario operating instructions:
B17: 1. To run a scenario, change ONLY the blue cells on the Assumptions sheet.
B18: 2. The whole model re-flows. Read updated metrics on Returns and Dashboard.
B19: 3. To compare side-by-side, save the workbook under each scenario name (e.g. v4_Base.xlsx).
B20: 4. For automated multi-scenario tables, see the Sensitivity sheet which uses one-way shocks.

Sheet Scenario_Engine
B2: SCENARIO ENGINE — full recalculation across cases
B3: Each case applies stress shocks from Assumptions §14 to the base build. Computes NOI, debt service, equity IRR, NPV, MOIC, DSCR.
B5: Metric | C5: Base | D5: Downside | E5: Severe | F5: Stress | G5: Upside
B6: Adjusted revenue growth | C6: =Assumptions!$D$20+Assumptions!C98 | D6: =Assumptions!$D$20+Assumptions!D98 | E6: =Assumptions!$D$20+Assumptions!E98 | F6: =Assumptions!$D$20+Assumptions!F98 | G6: =Assumptions!$D$20+Assumptions!G98
B7: Adjusted vacancy | C7: =Assumptions!$D$22+Assumptions!C99 | D7: =Assumptions!$D$22+Assumptions!D99 | E7: =Assumptions!$D$22+Assumptions!E99 | F7: =Assumptions!$D$22+Assumptions!F99 | G7: =Assumptions!$D$22+Assumptions!G99
B8: OpEx multiplier | C8: =Assumptions!C100 | D8: =Assumptions!D100 | E8: =Assumptions!E100 | F8: =Assumptions!F100 | G8: =Assumptions!G100
B9: Adjusted exit cap | C9: =Assumptions!$D$51+Assumptions!C101/10000 | D9: =Assumptions!$D$51+Assumptions!D101/10000 | E9: =Assumptions!$D$51+Assumptions!E101/10000 | F9: =Assumptions!$D$51+Assumptions!F101/10000 | G9: =Assumptions!$D$51+Assumptions!G101/10000
B10: Adjusted cost of debt | C10: =Assumptions!$D$42+Assumptions!C102/10000 | D10: =Assumptions!$D$42+Assumptions!D102/10000 | E10: =Assumptions!$D$42+Assumptions!E102/10000 | F10: =Assumptions!$D$42+Assumptions!F102/10000 | G10: =Assumptions!$D$42+Assumptions!G102/10000
B11: Refi failure flag (1=fail) | C11: =Assumptions!C103 | D11: =Assumptions!D103 | E11: =Assumptions!E103 | F11: =Assumptions!F103 | G11: =Assumptions!G103
B12: Cost overrun multiplier | C12: =1+Assumptions!C105 | D12: =1+Assumptions!D105 | E12: =1+Assumptions!E105 | F12: =1+Assumptions!F105 | G12: =1+Assumptions!G105
B13: Adjusted total cost | C13: =Assumptions!$D$16*C12 | D13: =Assumptions!$D$16*D12 | E13: =Assumptions!$D$16*E12 | F13: =Assumptions!$D$16*F12 | G13: =Assumptions!$D$16*G12
B15: Y1 EGI (stressed) | C15: =Assumptions!$D$19*(1-C7) | D15: =Assumptions!$D$19*(1-D7) | E15: =Assumptions!$D$19*(1-E7) | F15: =Assumptions!$D$19*(1-F7) | G15: =Assumptions!$D$19*(1-G7)
B16: Y1 asset NOI (stressed) | C16: =C15*(1-Assumptions!$D$25*C8-Assumptions!$D$26) | D16: =D15*(1-Assumptions!$D$25*D8-Assumptions!$D$26) | E16: =E15*(1-Assumptions!$D$25*E8-Assumptions!$D$26) | F16: =F15*(1-Assumptions!$D$25*F8-Assumptions!$D$26) | G16: =G15*(1-Assumptions!$D$25*G8-Assumptions!$D$26)
B17: NPV (Project) — stressed | C17: =-C13+((C16*((1+C6/2)^Assumptions!$D$7+1)/2)-(C15*Assumptions!$D$36)-(Assumptions!$D$77*Assumptions!$D$57))*(1-(1+Assumptions!$D$68)^-Assumptions!$D$7)/Assumptions!$D$68+(((C16*(1+C6/2)^Assumptions!$D$7)*(1+C6)/C9*(1-0.03))/(1+Assumptions!$D$68)^Assumptions!$D$7) | D17: =-D13+((D16*((1+D6/2)^Assumptions!$D$7+1)/2)-(D15*Assumptions!$D$36)-(Assumptions!$D$77*Assumptions!$D$57))*(1-(1+Assumptions!$D$68)^-Assumptions!$D$7)/Assumptions!$D$68+(((D16*(1+D6/2)^Assumptions!$D$7)*(1+D6)/D9*(1-0.03))/(1+Assumptions!$D$68)^Assumptions!$D$7) | E17: =-E13+((E16*((1+E6/2)^Assumptions!$D$7+1)/2)-(E15*Assumptions!$D$36)-(Assumptions!$D$77*Assumptions!$D$57))*(1-(1+Assumptions!$D$68)^-Assumptions!$D$7)/Assumptions!$D$68+(((E16*(1+E6/2)^Assumptions!$D$7)*(1+E6)/E9*(1-0.03))/(1+Assumptions!$D$68)^Assumptions!$D$7) | F17: =-F13+((F16*((1+F6/2)^Assumptions!$D$7+1)/2)-(F15*Assumptions!$D$36)-(Assumptions!$D$77*Assumptions!$D$57))*(1-(1+Assumptions!$D$68)^-Assumptions!$D$7)/Assumptions!$D$68+(((F16*(1+F6/2)^Assumptions!$D$7)*(1+F6)/F9*(1-0.03))/(1+Assumptions!$D$68)^Assumptions!$D$7) | G17: =-G13+((G16*((1+G6/2)^Assumptions!$D$7+1)/2)-(G15*Assumptions!$D$36)-(Assumptions!$D$77*Assumptions!$D$57))*(1-(1+Assumptions!$D$68)^-Assumptions!$D$7)/Assumptions!$D$68+(((G16*(1+G6/2)^Assumptions!$D$7)*(1+G6)/G9*(1-0.03))/(1+Assumptions!$D$68)^Assumptions!$D$7)
B18: Equity IRR (stressed, approx) | C18: =IFERROR(IF(IFERROR((Assumptions!$D$7*((C16*((1+C6/2)^Assumptions!$D$7+1)/2)-(C13*Assumptions!$D$41*C10)-(Assumptions!$D$77*Assumptions!$D$57)-(C15*Assumptions!$D$36))+IF(C11=1,(((C16*(1+C6/2)^Assumptions!$D$7)*(1+C6)/C9*(1-0.03))-(C13*Assumptions!$D$41))*0.75,(((C16*(1+C6/2)^Assumptions!$D$7)*(1+C6)/C9*(1-0.03))-(C13*Assumptions!$D$41))))/(C13*(1-Assumptions!$D$41)),0)>0,IFERROR((Assumptions!$D$7*((C16*((1+C6/2)^Assumptions!$D$7+1)/2)-(C13*Assumptions!$D$41*C10)-(Assumptions!$D$77*Assumptions!$D$57)-(C15*Assumptions!$D$36))+IF(C11=1,(((C16*(1+C6/2)^Assumptions!$D$7)*(1+C6)/C9*(1-0.03))-(C13*Assumptions!$D$41))*0.75,(((C16*(1+C6/2)^Assumptions!$D$7)*(1+C6)/C9*(1-0.03))-(C13*Assumptions!$D$41))))/(C13*(1-Assumptions!$D$41)),0)^(1/Assumptions!$D$7)-1,-1),-1) | D18: =IFERROR(IF(IFERROR((Assumptions!$D$7*((D16*((1+D6/2)^Assumptions!$D$7+1)/2)-(D13*Assumptions!$D$41*D10)-(Assumptions!$D$77*Assumptions!$D$57)-(D15*Assumptions!$D$36))+IF(D11=1,(((D16*(1+D6/2)^Assumptions!$D$7)*(1+D6)/D9*(1-0.03))-(D13*Assumptions!$D$41))*0.75,(((D16*(1+D6/2)^Assumptions!$D$7)*(1+D6)/D9*(1-0.03))-(D13*Assumptions!$D$41))))/(D13*(1-Assumptions!$D$41)),0)>0,IFERROR((Assumptions!$D$7*((D16*((1+D6/2)^Assumptions!$D$7+1)/2)-(D13*Assumptions!$D$41*D10)-(Assumptions!$D$77*Assumptions!$D$57)-(D15*Assumptions!$D$36))+IF(D11=1,(((D16*(1+D6/2)^Assumptions!$D$7)*(1+D6)/D9*(1-0.03))-(D13*Assumptions!$D$41))*0.75,(((D16*(1+D6/2)^Assumptions!$D$7)*(1+D6)/D9*(1-0.03))-(D13*Assumptions!$D$41))))/(D13*(1-Assumptions!$D$41)),0)^(1/Assumptions!$D$7)-1,-1),-1) | E18: =IFERROR(IF(IFERROR((Assumptions!$D$7*((E16*((1+E6/2)^Assumptions!$D$7+1)/2)-(E13*Assumptions!$D$41*E10)-(Assumptions!$D$77*Assumptions!$D$57)-(E15*Assumptions!$D$36))+IF(E11=1,(((E16*(1+E6/2)^Assumptions!$D$7)*(1+E6)/E9*(1-0.03))-(E13*Assumptions!$D$41))*0.75,(((E16*(1+E6/2)^Assumptions!$D$7)*(1+E6)/E9*(1-0.03))-(E13*Assumptions!$D$41))))/(E13*(1-Assumptions!$D$41)),0)>0,IFERROR((Assumptions!$D$7*((E16*((1+E6/2)^Assumptions!$D$7+1)/2)-(E13*Assumptions!$D$41*E10)-(Assumptions!$D$77*Assumptions!$D$57)-(E15*Assumptions!$D$36))+IF(E11=1,(((E16*(1+E6/2)^Assumptions!$D$7)*(1+E6)/E9*(1-0.03))-(E13*Assumptions!$D$41))*0.75,(((E16*(1+E6/2)^Assumptions!$D$7)*(1+E6)/E9*(1-0.03))-(E13*Assumptions!$D$41))))/(E13*(1-Assumptions!$D$41)),0)^(1/Assumptions!$D$7)-1,-1),-1) | F18: =IFERROR(IF(IFERROR((Assumptions!$D$7*((F16*((1+F6/2)^Assumptions!$D$7+1)/2)-(F13*Assumptions!$D$41*F10)-(Assumptions!$D$77*Assumptions!$D$57)-(F15*Assumptions!$D$36))+IF(F11=1,(((F16*(1+F6/2)^Assumptions!$D$7)*(1+F6)/F9*(1-0.03))-(F13*Assumptions!$D$41))*0.75,(((F16*(1+F6/2)^Assumptions!$D$7)*(1+F6)/F9*(1-0.03))-(F13*Assumptions!$D$41))))/(F13*(1-Assumptions!$D$41)),0)>0,IFERROR((Assumptions!$D$7*((F16*((1+F6/2)^Assumptions!$D$7+1)/2)-(F13*Assumptions!$D$41*F10)-(Assumptions!$D$77*Assumptions!$D$57)-(F15*Assumptions!$D$36))+IF(F11=1,(((F16*(1+F6/2)^Assumptions!$D$7)*(1+F6)/F9*(1-0.03))-(F13*Assumptions!$D$41))*0.75,(((F16*(1+F6/2)^Assumptions!$D$7)*(1+F6)/F9*(1-0.03))-(F13*Assumptions!$D$41))))/(F13*(1-Assumptions!$D$41)),0)^(1/Assumptions!$D$7)-1,-1),-1) | G18: =IFERROR(IF(IFERROR((Assumptions!$D$7*((G16*((1+G6/2)^Assumptions!$D$7+1)/2)-(G13*Assumptions!$D$41*G10)-(Assumptions!$D$77*Assumptions!$D$57)-(G15*Assumptions!$D$36))+IF(G11=1,(((G16*(1+G6/2)^Assumptions!$D$7)*(1+G6)/G9*(1-0.03))-(G13*Assumptions!$D$41))*0.75,(((G16*(1+G6/2)^Assumptions!$D$7)*(1+G6)/G9*(1-0.03))-(G13*Assumptions!$D$41))))/(G13*(1-Assumptions!$D$41)),0)>0,IFERROR((Assumptions!$D$7*((G16*((1+G6/2)^Assumptions!$D$7+1)/2)-(G13*Assumptions!$D$41*G10)-(Assumptions!$D$77*Assumptions!$D$57)-(G15*Assumptions!$D$36))+IF(G11=1,(((G16*(1+G6/2)^Assumptions!$D$7)*(1+G6)/G9*(1-0.03))-(G13*Assumptions!$D$41))*0.75,(((G16*(1+G6/2)^Assumptions!$D$7)*(1+G6)/G9*(1-0.03))-(G13*Assumptions!$D$41))))/(G13*(1-Assumptions!$D$41)),0)^(1/Assumptions!$D$7)-1,-1),-1)
B19: MOIC (stressed, approx) | C19: =IFERROR((Assumptions!$D$7*((C16*((1+C6/2)^Assumptions!$D$7+1)/2)-(C13*Assumptions!$D$41*C10)-(Assumptions!$D$77*Assumptions!$D$57)-(C15*Assumptions!$D$36))+IF(C11=1,(((C16*(1+C6/2)^Assumptions!$D$7)*(1+C6)/C9*(1-0.03))-(C13*Assumptions!$D$41))*0.75,(((C16*(1+C6/2)^Assumptions!$D$7)*(1+C6)/C9*(1-0.03))-(C13*Assumptions!$D$41))))/(C13*(1-Assumptions!$D$41)),0) | D19: =IFERROR((Assumptions!$D$7*((D16*((1+D6/2)^Assumptions!$D$7+1)/2)-(D13*Assumptions!$D$41*D10)-(Assumptions!$D$77*Assumptions!$D$57)-(D15*Assumptions!$D$36))+IF(D11=1,(((D16*(1+D6/2)^Assumptions!$D$7)*(1+D6)/D9*(1-0.03))-(D13*Assumptions!$D$41))*0.75,(((D16*(1+D6/2)^Assumptions!$D$7)*(1+D6)/D9*(1-0.03))-(D13*Assumptions!$D$41))))/(D13*(1-Assumptions!$D$41)),0) | E19: =IFERROR((Assumptions!$D$7*((E16*((1+E6/2)^Assumptions!$D$7+1)/2)-(E13*Assumptions!$D$41*E10)-(Assumptions!$D$77*Assumptions!$D$57)-(E15*Assumptions!$D$36))+IF(E11=1,(((E16*(1+E6/2)^Assumptions!$D$7)*(1+E6)/E9*(1-0.03))-(E13*Assumptions!$D$41))*0.75,(((E16*(1+E6/2)^Assumptions!$D$7)*(1+E6)/E9*(1-0.03))-(E13*Assumptions!$D$41))))/(E13*(1-Assumptions!$D$41)),0) | F19: =IFERROR((Assumptions!$D$7*((F16*((1+F6/2)^Assumptions!$D$7+1)/2)-(F13*Assumptions!$D$41*F10)-(Assumptions!$D$77*Assumptions!$D$57)-(F15*Assumptions!$D$36))+IF(F11=1,(((F16*(1+F6/2)^Assumptions!$D$7)*(1+F6)/F9*(1-0.03))-(F13*Assumptions!$D$41))*0.75,(((F16*(1+F6/2)^Assumptions!$D$7)*(1+F6)/F9*(1-0.03))-(F13*Assumptions!$D$41))))/(F13*(1-Assumptions!$D$41)),0) | G19: =IFERROR((Assumptions!$D$7*((G16*((1+G6/2)^Assumptions!$D$7+1)/2)-(G13*Assumptions!$D$41*G10)-(Assumptions!$D$77*Assumptions!$D$57)-(G15*Assumptions!$D$36))+IF(G11=1,(((G16*(1+G6/2)^Assumptions!$D$7)*(1+G6)/G9*(1-0.03))-(G13*Assumptions!$D$41))*0.75,(((G16*(1+G6/2)^Assumptions!$D$7)*(1+G6)/G9*(1-0.03))-(G13*Assumptions!$D$41))))/(G13*(1-Assumptions!$D$41)),0)
B20: Y1 DSCR (stressed) | C20: =C16/(Assumptions!$D$47*C10) | D20: =D16/(Assumptions!$D$47*D10) | E20: =E16/(Assumptions!$D$47*E10) | F20: =F16/(Assumptions!$D$47*F10) | G20: =G16/(Assumptions!$D$47*G10)
B21: Exit value (stressed) | C21: =(C16*(1+C6/2)^Assumptions!$D$7)*(1+C6)/C9*(1-0.03) | D21: =(D16*(1+D6/2)^Assumptions!$D$7)*(1+D6)/D9*(1-0.03) | E21: =(E16*(1+E6/2)^Assumptions!$D$7)*(1+E6)/E9*(1-0.03) | F21: =(F16*(1+F6/2)^Assumptions!$D$7)*(1+F6)/F9*(1-0.03) | G21: =(G16*(1+G6/2)^Assumptions!$D$7)*(1+G6)/G9*(1-0.03)
B22: Investment verdict | C22: =IF(C17>=0,IF(C18>=Assumptions!$D$71,"INVESTABLE","MARGINAL"),"REJECT") | D22: =IF(D17>=0,IF(D18>=Assumptions!$D$71,"INVESTABLE","MARGINAL"),"REJECT") | E22: =IF(E17>=0,IF(E18>=Assumptions!$D$71,"INVESTABLE","MARGINAL"),"REJECT") | F22: =IF(F17>=0,IF(F18>=Assumptions!$D$71,"INVESTABLE","MARGINAL"),"REJECT") | G22: =IF(G17>=0,IF(G18>=Assumptions!$D$71,"INVESTABLE","MARGINAL"),"REJECT")

Sheet Sensitivity
B2: SENSITIVITY ANALYSIS
B3: Excel two-variable data tables are not auto-generated by Python. To populate, use Data > What-If > Data Table on the matrices below.
B5: EXIT CAP RATE SENSITIVITY (Equity IRR)
B6: Equity IRR (base case) | D6: =Returns!D6
B8: Exit cap rate Δ: | C8: -0.01 | D8: -0.005 | E8: 0 | F8: 0.005 | G8: 0.01 | H8: 0.015
B9: Resulting exit cap | C9: =Assumptions!$D$51+C8 | D9: =Assumptions!$D$51+D8 | E9: =Assumptions!$D$51+E8 | F9: =Assumptions!$D$51+F8 | G9: =Assumptions!$D$51+G8 | H9: =Assumptions!$D$51+H8
B10: Gross exit value (SAR) | C10: =DCF!N6/C9 | D10: =DCF!N6/D9 | E10: =DCF!N6/E9 | F10: =DCF!N6/F9 | G10: =DCF!N6/G9 | H10: =DCF!N6/H9
B11: Net exit value (after disposal costs) | C11: =C10*(1-Assumptions!$D$52-Assumptions!$D$53-Assumptions!$D$54) | D11: =D10*(1-Assumptions!$D$52-Assumptions!$D$53-Assumptions!$D$54) | E11: =E10*(1-Assumptions!$D$52-Assumptions!$D$53-Assumptions!$D$54) | F11: =F10*(1-Assumptions!$D$52-Assumptions!$D$53-Assumptions!$D$54) | G11: =G10*(1-Assumptions!$D$52-Assumptions!$D$53-Assumptions!$D$54) | H11: =H10*(1-Assumptions!$D$52-Assumptions!$D$53-Assumptions!$D$54)
B12: Δ equity proceeds at exit | C12: =C11-DCF!N10 | D12: =D11-DCF!N10 | E12: =E11-DCF!N10 | F12: =F11-DCF!N10 | G12: =G11-DCF!N10 | H12: =H11-DCF!N10
B14: VACANCY SENSITIVITY (Y1 NOI)
B15: Vacancy rate | C15: 0 | D15: 0.025 | E15: 0.05 | F15: 0.1 | G15: 0.15 | H15: 0.2
B16: Y1 EGI | C16: =Assumptions!$D$19*(1-C15) | D16: =Assumptions!$D$19*(1-D15) | E16: =Assumptions!$D$19*(1-E15) | F16: =Assumptions!$D$19*(1-F15) | G16: =Assumptions!$D$19*(1-G15) | H16: =Assumptions!$D$19*(1-H15)
B17: Y1 NOI (approx) | C17: =C16*(1-Assumptions!$D$25-Assumptions!$D$26) | D17: =D16*(1-Assumptions!$D$25-Assumptions!$D$26) | E17: =E16*(1-Assumptions!$D$25-Assumptions!$D$26) | F17: =F16*(1-Assumptions!$D$25-Assumptions!$D$26) | G17: =G16*(1-Assumptions!$D$25-Assumptions!$D$26) | H17: =H16*(1-Assumptions!$D$25-Assumptions!$D$26)
B18: Y1 DSCR (approx) | C18: =IFERROR(C17/ABS(Debt!E12),0) | D18: =IFERROR(D17/ABS(Debt!E12),0) | E18: =IFERROR(E17/ABS(Debt!E12),0) | F18: =IFERROR(F17/ABS(Debt!E12),0) | G18: =IFERROR(G17/ABS(Debt!E12),0) | H18: =IFERROR(H17/ABS(Debt!E12),0)
B20: COST OF DEBT SENSITIVITY (Y1 DSCR)
B21: Cost of debt | C21: 0.05 | D21: 0.06 | E21: 0.07 | F21: 0.08 | G21: 0.09 | H21: 0.1
B22: Y1 interest (approx) | C22: =Assumptions!$D$47*C21 | D22: =Assumptions!$D$47*D21 | E22: =Assumptions!$D$47*E21 | F22: =Assumptions!$D$47*F21 | G22: =Assumptions!$D$47*G21 | H22: =Assumptions!$D$47*H21
B23: Y1 DSCR (approx, interest-only proxy) | C23: =IFERROR(OpEx_CapEx!E9/C22,0) | D23: =IFERROR(OpEx_CapEx!E9/D22,0) | E23: =IFERROR(OpEx_CapEx!E9/E22,0) | F23: =IFERROR(OpEx_CapEx!E9/F22,0) | G23: =IFERROR(OpEx_CapEx!E9/G22,0) | H23: =IFERROR(OpEx_CapEx!E9/H22,0)

Sheet Sens_Matrix
B2: TWO-WAY SENSITIVITY MATRICES — computed (no Data Table required)
B3: Each cell rebuilds the analytic NPV/IRR/DSCR formula using paired shocks. Verify with Scenario_Engine for tied points.
B5: MATRIX 1: Equity IRR (approx) — rows: Exit Cap; cols: Cost of Debt
C7: 0.055 | D7: 0.065 | E7: 0.07 | F7: 0.075 | G7: 0.085 | H7: 0.095 | I7: 0.105
B8: 0.06 | C8: =IFERROR(((Assumptions!$D$7*(OpEx_CapEx!$E$9*((1+Assumptions!$D$20/2)^Assumptions!$D$7+1)/2-Assumptions!$D$47*0.055-Assumptions!$D$77*Assumptions!$D$57)+OpEx_CapEx!$E$9*(1+Assumptions!$D$20/2)^Assumptions!$D$7*(1+Assumptions!$D$20)/0.06*(1-0.03)-Assumptions!$D$47)/Assumptions!$D$48)^(1/Assumptions!$D$7)-1,-1) | D8: =IFERROR(((Assumptions!$D$7*(OpEx_CapEx!$E$9*((1+Assumptions!$D$20/2)^Assumptions!$D$7+1)/2-Assumptions!$D$47*0.065-Assumptions!$D$77*Assumptions!$D$57)+OpEx_CapEx!$E$9*(1+Assumptions!$D$20/2)^Assumptions!$D$7*(1+Assumptions!$D$20)/0.06*(1-0.03)-Assumptions!$D$47)/Assumptions!$D$48)^(1/Assumptions!$D$7)-1,-1) | E8: =IFERROR(((Assumptions!$D$7*(OpEx_CapEx!$E$9*((1+Assumptions!$D$20/2)^Assumptions!$D$7+1)/2-Assumptions!$D$47*0.07-Assumptions!$D$77*Assumptions!$D$57)+OpEx_CapEx!$E$9*(1+Assumptions!$D$20/2)^Assumptions!$D$7*(1+Assumptions!$D$20)/0.06*(1-0.03)-Assumptions!$D$47)/Assumptions!$D$48)^(1/Assumptions!$D$7)-1,-1) | F8: =IFERROR(((Assumptions!$D$7*(OpEx_CapEx!$E$9*((1+Assumptions!$D$20/2)^Assumptions!$D$7+1)/2-Assumptions!$D$47*0.075-Assumptions!$D$77*Assumptions!$D$57)+OpEx_CapEx!$E$9*(1+Assumptions!$D$20/2)^Assumptions!$D$7*(1+Assumptions!$D$20)/0.06*(1-0.03)-Assumptions!$D$47)/Assumptions!$D$48)^(1/Assumptions!$D$7)-1,-1) | G8: =IFERROR(((Assumptions!$D$7*(OpEx_CapEx!$E$9*((1+Assumptions!$D$20/2)^Assumptions!$D$7+1)/2-Assumptions!$D$47*0.085-Assumptions!$D$77*Assumptions!$D$57)+OpEx_CapEx!$E$9*(1+Assumptions!$D$20/2)^Assumptions!$D$7*(1+Assumptions!$D$20)/0.06*(1-0.03)-Assumptions!$D$47)/Assumptions!$D$48)^(1/Assumptions!$D$7)-1,-1) | H8: =IFERROR(((Assumptions!$D$7*(OpEx_CapEx!$E$9*((1+Assumptions!$D$20/2)^Assumptions!$D$7+1)/2-Assumptions!$D$47*0.095-Assumptions!$D$77*Assumptions!$D$57)+OpEx_CapEx!$E$9*(1+Assumptions!$D$20/2)^Assumptions!$D$7*(1+Assumptions!$D$20)/0.06*(1-0.03)-Assumptions!$D$47)/Assumptions!$D$48)^(1/Assumptions!$D$7)-1,-1) | I8: =IFERROR(((Assumptions!$D$7*(OpEx_CapEx!$E$9*((1+Assumptions!$D$20/2)^Assumptions!$D$7+1)/2-Assumptions!$D$47*0.105-Assumptions!$D$77*Assumptions!$D$57)+OpEx_CapEx!$E$9*(1+Assumptions!$D$20/2)^Assumptions!$D$7*(1+Assumptions!$D$20)/0.06*(1-0.03)-Assumptions!$D$47)/Assumptions!$D$48)^(1/Assumptions!$D$7)-1,-1)
B9: 0.065 | C9: =IFERROR(((Assumptions!$D$7*(OpEx_CapEx!$E$9*((1+Assumptions!$D$20/2)^Assumptions!$D$7+1)/2-Assumptions!$D$47*0.055-Assumptions!$D$77*Assumptions!$D$57)+OpEx_CapEx!$E$9*(1+Assumptions!$D$20/2)^Assumptions!$D$7*(1+Assumptions!$D$20)/0.065*(1-0.03)-Assumptions!$D$47)/Assumptions!$D$48)^(1/Assumptions!$D$7)-1,-1) | D9: =IFERROR(((Assumptions!$D$7*(OpEx_CapEx!$E$9*((1+Assumptions!$D$20/2)^Assumptions!$D$7+1)/2-Assumptions!$D$47*0.065-Assumptions!$D$77*Assumptions!$D$57)+OpEx_CapEx!$E$9*(1+Assumptions!$D$20/2)^Assumptions!$D$7*(1+Assumptions!$D$20)/0.065*(1-0.03)-Assumptions!$D$47)/Assumptions!$D$48)^(1/Assumptions!$D$7)-1,-1) | E9: =IFERROR(((Assumptions!$D$7*(OpEx_CapEx!$E$9*((1+Assumptions!$D$20/2)^Assumptions!$D$7+1)/2-Assumptions!$D$47*0.07-Assumptions!$D$77*Assumptions!$D$57)+OpEx_CapEx!$E$9*(1+Assumptions!$D$20/2)^Assumptions!$D$7*(1+Assumptions!$D$20)/0.065*(1-0.03)-Assumptions!$D$47)/Assumptions!$D$48)^(1/Assumptions!$D$7)-1,-1) | F9: =IFERROR(((Assumptions!$D$7*(OpEx_CapEx!$E$9*((1+Assumptions!$D$20/2)^Assumptions!$D$7+1)/2-Assumptions!$D$47*0.075-Assumptions!$D$77*Assumptions!$D$57)+OpEx_CapEx!$E$9*(1+Assumptions!$D$20/2)^Assumptions!$D$7*(1+Assumptions!$D$20)/0.065*(1-0.03)-Assumptions!$D$47)/Assumptions!$D$48)^(1/Assumptions!$D$7)-1,-1) | G9: =IFERROR(((Assumptions!$D$7*(OpEx_CapEx!$E$9*((1+Assumptions!$D$20/2)^Assumptions!$D$7+1)/2-Assumptions!$D$47*0.085-Assumptions!$D$77*Assumptions!$D$57)+OpEx_CapEx!$E$9*(1+Assumptions!$D$20/2)^Assumptions!$D$7*(1+Assumptions!$D$20)/0.065*(1-0.03)-Assumptions!$D$47)/Assumptions!$D$48)^(1/Assumptions!$D$7)-1,-1) | H9: =IFERROR(((Assumptions!$D$7*(OpEx_CapEx!$E$9*((1+Assumptions!$D$20/2)^Assumptions!$D$7+1)/2-Assumptions!$D$47*0.095-Assumptions!$D$77*Assumptions!$D$57)+OpEx_CapEx!$E$9*(1+Assumptions!$D$20/2)^Assumptions!$D$7*(1+Assumptions!$D$20)/0.065*(1-0.03)-Assumptions!$D$47)/Assumptions!$D$48)^(1/Assumptions!$D$7)-1,-1) | I9: =IFERROR(((Assumptions!$D$7*(OpEx_CapEx!$E$9*((1+Assumptions!$D$20/2)^Assumptions!$D$7+1)/2-Assumptions!$D$47*0.105-Assumptions!$D$77*Assumptions!$D$57)+OpEx_CapEx!$E$9*(1+Assumptions!$D$20/2)^Assumptions!$D$7*(1+Assumptions!$D$20)/0.065*(1-0.03)-Assumptions!$D$47)/Assumptions!$D$48)^(1/Assumptions!$D$7)-1,-1)
B10: 0.07 | C10: =IFERROR(((Assumptions!$D$7*(OpEx_CapEx!$E$9*((1+Assumptions!$D$20/2)^Assumptions!$D$7+1)/2-Assumptions!$D$47*0.055-Assumptions!$D$77*Assumptions!$D$57)+OpEx_CapEx!$E$9*(1+Assumptions!$D$20/2)^Assumptions!$D$7*(1+Assumptions!$D$20)/0.07*(1-0.03)-Assumptions!$D$47)/Assumptions!$D$48)^(1/Assumptions!$D$7)-1,-1) | D10: =IFERROR(((Assumptions!$D$7*(OpEx_CapEx!$E$9*((1+Assumptions!$D$20/2)^Assumptions!$D$7+1)/2-Assumptions!$D$47*0.065-Assumptions!$D$77*Assumptions!$D$57)+OpEx_CapEx!$E$9*(1+Assumptions!$D$20/2)^Assumptions!$D$7*(1+Assumptions!$D$20)/0.07*(1-0.03)-Assumptions!$D$47)/Assumptions!$D$48)^(1/Assumptions!$D$7)-1,-1) | E10: =IFERROR(((Assumptions!$D$7*(OpEx_CapEx!$E$9*((1+Assumptions!$D$20/2)^Assumptions!$D$7+1)/2-Assumptions!$D$47*0.07-Assumptions!$D$77*Assumptions!$D$57)+OpEx_CapEx!$E$9*(1+Assumptions!$D$20/2)^Assumptions!$D$7*(1+Assumptions!$D$20)/0.07*(1-0.03)-Assumptions!$D$47)/Assumptions!$D$48)^(1/Assumptions!$D$7)-1,-1) | F10: =IFERROR(((Assumptions!$D$7*(OpEx_CapEx!$E$9*((1+Assumptions!$D$20/2)^Assumptions!$D$7+1)/2-Assumptions!$D$47*0.075-Assumptions!$D$77*Assumptions!$D$57)+OpEx_CapEx!$E$9*(1+Assumptions!$D$20/2)^Assumptions!$D$7*(1+Assumptions!$D$20)/0.07*(1-0.03)-Assumptions!$D$47)/Assumptions!$D$48)^(1/Assumptions!$D$7)-1,-1) | G10: =IFERROR(((Assumptions!$D$7*(OpEx_CapEx!$E$9*((1+Assumptions!$D$20/2)^Assumptions!$D$7+1)/2-Assumptions!$D$47*0.085-Assumptions!$D$77*Assumptions!$D$57)+OpEx_CapEx!$E$9*(1+Assumptions!$D$20/2)^Assumptions!$D$7*(1+Assumptions!$D$20)/0.07*(1-0.03)-Assumptions!$D$47)/Assumptions!$D$48)^(1/Assumptions!$D$7)-1,-1) | H10: =IFERROR(((Assumptions!$D$7*(OpEx_CapEx!$E$9*((1+Assumptions!$D$20/2)^Assumptions!$D$7+1)/2-Assumptions!$D$47*0.095-Assumptions!$D$77*Assumptions!$D$57)+OpEx_CapEx!$E$9*(1+Assumptions!$D$20/2)^Assumptions!$D$7*(1+Assumptions!$D$20)/0.07*(1-0.03)-Assumptions!$D$47)/Assumptions!$D$48)^(1/Assumptions!$D$7)-1,-1) | I10: =IFERROR(((Assumptions!$D$7*(OpEx_CapEx!$E$9*((1+Assumptions!$D$20/2)^Assumptions!$D$7+1)/2-Assumptions!$D$47*0.105-Assumptions!$D$77*Assumptions!$D$57)+OpEx_CapEx!$E$9*(1+Assumptions!$D$20/2)^Assumptions!$D$7*(1+Assumptions!$D$20)/0.07*(1-0.03)-Assumptions!$D$47)/Assumptions!$D$48)^(1/Assumptions!$D$7)-1,-1)
B11: 0.075 | C11: =IFERROR(((Assumptions!$D$7*(OpEx_CapEx!$E$9*((1+Assumptions!$D$20/2)^Assumptions!$D$7+1)/2-Assumptions!$D$47*0.055-Assumptions!$D$77*Assumptions!$D$57)+OpEx_CapEx!$E$9*(1+Assumptions!$D$20/2)^Assumptions!$D$7*(1+Assumptions!$D$20)/0.075*(1-0.03)-Assumptions!$D$47)/Assumptions!$D$48)^(1/Assumptions!$D$7)-1,-1) | D11: =IFERROR(((Assumptions!$D$7*(OpEx_CapEx!$E$9*((1+Assumptions!$D$20/2)^Assumptions!$D$7+1)/2-Assumptions!$D$47*0.065-Assumptions!$D$77*Assumptions!$D$57)+OpEx_CapEx!$E$9*(1+Assumptions!$D$20/2)^Assumptions!$D$7*(1+Assumptions!$D$20)/0.075*(1-0.03)-Assumptions!$D$47)/Assumptions!$D$48)^(1/Assumptions!$D$7)-1,-1) | E11: =IFERROR(((Assumptions!$D$7*(OpEx_CapEx!$E$9*((1+Assumptions!$D$20/2)^Assumptions!$D$7+1)/2-Assumptions!$D$47*0.07-Assumptions!$D$77*Assumptions!$D$57)+OpEx_CapEx!$E$9*(1+Assumptions!$D$20/2)^Assumptions!$D$7*(1+Assumptions!$D$20)/0.075*(1-0.03)-Assumptions!$D$47)/Assumptions!$D$48)^(1/Assumptions!$D$7)-1,-1) | F11: =IFERROR(((Assumptions!$D$7*(OpEx_CapEx!$E$9*((1+Assumptions!$D$20/2)^Assumptions!$D$7+1)/2-Assumptions!$D$47*0.075-Assumptions!$D$77*Assumptions!$D$57)+OpEx_CapEx!$E$9*(1+Assumptions!$D$20/2)^Assumptions!$D$7*(1+Assumptions!$D$20)/0.075*(1-0.03)-Assumptions!$D$47)/Assumptions!$D$48)^(1/Assumptions!$D$7)-1,-1) | G11: =IFERROR(((Assumptions!$D$7*(OpEx_CapEx!$E$9*((1+Assumptions!$D$20/2)^Assumptions!$D$7+1)/2-Assumptions!$D$47*0.085-Assumptions!$D$77*Assumptions!$D$57)+OpEx_CapEx!$E$9*(1+Assumptions!$D$20/2)^Assumptions!$D$7*(1+Assumptions!$D$20)/0.075*(1-0.03)-Assumptions!$D$47)/Assumptions!$D$48)^(1/Assumptions!$D$7)-1,-1) | H11: =IFERROR(((Assumptions!$D$7*(OpEx_CapEx!$E$9*((1+Assumptions!$D$20/2)^Assumptions!$D$7+1)/2-Assumptions!$D$47*0.095-Assumptions!$D$77*Assumptions!$D$57)+OpEx_CapEx!$E$9*(1+Assumptions!$D$20/2)^Assumptions!$D$7*(1+Assumptions!$D$20)/0.075*(1-0.03)-Assumptions!$D$47)/Assumptions!$D$48)^(1/Assumptions!$D$7)-1,-1) | I11: =IFERROR(((Assumptions!$D$7*(OpEx_CapEx!$E$9*((1+Assumptions!$D$20/2)^Assumptions!$D$7+1)/2-Assumptions!$D$47*0.105-Assumptions!$D$77*Assumptions!$D$57)+OpEx_CapEx!$E$9*(1+Assumptions!$D$20/2)^Assumptions!$D$7*(1+Assumptions!$D$20)/0.075*(1-0.03)-Assumptions!$D$47)/Assumptions!$D$48)^(1/Assumptions!$D$7)-1,-1)
B12: 0.08 | C12: =IFERROR(((Assumptions!$D$7*(OpEx_CapEx!$E$9*((1+Assumptions!$D$20/2)^Assumptions!$D$7+1)/2-Assumptions!$D$47*0.055-Assumptions!$D$77*Assumptions!$D$57)+OpEx_CapEx!$E$9*(1+Assumptions!$D$20/2)^Assumptions!$D$7*(1+Assumptions!$D$20)/0.08*(1-0.03)-Assumptions!$D$47)/Assumptions!$D$48)^(1/Assumptions!$D$7)-1,-1) | D12: =IFERROR(((Assumptions!$D$7*(OpEx_CapEx!$E$9*((1+Assumptions!$D$20/2)^Assumptions!$D$7+1)/2-Assumptions!$D$47*0.065-Assumptions!$D$77*Assumptions!$D$57)+OpEx_CapEx!$E$9*(1+Assumptions!$D$20/2)^Assumptions!$D$7*(1+Assumptions!$D$20)/0.08*(1-0.03)-Assumptions!$D$47)/Assumptions!$D$48)^(1/Assumptions!$D$7)-1,-1) | E12: =IFERROR(((Assumptions!$D$7*(OpEx_CapEx!$E$9*((1+Assumptions!$D$20/2)^Assumptions!$D$7+1)/2-Assumptions!$D$47*0.07-Assumptions!$D$77*Assumptions!$D$57)+OpEx_CapEx!$E$9*(1+Assumptions!$D$20/2)^Assumptions!$D$7*(1+Assumptions!$D$20)/0.08*(1-0.03)-Assumptions!$D$47)/Assumptions!$D$48)^(1/Assumptions!$D$7)-1,-1) | F12: =IFERROR(((Assumptions!$D$7*(OpEx_CapEx!$E$9*((1+Assumptions!$D$20/2)^Assumptions!$D$7+1)/2-Assumptions!$D$47*0.075-Assumptions!$D$77*Assumptions!$D$57)+OpEx_CapEx!$E$9*(1+Assumptions!$D$20/2)^Assumptions!$D$7*(1+Assumptions!$D$20)/0.08*(1-0.03)-Assumptions!$D$47)/Assumptions!$D$48)^(1/Assumptions!$D$7)-1,-1) | G12: =IFERROR(((Assumptions!$D$7*(OpEx_CapEx!$E$9*((1+Assumptions!$D$20/2)^Assumptions!$D$7+1)/2-Assumptions!$D$47*0.085-Assumptions!$D$77*Assumptions!$D$57)+OpEx_CapEx!$E$9*(1+Assumptions!$D$20/2)^Assumptions!$D$7*(1+Assumptions!$D$20)/0.08*(1-0.03)-Assumptions!$D$47)/Assumptions!$D$48)^(1/Assumptions!$D$7)-1,-1) | H12: =IFERROR(((Assumptions!$D$7*(OpEx_CapEx!$E$9*((1+Assumptions!$D$20/2)^Assumptions!$D$7+1)/2-Assumptions!$D$47*0.095-Assumptions!$D$77*Assumptions!$D$57)+OpEx_CapEx!$E$9*(1+Assumptions!$D$20/2)^Assumptions!$D$7*(1+Assumptions!$D$20)/0.08*(1-0.03)-Assumptions!$D$47)/Assumptions!$D$48)^(1/Assumptions!$D$7)-1,-1) | I12: =IFERROR(((Assumptions!$D$7*(OpEx_CapEx!$E$9*((1+Assumptions!$D$20/2)^Assumptions!$D$7+1)/2-Assumptions!$D$47*0.105-Assumptions!$D$77*Assumptions!$D$57)+OpEx_CapEx!$E$9*(1+Assumptions!$D$20/2)^Assumptions!$D$7*(1+Assumptions!$D$20)/0.08*(1-0.03)-Assumptions!$D$47)/Assumptions!$D$48)^(1/Assumptions!$D$7)-1,-1)
B13: 0.085 | C13: =IFERROR(((Assumptions!$D$7*(OpEx_CapEx!$E$9*((1+Assumptions!$D$20/2)^Assumptions!$D$7+1)/2-Assumptions!$D$47*0.055-Assumptions!$D$77*Assumptions!$D$57)+OpEx_CapEx!$E$9*(1+Assumptions!$D$20/2)^Assumptions!$D$7*(1+Assumptions!$D$20)/0.085*(1-0.03)-Assumptions!$D$47)/Assumptions!$D$48)^(1/Assumptions!$D$7)-1,-1) | D13: =IFERROR(((Assumptions!$D$7*(OpEx_CapEx!$E$9*((1+Assumptions!$D$20/2)^Assumptions!$D$7+1)/2-Assumptions!$D$47*0.065-Assumptions!$D$77*Assumptions!$D$57)+OpEx_CapEx!$E$9*(1+Assumptions!$D$20/2)^Assumptions!$D$7*(1+Assumptions!$D$20)/0.085*(1-0.03)-Assumptions!$D$47)/Assumptions!$D$48)^(1/Assumptions!$D$7)-1,-1) | E13: =IFERROR(((Assumptions!$D$7*(OpEx_CapEx!$E$9*((1+Assumptions!$D$20/2)^Assumptions!$D$7+1)/2-Assumptions!$D$47*0.07-Assumptions!$D$77*Assumptions!$D$57)+OpEx_CapEx!$E$9*(1+Assumptions!$D$20/2)^Assumptions!$D$7*(1+Assumptions!$D$20)/0.085*(1-0.03)-Assumptions!$D$47)/Assumptions!$D$48)^(1/Assumptions!$D$7)-1,-1) | F13: =IFERROR(((Assumptions!$D$7*(OpEx_CapEx!$E$9*((1+Assumptions!$D$20/2)^Assumptions!$D$7+1)/2-Assumptions!$D$47*0.075-Assumptions!$D$77*Assumptions!$D$57)+OpEx_CapEx!$E$9*(1+Assumptions!$D$20/2)^Assumptions!$D$7*(1+Assumptions!$D$20)/0.085*(1-0.03)-Assumptions!$D$47)/Assumptions!$D$48)^(1/Assumptions!$D$7)-1,-1) | G13: =IFERROR(((Assumptions!$D$7*(OpEx_CapEx!$E$9*((1+Assumptions!$D$20/2)^Assumptions!$D$7+1)/2-Assumptions!$D$47*0.085-Assumptions!$D$77*Assumptions!$D$57)+OpEx_CapEx!$E$9*(1+Assumptions!$D$20/2)^Assumptions!$D$7*(1+Assumptions!$D$20)/0.085*(1-0.03)-Assumptions!$D$47)/Assumptions!$D$48)^(1/Assumptions!$D$7)-1,-1) | H13: =IFERROR(((Assumptions!$D$7*(OpEx_CapEx!$E$9*((1+Assumptions!$D$20/2)^Assumptions!$D$7+1)/2-Assumptions!$D$47*0.095-Assumptions!$D$77*Assumptions!$D$57)+OpEx_CapEx!$E$9*(1+Assumptions!$D$20/2)^Assumptions!$D$7*(1+Assumptions!$D$20)/0.085*(1-0.03)-Assumptions!$D$47)/Assumptions!$D$48)^(1/Assumptions!$D$7)-1,-1) | I13: =IFERROR(((Assumptions!$D$7*(OpEx_CapEx!$E$9*((1+Assumptions!$D$20/2)^Assumptions!$D$7+1)/2-Assumptions!$D$47*0.105-Assumptions!$D$77*Assumptions!$D$57)+OpEx_CapEx!$E$9*(1+Assumptions!$D$20/2)^Assumptions!$D$7*(1+Assumptions!$D$20)/0.085*(1-0.03)-Assumptions!$D$47)/Assumptions!$D$48)^(1/Assumptions!$D$7)-1,-1)
B14: 0.09 | C14: =IFERROR(((Assumptions!$D$7*(OpEx_CapEx!$E$9*((1+Assumptions!$D$20/2)^Assumptions!$D$7+1)/2-Assumptions!$D$47*0.055-Assumptions!$D$77*Assumptions!$D$57)+OpEx_CapEx!$E$9*(1+Assumptions!$D$20/2)^Assumptions!$D$7*(1+Assumptions!$D$20)/0.09*(1-0.03)-Assumptions!$D$47)/Assumptions!$D$48)^(1/Assumptions!$D$7)-1,-1) | D14: =IFERROR(((Assumptions!$D$7*(OpEx_CapEx!$E$9*((1+Assumptions!$D$20/2)^Assumptions!$D$7+1)/2-Assumptions!$D$47*0.065-Assumptions!$D$77*Assumptions!$D$57)+OpEx_CapEx!$E$9*(1+Assumptions!$D$20/2)^Assumptions!$D$7*(1+Assumptions!$D$20)/0.09*(1-0.03)-Assumptions!$D$47)/Assumptions!$D$48)^(1/Assumptions!$D$7)-1,-1) | E14: =IFERROR(((Assumptions!$D$7*(OpEx_CapEx!$E$9*((1+Assumptions!$D$20/2)^Assumptions!$D$7+1)/2-Assumptions!$D$47*0.07-Assumptions!$D$77*Assumptions!$D$57)+OpEx_CapEx!$E$9*(1+Assumptions!$D$20/2)^Assumptions!$D$7*(1+Assumptions!$D$20)/0.09*(1-0.03)-Assumptions!$D$47)/Assumptions!$D$48)^(1/Assumptions!$D$7)-1,-1) | F14: =IFERROR(((Assumptions!$D$7*(OpEx_CapEx!$E$9*((1+Assumptions!$D$20/2)^Assumptions!$D$7+1)/2-Assumptions!$D$47*0.075-Assumptions!$D$77*Assumptions!$D$57)+OpEx_CapEx!$E$9*(1+Assumptions!$D$20/2)^Assumptions!$D$7*(1+Assumptions!$D$20)/0.09*(1-0.03)-Assumptions!$D$47)/Assumptions!$D$48)^(1/Assumptions!$D$7)-1,-1) | G14: =IFERROR(((Assumptions!$D$7*(OpEx_CapEx!$E$9*((1+Assumptions!$D$20/2)^Assumptions!$D$7+1)/2-Assumptions!$D$47*0.085-Assumptions!$D$77*Assumptions!$D$57)+OpEx_CapEx!$E$9*(1+Assumptions!$D$20/2)^Assumptions!$D$7*(1+Assumptions!$D$20)/0.09*(1-0.03)-Assumptions!$D$47)/Assumptions!$D$48)^(1/Assumptions!$D$7)-1,-1) | H14: =IFERROR(((Assumptions!$D$7*(OpEx_CapEx!$E$9*((1+Assumptions!$D$20/2)^Assumptions!$D$7+1)/2-Assumptions!$D$47*0.095-Assumptions!$D$77*Assumptions!$D$57)+OpEx_CapEx!$E$9*(1+Assumptions!$D$20/2)^Assumptions!$D$7*(1+Assumptions!$D$20)/0.09*(1-0.03)-Assumptions!$D$47)/Assumptions!$D$48)^(1/Assumptions!$D$7)-1,-1) | I14: =IFERROR(((Assumptions!$D$7*(OpEx_CapEx!$E$9*((1+Assumptions!$D$20/2)^Assumptions!$D$7+1)/2-Assumptions!$D$47*0.105-Assumptions!$D$77*Assumptions!$D$57)+OpEx_CapEx!$E$9*(1+Assumptions!$D$20/2)^Assumptions!$D$7*(1+Assumptions!$D$20)/0.09*(1-0.03)-Assumptions!$D$47)/Assumptions!$D$48)^(1/Assumptions!$D$7)-1,-1)
B18: MATRIX 2: Y1 DSCR — rows: Vacancy; cols: Cost of Debt
C20: 0.055 | D20: 0.065 | E20: 0.07 | F20: 0.075 | G20: 0.085 | H20: 0.095 | I20: 0.105
B21: 0 | C21: =IFERROR((Assumptions!$D$19*(1-0.0)*(1-Assumptions!$D$25))/(Assumptions!$D$47*0.055),0) | D21: =IFERROR((Assumptions!$D$19*(1-0.0)*(1-Assumptions!$D$25))/(Assumptions!$D$47*0.065),0) | E21: =IFERROR((Assumptions!$D$19*(1-0.0)*(1-Assumptions!$D$25))/(Assumptions!$D$47*0.07),0) | F21: =IFERROR((Assumptions!$D$19*(1-0.0)*(1-Assumptions!$D$25))/(Assumptions!$D$47*0.075),0) | G21: =IFERROR((Assumptions!$D$19*(1-0.0)*(1-Assumptions!$D$25))/(Assumptions!$D$47*0.085),0) | H21: =IFERROR((Assumptions!$D$19*(1-0.0)*(1-Assumptions!$D$25))/(Assumptions!$D$47*0.095),0) | I21: =IFERROR((Assumptions!$D$19*(1-0.0)*(1-Assumptions!$D$25))/(Assumptions!$D$47*0.105),0)
B22: 0.03 | C22: =IFERROR((Assumptions!$D$19*(1-0.03)*(1-Assumptions!$D$25))/(Assumptions!$D$47*0.055),0) | D22: =IFERROR((Assumptions!$D$19*(1-0.03)*(1-Assumptions!$D$25))/(Assumptions!$D$47*0.065),0) | E22: =IFERROR((Assumptions!$D$19*(1-0.03)*(1-Assumptions!$D$25))/(Assumptions!$D$47*0.07),0) | F22: =IFERROR((Assumptions!$D$19*(1-0.03)*(1-Assumptions!$D$25))/(Assumptions!$D$47*0.075),0) | G22: =IFERROR((Assumptions!$D$19*(1-0.03)*(1-Assumptions!$D$25))/(Assumptions!$D$47*0.085),0) | H22: =IFERROR((Assumptions!$D$19*(1-0.03)*(1-Assumptions!$D$25))/(Assumptions!$D$47*0.095),0) | I22: =IFERROR((Assumptions!$D$19*(1-0.03)*(1-Assumptions!$D$25))/(Assumptions!$D$47*0.105),0)
B23: 0.05 | C23: =IFERROR((Assumptions!$D$19*(1-0.05)*(1-Assumptions!$D$25))/(Assumptions!$D$47*0.055),0) | D23: =IFERROR((Assumptions!$D$19*(1-0.05)*(1-Assumptions!$D$25))/(Assumptions!$D$47*0.065),0) | E23: =IFERROR((Assumptions!$D$19*(1-0.05)*(1-Assumptions!$D$25))/(Assumptions!$D$47*0.07),0) | F23: =IFERROR((Assumptions!$D$19*(1-0.05)*(1-Assumptions!$D$25))/(Assumptions!$D$47*0.075),0) | G23: =IFERROR((Assumptions!$D$19*(1-0.05)*(1-Assumptions!$D$25))/(Assumptions!$D$47*0.085),0) | H23: =IFERROR((Assumptions!$D$19*(1-0.05)*(1-Assumptions!$D$25))/(Assumptions!$D$47*0.095),0) | I23: =IFERROR((Assumptions!$D$19*(1-0.05)*(1-Assumptions!$D$25))/(Assumptions!$D$47*0.105),0)
B24: 0.08 | C24: =IFERROR((Assumptions!$D$19*(1-0.08)*(1-Assumptions!$D$25))/(Assumptions!$D$47*0.055),0) | D24: =IFERROR((Assumptions!$D$19*(1-0.08)*(1-Assumptions!$D$25))/(Assumptions!$D$47*0.065),0) | E24: =IFERROR((Assumptions!$D$19*(1-0.08)*(1-Assumptions!$D$25))/(Assumptions!$D$47*0.07),0) | F24: =IFERROR((Assumptions!$D$19*(1-0.08)*(1-Assumptions!$D$25))/(Assumptions!$D$47*0.075),0) | G24: =IFERROR((Assumptions!$D$19*(1-0.08)*(1-Assumptions!$D$25))/(Assumptions!$D$47*0.085),0) | H24: =IFERROR((Assumptions!$D$19*(1-0.08)*(1-Assumptions!$D$25))/(Assumptions!$D$47*0.095),0) | I24: =IFERROR((Assumptions!$D$19*(1-0.08)*(1-Assumptions!$D$25))/(Assumptions!$D$47*0.105),0)
B25: 0.12 | C25: =IFERROR((Assumptions!$D$19*(1-0.12)*(1-Assumptions!$D$25))/(Assumptions!$D$47*0.055),0) | D25: =IFERROR((Assumptions!$D$19*(1-0.12)*(1-Assumptions!$D$25))/(Assumptions!$D$47*0.065),0) | E25: =IFERROR((Assumptions!$D$19*(1-0.12)*(1-Assumptions!$D$25))/(Assumptions!$D$47*0.07),0) | F25: =IFERROR((Assumptions!$D$19*(1-0.12)*(1-Assumptions!$D$25))/(Assumptions!$D$47*0.075),0) | G25: =IFERROR((Assumptions!$D$19*(1-0.12)*(1-Assumptions!$D$25))/(Assumptions!$D$47*0.085),0) | H25: =IFERROR((Assumptions!$D$19*(1-0.12)*(1-Assumptions!$D$25))/(Assumptions!$D$47*0.095),0) | I25: =IFERROR((Assumptions!$D$19*(1-0.12)*(1-Assumptions!$D$25))/(Assumptions!$D$47*0.105),0)
B26: 0.18 | C26: =IFERROR((Assumptions!$D$19*(1-0.18)*(1-Assumptions!$D$25))/(Assumptions!$D$47*0.055),0) | D26: =IFERROR((Assumptions!$D$19*(1-0.18)*(1-Assumptions!$D$25))/(Assumptions!$D$47*0.065),0) | E26: =IFERROR((Assumptions!$D$19*(1-0.18)*(1-Assumptions!$D$25))/(Assumptions!$D$47*0.07),0) | F26: =IFERROR((Assumptions!$D$19*(1-0.18)*(1-Assumptions!$D$25))/(Assumptions!$D$47*0.075),0) | G26: =IFERROR((Assumptions!$D$19*(1-0.18)*(1-Assumptions!$D$25))/(Assumptions!$D$47*0.085),0) | H26: =IFERROR((Assumptions!$D$19*(1-0.18)*(1-Assumptions!$D$25))/(Assumptions!$D$47*0.095),0) | I26: =IFERROR((Assumptions!$D$19*(1-0.18)*(1-Assumptions!$D$25))/(Assumptions!$D$47*0.105),0)
B27: 0.25 | C27: =IFERROR((Assumptions!$D$19*(1-0.25)*(1-Assumptions!$D$25))/(Assumptions!$D$47*0.055),0) | D27: =IFERROR((Assumptions!$D$19*(1-0.25)*(1-Assumptions!$D$25))/(Assumptions!$D$47*0.065),0) | E27: =IFERROR((Assumptions!$D$19*(1-0.25)*(1-Assumptions!$D$25))/(Assumptions!$D$47*0.07),0) | F27: =IFERROR((Assumptions!$D$19*(1-0.25)*(1-Assumptions!$D$25))/(Assumptions!$D$47*0.075),0) | G27: =IFERROR((Assumptions!$D$19*(1-0.25)*(1-Assumptions!$D$25))/(Assumptions!$D$47*0.085),0) | H27: =IFERROR((Assumptions!$D$19*(1-0.25)*(1-Assumptions!$D$25))/(Assumptions!$D$47*0.095),0) | I27: =IFERROR((Assumptions!$D$19*(1-0.25)*(1-Assumptions!$D$25))/(Assumptions!$D$47*0.105),0)
B30: MATRIX 3: NPV (Project, SAR M) — rows: Purchase price; cols: Exit cap
C32: 0.065 | D32: 0.07 | E32: 0.075 | F32: 0.08 | G32: 0.085 | H32: 0.09 | I32: 0.1
B33: 150000000 | C33: =(-150000000.0*(1+Assumptions!$D$15)+(OpEx_CapEx!$E$9-OpEx_CapEx!$E$21+Tax!$E$12)*((1-(1+Assumptions!$D$68)^-Assumptions!$D$7)/Assumptions!$D$68)+(OpEx_CapEx!$E$9*(1+Assumptions!$D$20/2)^Assumptions!$D$7*(1+Assumptions!$D$20)/0.065*(1-Assumptions!$D$52-Assumptions!$D$53-Assumptions!$D$54))/(1+Assumptions!$D$68)^Assumptions!$D$7)/1e6 | D33: =(-150000000.0*(1+Assumptions!$D$15)+(OpEx_CapEx!$E$9-OpEx_CapEx!$E$21+Tax!$E$12)*((1-(1+Assumptions!$D$68)^-Assumptions!$D$7)/Assumptions!$D$68)+(OpEx_CapEx!$E$9*(1+Assumptions!$D$20/2)^Assumptions!$D$7*(1+Assumptions!$D$20)/0.07*(1-Assumptions!$D$52-Assumptions!$D$53-Assumptions!$D$54))/(1+Assumptions!$D$68)^Assumptions!$D$7)/1e6 | E33: =(-150000000.0*(1+Assumptions!$D$15)+(OpEx_CapEx!$E$9-OpEx_CapEx!$E$21+Tax!$E$12)*((1-(1+Assumptions!$D$68)^-Assumptions!$D$7)/Assumptions!$D$68)+(OpEx_CapEx!$E$9*(1+Assumptions!$D$20/2)^Assumptions!$D$7*(1+Assumptions!$D$20)/0.075*(1-Assumptions!$D$52-Assumptions!$D$53-Assumptions!$D$54))/(1+Assumptions!$D$68)^Assumptions!$D$7)/1e6 | F33: =(-150000000.0*(1+Assumptions!$D$15)+(OpEx_CapEx!$E$9-OpEx_CapEx!$E$21+Tax!$E$12)*((1-(1+Assumptions!$D$68)^-Assumptions!$D$7)/Assumptions!$D$68)+(OpEx_CapEx!$E$9*(1+Assumptions!$D$20/2)^Assumptions!$D$7*(1+Assumptions!$D$20)/0.08*(1-Assumptions!$D$52-Assumptions!$D$53-Assumptions!$D$54))/(1+Assumptions!$D$68)^Assumptions!$D$7)/1e6 | G33: =(-150000000.0*(1+Assumptions!$D$15)+(OpEx_CapEx!$E$9-OpEx_CapEx!$E$21+Tax!$E$12)*((1-(1+Assumptions!$D$68)^-Assumptions!$D$7)/Assumptions!$D$68)+(OpEx_CapEx!$E$9*(1+Assumptions!$D$20/2)^Assumptions!$D$7*(1+Assumptions!$D$20)/0.085*(1-Assumptions!$D$52-Assumptions!$D$53-Assumptions!$D$54))/(1+Assumptions!$D$68)^Assumptions!$D$7)/1e6 | H33: =(-150000000.0*(1+Assumptions!$D$15)+(OpEx_CapEx!$E$9-OpEx_CapEx!$E$21+Tax!$E$12)*((1-(1+Assumptions!$D$68)^-Assumptions!$D$7)/Assumptions!$D$68)+(OpEx_CapEx!$E$9*(1+Assumptions!$D$20/2)^Assumptions!$D$7*(1+Assumptions!$D$20)/0.09*(1-Assumptions!$D$52-Assumptions!$D$53-Assumptions!$D$54))/(1+Assumptions!$D$68)^Assumptions!$D$7)/1e6 | I33: =(-150000000.0*(1+Assumptions!$D$15)+(OpEx_CapEx!$E$9-OpEx_CapEx!$E$21+Tax!$E$12)*((1-(1+Assumptions!$D$68)^-Assumptions!$D$7)/Assumptions!$D$68)+(OpEx_CapEx!$E$9*(1+Assumptions!$D$20/2)^Assumptions!$D$7*(1+Assumptions!$D$20)/0.1*(1-Assumptions!$D$52-Assumptions!$D$53-Assumptions!$D$54))/(1+Assumptions!$D$68)^Assumptions!$D$7)/1e6
B34: 165000000 | C34: =(-165000000.0*(1+Assumptions!$D$15)+(OpEx_CapEx!$E$9-OpEx_CapEx!$E$21+Tax!$E$12)*((1-(1+Assumptions!$D$68)^-Assumptions!$D$7)/Assumptions!$D$68)+(OpEx_CapEx!$E$9*(1+Assumptions!$D$20/2)^Assumptions!$D$7*(1+Assumptions!$D$20)/0.065*(1-Assumptions!$D$52-Assumptions!$D$53-Assumptions!$D$54))/(1+Assumptions!$D$68)^Assumptions!$D$7)/1e6 | D34: =(-165000000.0*(1+Assumptions!$D$15)+(OpEx_CapEx!$E$9-OpEx_CapEx!$E$21+Tax!$E$12)*((1-(1+Assumptions!$D$68)^-Assumptions!$D$7)/Assumptions!$D$68)+(OpEx_CapEx!$E$9*(1+Assumptions!$D$20/2)^Assumptions!$D$7*(1+Assumptions!$D$20)/0.07*(1-Assumptions!$D$52-Assumptions!$D$53-Assumptions!$D$54))/(1+Assumptions!$D$68)^Assumptions!$D$7)/1e6 | E34: =(-165000000.0*(1+Assumptions!$D$15)+(OpEx_CapEx!$E$9-OpEx_CapEx!$E$21+Tax!$E$12)*((1-(1+Assumptions!$D$68)^-Assumptions!$D$7)/Assumptions!$D$68)+(OpEx_CapEx!$E$9*(1+Assumptions!$D$20/2)^Assumptions!$D$7*(1+Assumptions!$D$20)/0.075*(1-Assumptions!$D$52-Assumptions!$D$53-Assumptions!$D$54))/(1+Assumptions!$D$68)^Assumptions!$D$7)/1e6 | F34: =(-165000000.0*(1+Assumptions!$D$15)+(OpEx_CapEx!$E$9-OpEx_CapEx!$E$21+Tax!$E$12)*((1-(1+Assumptions!$D$68)^-Assumptions!$D$7)/Assumptions!$D$68)+(OpEx_CapEx!$E$9*(1+Assumptions!$D$20/2)^Assumptions!$D$7*(1+Assumptions!$D$20)/0.08*(1-Assumptions!$D$52-Assumptions!$D$53-Assumptions!$D$54))/(1+Assumptions!$D$68)^Assumptions!$D$7)/1e6 | G34: =(-165000000.0*(1+Assumptions!$D$15)+(OpEx_CapEx!$E$9-OpEx_CapEx!$E$21+Tax!$E$12)*((1-(1+Assumptions!$D$68)^-Assumptions!$D$7)/Assumptions!$D$68)+(OpEx_CapEx!$E$9*(1+Assumptions!$D$20/2)^Assumptions!$D$7*(1+Assumptions!$D$20)/0.085*(1-Assumptions!$D$52-Assumptions!$D$53-Assumptions!$D$54))/(1+Assumptions!$D$68)^Assumptions!$D$7)/1e6 | H34: =(-165000000.0*(1+Assumptions!$D$15)+(OpEx_CapEx!$E$9-OpEx_CapEx!$E$21+Tax!$E$12)*((1-(1+Assumptions!$D$68)^-Assumptions!$D$7)/Assumptions!$D$68)+(OpEx_CapEx!$E$9*(1+Assumptions!$D$20/2)^Assumptions!$D$7*(1+Assumptions!$D$20)/0.09*(1-Assumptions!$D$52-Assumptions!$D$53-Assumptions!$D$54))/(1+Assumptions!$D$68)^Assumptions!$D$7)/1e6 | I34: =(-165000000.0*(1+Assumptions!$D$15)+(OpEx_CapEx!$E$9-OpEx_CapEx!$E$21+Tax!$E$12)*((1-(1+Assumptions!$D$68)^-Assumptions!$D$7)/Assumptions!$D$68)+(OpEx_CapEx!$E$9*(1+Assumptions!$D$20/2)^Assumptions!$D$7*(1+Assumptions!$D$20)/0.1*(1-Assumptions!$D$52-Assumptions!$D$53-Assumptions!$D$54))/(1+Assumptions!$D$68)^Assumptions!$D$7)/1e6
B35: 175000000 | C35: =(-175000000.0*(1+Assumptions!$D$15)+(OpEx_CapEx!$E$9-OpEx_CapEx!$E$21+Tax!$E$12)*((1-(1+Assumptions!$D$68)^-Assumptions!$D$7)/Assumptions!$D$68)+(OpEx_CapEx!$E$9*(1+Assumptions!$D$20/2)^Assumptions!$D$7*(1+Assumptions!$D$20)/0.065*(1-Assumptions!$D$52-Assumptions!$D$53-Assumptions!$D$54))/(1+Assumptions!$D$68)^Assumptions!$D$7)/1e6 | D35: =(-175000000.0*(1+Assumptions!$D$15)+(OpEx_CapEx!$E$9-OpEx_CapEx!$E$21+Tax!$E$12)*((1-(1+Assumptions!$D$68)^-Assumptions!$D$7)/Assumptions!$D$68)+(OpEx_CapEx!$E$9*(1+Assumptions!$D$20/2)^Assumptions!$D$7*(1+Assumptions!$D$20)/0.07*(1-Assumptions!$D$52-Assumptions!$D$53-Assumptions!$D$54))/(1+Assumptions!$D$68)^Assumptions!$D$7)/1e6 | E35: =(-175000000.0*(1+Assumptions!$D$15)+(OpEx_CapEx!$E$9-OpEx_CapEx!$E$21+Tax!$E$12)*((1-(1+Assumptions!$D$68)^-Assumptions!$D$7)/Assumptions!$D$68)+(OpEx_CapEx!$E$9*(1+Assumptions!$D$20/2)^Assumptions!$D$7*(1+Assumptions!$D$20)/0.075*(1-Assumptions!$D$52-Assumptions!$D$53-Assumptions!$D$54))/(1+Assumptions!$D$68)^Assumptions!$D$7)/1e6 | F35: =(-175000000.0*(1+Assumptions!$D$15)+(OpEx_CapEx!$E$9-OpEx_CapEx!$E$21+Tax!$E$12)*((1-(1+Assumptions!$D$68)^-Assumptions!$D$7)/Assumptions!$D$68)+(OpEx_CapEx!$E$9*(1+Assumptions!$D$20/2)^Assumptions!$D$7*(1+Assumptions!$D$20)/0.08*(1-Assumptions!$D$52-Assumptions!$D$53-Assumptions!$D$54))/(1+Assumptions!$D$68)^Assumptions!$D$7)/1e6 | G35: =(-175000000.0*(1+Assumptions!$D$15)+(OpEx_CapEx!$E$9-OpEx_CapEx!$E$21+Tax!$E$12)*((1-(1+Assumptions!$D$68)^-Assumptions!$D$7)/Assumptions!$D$68)+(OpEx_CapEx!$E$9*(1+Assumptions!$D$20/2)^Assumptions!$D$7*(1+Assumptions!$D$20)/0.085*(1-Assumptions!$D$52-Assumptions!$D$53-Assumptions!$D$54))/(1+Assumptions!$D$68)^Assumptions!$D$7)/1e6 | H35: =(-175000000.0*(1+Assumptions!$D$15)+(OpEx_CapEx!$E$9-OpEx_CapEx!$E$21+Tax!$E$12)*((1-(1+Assumptions!$D$68)^-Assumptions!$D$7)/Assumptions!$D$68)+(OpEx_CapEx!$E$9*(1+Assumptions!$D$20/2)^Assumptions!$D$7*(1+Assumptions!$D$20)/0.09*(1-Assumptions!$D$52-Assumptions!$D$53-Assumptions!$D$54))/(1+Assumptions!$D$68)^Assumptions!$D$7)/1e6 | I35: =(-175000000.0*(1+Assumptions!$D$15)+(OpEx_CapEx!$E$9-OpEx_CapEx!$E$21+Tax!$E$12)*((1-(1+Assumptions!$D$68)^-Assumptions!$D$7)/Assumptions!$D$68)+(OpEx_CapEx!$E$9*(1+Assumptions!$D$20/2)^Assumptions!$D$7*(1+Assumptions!$D$20)/0.1*(1-Assumptions!$D$52-Assumptions!$D$53-Assumptions!$D$54))/(1+Assumptions!$D$68)^Assumptions!$D$7)/1e6
B36: 185000000 | C36: =(-185000000.0*(1+Assumptions!$D$15)+(OpEx_CapEx!$E$9-OpEx_CapEx!$E$21+Tax!$E$12)*((1-(1+Assumptions!$D$68)^-Assumptions!$D$7)/Assumptions!$D$68)+(OpEx_CapEx!$E$9*(1+Assumptions!$D$20/2)^Assumptions!$D$7*(1+Assumptions!$D$20)/0.065*(1-Assumptions!$D$52-Assumptions!$D$53-Assumptions!$D$54))/(1+Assumptions!$D$68)^Assumptions!$D$7)/1e6 | D36: =(-185000000.0*(1+Assumptions!$D$15)+(OpEx_CapEx!$E$9-OpEx_CapEx!$E$21+Tax!$E$12)*((1-(1+Assumptions!$D$68)^-Assumptions!$D$7)/Assumptions!$D$68)+(OpEx_CapEx!$E$9*(1+Assumptions!$D$20/2)^Assumptions!$D$7*(1+Assumptions!$D$20)/0.07*(1-Assumptions!$D$52-Assumptions!$D$53-Assumptions!$D$54))/(1+Assumptions!$D$68)^Assumptions!$D$7)/1e6 | E36: =(-185000000.0*(1+Assumptions!$D$15)+(OpEx_CapEx!$E$9-OpEx_CapEx!$E$21+Tax!$E$12)*((1-(1+Assumptions!$D$68)^-Assumptions!$D$7)/Assumptions!$D$68)+(OpEx_CapEx!$E$9*(1+Assumptions!$D$20/2)^Assumptions!$D$7*(1+Assumptions!$D$20)/0.075*(1-Assumptions!$D$52-Assumptions!$D$53-Assumptions!$D$54))/(1+Assumptions!$D$68)^Assumptions!$D$7)/1e6 | F36: =(-185000000.0*(1+Assumptions!$D$15)+(OpEx_CapEx!$E$9-OpEx_CapEx!$E$21+Tax!$E$12)*((1-(1+Assumptions!$D$68)^-Assumptions!$D$7)/Assumptions!$D$68)+(OpEx_CapEx!$E$9*(1+Assumptions!$D$20/2)^Assumptions!$D$7*(1+Assumptions!$D$20)/0.08*(1-Assumptions!$D$52-Assumptions!$D$53-Assumptions!$D$54))/(1+Assumptions!$D$68)^Assumptions!$D$7)/1e6 | G36: =(-185000000.0*(1+Assumptions!$D$15)+(OpEx_CapEx!$E$9-OpEx_CapEx!$E$21+Tax!$E$12)*((1-(1+Assumptions!$D$68)^-Assumptions!$D$7)/Assumptions!$D$68)+(OpEx_CapEx!$E$9*(1+Assumptions!$D$20/2)^Assumptions!$D$7*(1+Assumptions!$D$20)/0.085*(1-Assumptions!$D$52-Assumptions!$D$53-Assumptions!$D$54))/(1+Assumptions!$D$68)^Assumptions!$D$7)/1e6 | H36: =(-185000000.0*(1+Assumptions!$D$15)+(OpEx_CapEx!$E$9-OpEx_CapEx!$E$21+Tax!$E$12)*((1-(1+Assumptions!$D$68)^-Assumptions!$D$7)/Assumptions!$D$68)+(OpEx_CapEx!$E$9*(1+Assumptions!$D$20/2)^Assumptions!$D$7*(1+Assumptions!$D$20)/0.09*(1-Assumptions!$D$52-Assumptions!$D$53-Assumptions!$D$54))/(1+Assumptions!$D$68)^Assumptions!$D$7)/1e6 | I36: =(-185000000.0*(1+Assumptions!$D$15)+(OpEx_CapEx!$E$9-OpEx_CapEx!$E$21+Tax!$E$12)*((1-(1+Assumptions!$D$68)^-Assumptions!$D$7)/Assumptions!$D$68)+(OpEx_CapEx!$E$9*(1+Assumptions!$D$20/2)^Assumptions!$D$7*(1+Assumptions!$D$20)/0.1*(1-Assumptions!$D$52-Assumptions!$D$53-Assumptions!$D$54))/(1+Assumptions!$D$68)^Assumptions!$D$7)/1e6
B37: 200000000 | C37: =(-200000000.0*(1+Assumptions!$D$15)+(OpEx_CapEx!$E$9-OpEx_CapEx!$E$21+Tax!$E$12)*((1-(1+Assumptions!$D$68)^-Assumptions!$D$7)/Assumptions!$D$68)+(OpEx_CapEx!$E$9*(1+Assumptions!$D$20/2)^Assumptions!$D$7*(1+Assumptions!$D$20)/0.065*(1-Assumptions!$D$52-Assumptions!$D$53-Assumptions!$D$54))/(1+Assumptions!$D$68)^Assumptions!$D$7)/1e6 | D37: =(-200000000.0*(1+Assumptions!$D$15)+(OpEx_CapEx!$E$9-OpEx_CapEx!$E$21+Tax!$E$12)*((1-(1+Assumptions!$D$68)^-Assumptions!$D$7)/Assumptions!$D$68)+(OpEx_CapEx!$E$9*(1+Assumptions!$D$20/2)^Assumptions!$D$7*(1+Assumptions!$D$20)/0.07*(1-Assumptions!$D$52-Assumptions!$D$53-Assumptions!$D$54))/(1+Assumptions!$D$68)^Assumptions!$D$7)/1e6 | E37: =(-200000000.0*(1+Assumptions!$D$15)+(OpEx_CapEx!$E$9-OpEx_CapEx!$E$21+Tax!$E$12)*((1-(1+Assumptions!$D$68)^-Assumptions!$D$7)/Assumptions!$D$68)+(OpEx_CapEx!$E$9*(1+Assumptions!$D$20/2)^Assumptions!$D$7*(1+Assumptions!$D$20)/0.075*(1-Assumptions!$D$52-Assumptions!$D$53-Assumptions!$D$54))/(1+Assumptions!$D$68)^Assumptions!$D$7)/1e6 | F37: =(-200000000.0*(1+Assumptions!$D$15)+(OpEx_CapEx!$E$9-OpEx_CapEx!$E$21+Tax!$E$12)*((1-(1+Assumptions!$D$68)^-Assumptions!$D$7)/Assumptions!$D$68)+(OpEx_CapEx!$E$9*(1+Assumptions!$D$20/2)^Assumptions!$D$7*(1+Assumptions!$D$20)/0.08*(1-Assumptions!$D$52-Assumptions!$D$53-Assumptions!$D$54))/(1+Assumptions!$D$68)^Assumptions!$D$7)/1e6 | G37: =(-200000000.0*(1+Assumptions!$D$15)+(OpEx_CapEx!$E$9-OpEx_CapEx!$E$21+Tax!$E$12)*((1-(1+Assumptions!$D$68)^-Assumptions!$D$7)/Assumptions!$D$68)+(OpEx_CapEx!$E$9*(1+Assumptions!$D$20/2)^Assumptions!$D$7*(1+Assumptions!$D$20)/0.085*(1-Assumptions!$D$52-Assumptions!$D$53-Assumptions!$D$54))/(1+Assumptions!$D$68)^Assumptions!$D$7)/1e6 | H37: =(-200000000.0*(1+Assumptions!$D$15)+(OpEx_CapEx!$E$9-OpEx_CapEx!$E$21+Tax!$E$12)*((1-(1+Assumptions!$D$68)^-Assumptions!$D$7)/Assumptions!$D$68)+(OpEx_CapEx!$E$9*(1+Assumptions!$D$20/2)^Assumptions!$D$7*(1+Assumptions!$D$20)/0.09*(1-Assumptions!$D$52-Assumptions!$D$53-Assumptions!$D$54))/(1+Assumptions!$D$68)^Assumptions!$D$7)/1e6 | I37: =(-200000000.0*(1+Assumptions!$D$15)+(OpEx_CapEx!$E$9-OpEx_CapEx!$E$21+Tax!$E$12)*((1-(1+Assumptions!$D$68)^-Assumptions!$D$7)/Assumptions!$D$68)+(OpEx_CapEx!$E$9*(1+Assumptions!$D$20/2)^Assumptions!$D$7*(1+Assumptions!$D$20)/0.1*(1-Assumptions!$D$52-Assumptions!$D$53-Assumptions!$D$54))/(1+Assumptions!$D$68)^Assumptions!$D$7)/1e6
B38: 215000000 | C38: =(-215000000.0*(1+Assumptions!$D$15)+(OpEx_CapEx!$E$9-OpEx_CapEx!$E$21+Tax!$E$12)*((1-(1+Assumptions!$D$68)^-Assumptions!$D$7)/Assumptions!$D$68)+(OpEx_CapEx!$E$9*(1+Assumptions!$D$20/2)^Assumptions!$D$7*(1+Assumptions!$D$20)/0.065*(1-Assumptions!$D$52-Assumptions!$D$53-Assumptions!$D$54))/(1+Assumptions!$D$68)^Assumptions!$D$7)/1e6 | D38: =(-215000000.0*(1+Assumptions!$D$15)+(OpEx_CapEx!$E$9-OpEx_CapEx!$E$21+Tax!$E$12)*((1-(1+Assumptions!$D$68)^-Assumptions!$D$7)/Assumptions!$D$68)+(OpEx_CapEx!$E$9*(1+Assumptions!$D$20/2)^Assumptions!$D$7*(1+Assumptions!$D$20)/0.07*(1-Assumptions!$D$52-Assumptions!$D$53-Assumptions!$D$54))/(1+Assumptions!$D$68)^Assumptions!$D$7)/1e6 | E38: =(-215000000.0*(1+Assumptions!$D$15)+(OpEx_CapEx!$E$9-OpEx_CapEx!$E$21+Tax!$E$12)*((1-(1+Assumptions!$D$68)^-Assumptions!$D$7)/Assumptions!$D$68)+(OpEx_CapEx!$E$9*(1+Assumptions!$D$20/2)^Assumptions!$D$7*(1+Assumptions!$D$20)/0.075*(1-Assumptions!$D$52-Assumptions!$D$53-Assumptions!$D$54))/(1+Assumptions!$D$68)^Assumptions!$D$7)/1e6 | F38: =(-215000000.0*(1+Assumptions!$D$15)+(OpEx_CapEx!$E$9-OpEx_CapEx!$E$21+Tax!$E$12)*((1-(1+Assumptions!$D$68)^-Assumptions!$D$7)/Assumptions!$D$68)+(OpEx_CapEx!$E$9*(1+Assumptions!$D$20/2)^Assumptions!$D$7*(1+Assumptions!$D$20)/0.08*(1-Assumptions!$D$52-Assumptions!$D$53-Assumptions!$D$54))/(1+Assumptions!$D$68)^Assumptions!$D$7)/1e6 | G38: =(-215000000.0*(1+Assumptions!$D$15)+(OpEx_CapEx!$E$9-OpEx_CapEx!$E$21+Tax!$E$12)*((1-(1+Assumptions!$D$68)^-Assumptions!$D$7)/Assumptions!$D$68)+(OpEx_CapEx!$E$9*(1+Assumptions!$D$20/2)^Assumptions!$D$7*(1+Assumptions!$D$20)/0.085*(1-Assumptions!$D$52-Assumptions!$D$53-Assumptions!$D$54))/(1+Assumptions!$D$68)^Assumptions!$D$7)/1e6 | H38: =(-215000000.0*(1+Assumptions!$D$15)+(OpEx_CapEx!$E$9-OpEx_CapEx!$E$21+Tax!$E$12)*((1-(1+Assumptions!$D$68)^-Assumptions!$D$7)/Assumptions!$D$68)+(OpEx_CapEx!$E$9*(1+Assumptions!$D$20/2)^Assumptions!$D$7*(1+Assumptions!$D$20)/0.09*(1-Assumptions!$D$52-Assumptions!$D$53-Assumptions!$D$54))/(1+Assumptions!$D$68)^Assumptions!$D$7)/1e6 | I38: =(-215000000.0*(1+Assumptions!$D$15)+(OpEx_CapEx!$E$9-OpEx_CapEx!$E$21+Tax!$E$12)*((1-(1+Assumptions!$D$68)^-Assumptions!$D$7)/Assumptions!$D$68)+(OpEx_CapEx!$E$9*(1+Assumptions!$D$20/2)^Assumptions!$D$7*(1+Assumptions!$D$20)/0.1*(1-Assumptions!$D$52-Assumptions!$D$53-Assumptions!$D$54))/(1+Assumptions!$D$68)^Assumptions!$D$7)/1e6
B39: 230000000 | C39: =(-230000000.0*(1+Assumptions!$D$15)+(OpEx_CapEx!$E$9-OpEx_CapEx!$E$21+Tax!$E$12)*((1-(1+Assumptions!$D$68)^-Assumptions!$D$7)/Assumptions!$D$68)+(OpEx_CapEx!$E$9*(1+Assumptions!$D$20/2)^Assumptions!$D$7*(1+Assumptions!$D$20)/0.065*(1-Assumptions!$D$52-Assumptions!$D$53-Assumptions!$D$54))/(1+Assumptions!$D$68)^Assumptions!$D$7)/1e6 | D39: =(-230000000.0*(1+Assumptions!$D$15)+(OpEx_CapEx!$E$9-OpEx_CapEx!$E$21+Tax!$E$12)*((1-(1+Assumptions!$D$68)^-Assumptions!$D$7)/Assumptions!$D$68)+(OpEx_CapEx!$E$9*(1+Assumptions!$D$20/2)^Assumptions!$D$7*(1+Assumptions!$D$20)/0.07*(1-Assumptions!$D$52-Assumptions!$D$53-Assumptions!$D$54))/(1+Assumptions!$D$68)^Assumptions!$D$7)/1e6 | E39: =(-230000000.0*(1+Assumptions!$D$15)+(OpEx_CapEx!$E$9-OpEx_CapEx!$E$21+Tax!$E$12)*((1-(1+Assumptions!$D$68)^-Assumptions!$D$7)/Assumptions!$D$68)+(OpEx_CapEx!$E$9*(1+Assumptions!$D$20/2)^Assumptions!$D$7*(1+Assumptions!$D$20)/0.075*(1-Assumptions!$D$52-Assumptions!$D$53-Assumptions!$D$54))/(1+Assumptions!$D$68)^Assumptions!$D$7)/1e6 | F39: =(-230000000.0*(1+Assumptions!$D$15)+(OpEx_CapEx!$E$9-OpEx_CapEx!$E$21+Tax!$E$12)*((1-(1+Assumptions!$D$68)^-Assumptions!$D$7)/Assumptions!$D$68)+(OpEx_CapEx!$E$9*(1+Assumptions!$D$20/2)^Assumptions!$D$7*(1+Assumptions!$D$20)/0.08*(1-Assumptions!$D$52-Assumptions!$D$53-Assumptions!$D$54))/(1+Assumptions!$D$68)^Assumptions!$D$7)/1e6 | G39: =(-230000000.0*(1+Assumptions!$D$15)+(OpEx_CapEx!$E$9-OpEx_CapEx!$E$21+Tax!$E$12)*((1-(1+Assumptions!$D$68)^-Assumptions!$D$7)/Assumptions!$D$68)+(OpEx_CapEx!$E$9*(1+Assumptions!$D$20/2)^Assumptions!$D$7*(1+Assumptions!$D$20)/0.085*(1-Assumptions!$D$52-Assumptions!$D$53-Assumptions!$D$54))/(1+Assumptions!$D$68)^Assumptions!$D$7)/1e6 | H39: =(-230000000.0*(1+Assumptions!$D$15)+(OpEx_CapEx!$E$9-OpEx_CapEx!$E$21+Tax!$E$12)*((1-(1+Assumptions!$D$68)^-Assumptions!$D$7)/Assumptions!$D$68)+(OpEx_CapEx!$E$9*(1+Assumptions!$D$20/2)^Assumptions!$D$7*(1+Assumptions!$D$20)/0.09*(1-Assumptions!$D$52-Assumptions!$D$53-Assumptions!$D$54))/(1+Assumptions!$D$68)^Assumptions!$D$7)/1e6 | I39: =(-230000000.0*(1+Assumptions!$D$15)+(OpEx_CapEx!$E$9-OpEx_CapEx!$E$21+Tax!$E$12)*((1-(1+Assumptions!$D$68)^-Assumptions!$D$7)/Assumptions!$D$68)+(OpEx_CapEx!$E$9*(1+Assumptions!$D$20/2)^Assumptions!$D$7*(1+Assumptions!$D$20)/0.1*(1-Assumptions!$D$52-Assumptions!$D$53-Assumptions!$D$54))/(1+Assumptions!$D$68)^Assumptions!$D$7)/1e6
B41: Heat-map convention: GREEN = institutionally acceptable; RED = breach of hurdle/covenant; UNSHADED = marginal.

Sheet Lender_Metrics
B2: LENDER METRICS — institutional credit view
D5: Y0 | E5: Y1 | F5: Y2 | G5: Y3 | H5: Y4 | I5: Y5 | J5: Y6 | K5: Y7 | L5: Y8 | M5: Y9 | N5: Y10
B6: CFADS (NOI − CapEx − tax) | D6: =OpEx_CapEx!D9+OpEx_CapEx!D23+Tax!D12 | E6: =OpEx_CapEx!E9+OpEx_CapEx!E23+Tax!E12 | F6: =OpEx_CapEx!F9+OpEx_CapEx!F23+Tax!F12 | G6: =OpEx_CapEx!G9+OpEx_CapEx!G23+Tax!G12 | H6: =OpEx_CapEx!H9+OpEx_CapEx!H23+Tax!H12 | I6: =OpEx_CapEx!I9+OpEx_CapEx!I23+Tax!I12 | J6: =OpEx_CapEx!J9+OpEx_CapEx!J23+Tax!J12 | K6: =OpEx_CapEx!K9+OpEx_CapEx!K23+Tax!K12 | ... N6: =OpEx_CapEx!N9+OpEx_CapEx!N23+Tax!N12
B7: Total debt service | D7: =ABS(Debt!D10)+ABS(Debt!D7)+ABS(Debt!D8) | E7: =ABS(Debt!E10)+ABS(Debt!E7)+ABS(Debt!E8) | F7: =ABS(Debt!F10)+ABS(Debt!F7)+ABS(Debt!F8) | G7: =ABS(Debt!G10)+ABS(Debt!G7)+ABS(Debt!G8) | H7: =ABS(Debt!H10)+ABS(Debt!H7)+ABS(Debt!H8) | I7: =ABS(Debt!I10)+ABS(Debt!I7)+ABS(Debt!I8) | J7: =ABS(Debt!J10)+ABS(Debt!J7)+ABS(Debt!J8) | K7: =ABS(Debt!K10)+ABS(Debt!K7)+ABS(Debt!K8) | ... N7: =ABS(Debt!N10)+ABS(Debt!N7)+ABS(Debt!N8)
B8: DSCR (CFADS / DS) | D8: =IFERROR(IF(D7=0,"-",D6/D7),"-") | E8: =IFERROR(IF(E7=0,"-",E6/E7),"-") | F8: =IFERROR(IF(F7=0,"-",F6/F7),"-") | G8: =IFERROR(IF(G7=0,"-",G6/G7),"-") | H8: =IFERROR(IF(H7=0,"-",H6/H7),"-") | I8: =IFERROR(IF(I7=0,"-",I6/I7),"-") | J8: =IFERROR(IF(J7=0,"-",J6/J7),"-") | K8: =IFERROR(IF(K7=0,"-",K6/K7),"-") | ... N8: =IFERROR(IF(N7=0,"-",N6/N7),"-")
B10: LLCR (PV CFADS over loan life / Debt outstanding) | D10: =IFERROR(IF(Debt!D9=0,"-",(E6/(1+Assumptions!$D$42)^1+F6/(1+Assumptions!$D$42)^2+G6/(1+Assumptions!$D$42)^3+H6/(1+Assumptions!$D$42)^4+I6/(1+Assumptions!$D$42)^5+J6/(1+Assumptions!$D$42)^6+K6/(1+Assumptions!$D$42)^7+L6/(1+Assumptions!$D$42)^8+M6/(1+Assumptions!$D$42)^9+N6/(1+Assumptions!$D$42)^10)/Debt!D9),"-") | E10: =IFERROR(IF(Debt!E9=0,"-",(E6/(1+Assumptions!$D$42)^1+F6/(1+Assumptions!$D$42)^2+G6/(1+Assumptions!$D$42)^3+H6/(1+Assumptions!$D$42)^4+I6/(1+Assumptions!$D$42)^5+J6/(1+Assumptions!$D$42)^6+K6/(1+Assumptions!$D$42)^7+L6/(1+Assumptions!$D$42)^8+M6/(1+Assumptions!$D$42)^9+N6/(1+Assumptions!$D$42)^10)/Debt!E9),"-") | F10: =IFERROR(IF(Debt!F9=0,"-",(F6/(1+Assumptions!$D$42)^1+G6/(1+Assumptions!$D$42)^2+H6/(1+Assumptions!$D$42)^3+I6/(1+Assumptions!$D$42)^4+J6/(1+Assumptions!$D$42)^5+K6/(1+Assumptions!$D$42)^6+L6/(1+Assumptions!$D$42)^7+M6/(1+Assumptions!$D$42)^8+N6/(1+Assumptions!$D$42)^9)/Debt!F9),"-") | G10: =IFERROR(IF(Debt!G9=0,"-",(G6/(1+Assumptions!$D$42)^1+H6/(1+Assumptions!$D$42)^2+I6/(1+Assumptions!$D$42)^3+J6/(1+Assumptions!$D$42)^4+K6/(1+Assumptions!$D$42)^5+L6/(1+Assumptions!$D$42)^6+M6/(1+Assumptions!$D$42)^7+N6/(1+Assumptions!$D$42)^8)/Debt!G9),"-") | H10: =IFERROR(IF(Debt!H9=0,"-",(H6/(1+Assumptions!$D$42)^1+I6/(1+Assumptions!$D$42)^2+J6/(1+Assumptions!$D$42)^3+K6/(1+Assumptions!$D$42)^4+L6/(1+Assumptions!$D$42)^5+M6/(1+Assumptions!$D$42)^6+N6/(1+Assumptions!$D$42)^7)/Debt!H9),"-") | I10: =IFERROR(IF(Debt!I9=0,"-",(I6/(1+Assumptions!$D$42)^1+J6/(1+Assumptions!$D$42)^2+K6/(1+Assumptions!$D$42)^3+L6/(1+Assumptions!$D$42)^4+M6/(1+Assumptions!$D$42)^5+N6/(1+Assumptions!$D$42)^6)/Debt!I9),"-") | J10: =IFERROR(IF(Debt!J9=0,"-",(J6/(1+Assumptions!$D$42)^1+K6/(1+Assumptions!$D$42)^2+L6/(1+Assumptions!$D$42)^3+M6/(1+Assumptions!$D$42)^4+N6/(1+Assumptions!$D$42)^5)/Debt!J9),"-") | K10: =IFERROR(IF(Debt!K9=0,"-",(K6/(1+Assumptions!$D$42)^1+L6/(1+Assumptions!$D$42)^2+M6/(1+Assumptions!$D$42)^3+N6/(1+Assumptions!$D$42)^4)/Debt!K9),"-") | L10: =IFERROR(IF(Debt!L9=0,"-",(L6/(1+Assumptions!$D$42)^1+M6/(1+Assumptions!$D$42)^2+N6/(1+Assumptions!$D$42)^3)/Debt!L9),"-") | M10: =IFERROR(IF(Debt!M9=0,"-",(M6/(1+Assumptions!$D$42)^1+N6/(1+Assumptions!$D$42)^2)/Debt!M9),"-") | N10: =IFERROR(IF(Debt!N9=0,"-",(N6/(1+Assumptions!$D$42)^1)/Debt!N9),"-")
B11: PLCR (PV CFADS + terminal / Debt outstanding) | D11: =IFERROR(IF(Debt!D9=0,"-",(E6/(1+Assumptions!$D$42)^1+F6/(1+Assumptions!$D$42)^2+G6/(1+Assumptions!$D$42)^3+H6/(1+Assumptions!$D$42)^4+I6/(1+Assumptions!$D$42)^5+J6/(1+Assumptions!$D$42)^6+K6/(1+Assumptions!$D$42)^7+L6/(1+Assumptions!$D$42)^8+M6/(1+Assumptions!$D$42)^9+N6/(1+Assumptions!$D$42)^10+DCF!N10/(1+Assumptions!$D$42)^10)/Debt!D9),"-") | E11: =IFERROR(IF(Debt!E9=0,"-",(E6/(1+Assumptions!$D$42)^1+F6/(1+Assumptions!$D$42)^2+G6/(1+Assumptions!$D$42)^3+H6/(1+Assumptions!$D$42)^4+I6/(1+Assumptions!$D$42)^5+J6/(1+Assumptions!$D$42)^6+K6/(1+Assumptions!$D$42)^7+L6/(1+Assumptions!$D$42)^8+M6/(1+Assumptions!$D$42)^9+N6/(1+Assumptions!$D$42)^10+DCF!N10/(1+Assumptions!$D$42)^9)/Debt!E9),"-") | F11: =IFERROR(IF(Debt!F9=0,"-",(F6/(1+Assumptions!$D$42)^1+G6/(1+Assumptions!$D$42)^2+H6/(1+Assumptions!$D$42)^3+I6/(1+Assumptions!$D$42)^4+J6/(1+Assumptions!$D$42)^5+K6/(1+Assumptions!$D$42)^6+L6/(1+Assumptions!$D$42)^7+M6/(1+Assumptions!$D$42)^8+N6/(1+Assumptions!$D$42)^9+DCF!N10/(1+Assumptions!$D$42)^8)/Debt!F9),"-") | G11: =IFERROR(IF(Debt!G9=0,"-",(G6/(1+Assumptions!$D$42)^1+H6/(1+Assumptions!$D$42)^2+I6/(1+Assumptions!$D$42)^3+J6/(1+Assumptions!$D$42)^4+K6/(1+Assumptions!$D$42)^5+L6/(1+Assumptions!$D$42)^6+M6/(1+Assumptions!$D$42)^7+N6/(1+Assumptions!$D$42)^8+DCF!N10/(1+Assumptions!$D$42)^7)/Debt!G9),"-") | H11: =IFERROR(IF(Debt!H9=0,"-",(H6/(1+Assumptions!$D$42)^1+I6/(1+Assumptions!$D$42)^2+J6/(1+Assumptions!$D$42)^3+K6/(1+Assumptions!$D$42)^4+L6/(1+Assumptions!$D$42)^5+M6/(1+Assumptions!$D$42)^6+N6/(1+Assumptions!$D$42)^7+DCF!N10/(1+Assumptions!$D$42)^6)/Debt!H9),"-") | I11: =IFERROR(IF(Debt!I9=0,"-",(I6/(1+Assumptions!$D$42)^1+J6/(1+Assumptions!$D$42)^2+K6/(1+Assumptions!$D$42)^3+L6/(1+Assumptions!$D$42)^4+M6/(1+Assumptions!$D$42)^5+N6/(1+Assumptions!$D$42)^6+DCF!N10/(1+Assumptions!$D$42)^5)/Debt!I9),"-") | J11: =IFERROR(IF(Debt!J9=0,"-",(J6/(1+Assumptions!$D$42)^1+K6/(1+Assumptions!$D$42)^2+L6/(1+Assumptions!$D$42)^3+M6/(1+Assumptions!$D$42)^4+N6/(1+Assumptions!$D$42)^5+DCF!N10/(1+Assumptions!$D$42)^4)/Debt!J9),"-") | K11: =IFERROR(IF(Debt!K9=0,"-",(K6/(1+Assumptions!$D$42)^1+L6/(1+Assumptions!$D$42)^2+M6/(1+Assumptions!$D$42)^3+N6/(1+Assumptions!$D$42)^4+DCF!N10/(1+Assumptions!$D$42)^3)/Debt!K9),"-") | L11: =IFERROR(IF(Debt!L9=0,"-",(L6/(1+Assumptions!$D$42)^1+M6/(1+Assumptions!$D$42)^2+N6/(1+Assumptions!$D$42)^3+DCF!N10/(1+Assumptions!$D$42)^2)/Debt!L9),"-") | M11: =IFERROR(IF(Debt!M9=0,"-",(M6/(1+Assumptions!$D$42)^1+N6/(1+Assumptions!$D$42)^2+DCF!N10/(1+Assumptions!$D$42)^1)/Debt!M9),"-") | N11: =IFERROR(IF(Debt!N9=0,"-",(N6/(1+Assumptions!$D$42)^1+DCF!N10/(1+Assumptions!$D$42)^0)/Debt!N9),"-")
B13: Debt yield (NOI / Debt outstanding) | D13: =IFERROR(IF(Debt!D9=0,"-",OpEx_CapEx!D9/Debt!D9),"-") | E13: =IFERROR(IF(Debt!E9=0,"-",OpEx_CapEx!E9/Debt!E9),"-") | F13: =IFERROR(IF(Debt!F9=0,"-",OpEx_CapEx!F9/Debt!F9),"-") | G13: =IFERROR(IF(Debt!G9=0,"-",OpEx_CapEx!G9/Debt!G9),"-") | H13: =IFERROR(IF(Debt!H9=0,"-",OpEx_CapEx!H9/Debt!H9),"-") | I13: =IFERROR(IF(Debt!I9=0,"-",OpEx_CapEx!I9/Debt!I9),"-") | J13: =IFERROR(IF(Debt!J9=0,"-",OpEx_CapEx!J9/Debt!J9),"-") | K13: =IFERROR(IF(Debt!K9=0,"-",OpEx_CapEx!K9/Debt!K9),"-") | ... N13: =IFERROR(IF(Debt!N9=0,"-",OpEx_CapEx!N9/Debt!N9),"-")
B14: Break-even occupancy (% of revenue needed for DS) | D14: =IFERROR(IF(Revenue!D5=0,"-",1-(Revenue!D5-D7-ABS(OpEx_CapEx!D8))/Revenue!D5),"-") | E14: =IFERROR(IF(Revenue!E5=0,"-",1-(Revenue!E5-E7-ABS(OpEx_CapEx!E8))/Revenue!E5),"-") | F14: =IFERROR(IF(Revenue!F5=0,"-",1-(Revenue!F5-F7-ABS(OpEx_CapEx!F8))/Revenue!F5),"-") | G14: =IFERROR(IF(Revenue!G5=0,"-",1-(Revenue!G5-G7-ABS(OpEx_CapEx!G8))/Revenue!G5),"-") | H14: =IFERROR(IF(Revenue!H5=0,"-",1-(Revenue!H5-H7-ABS(OpEx_CapEx!H8))/Revenue!H5),"-") | I14: =IFERROR(IF(Revenue!I5=0,"-",1-(Revenue!I5-I7-ABS(OpEx_CapEx!I8))/Revenue!I5),"-") | J14: =IFERROR(IF(Revenue!J5=0,"-",1-(Revenue!J5-J7-ABS(OpEx_CapEx!J8))/Revenue!J5),"-") | K14: =IFERROR(IF(Revenue!K5=0,"-",1-(Revenue!K5-K7-ABS(OpEx_CapEx!K8))/Revenue!K5),"-") | ... N14: =IFERROR(IF(Revenue!N5=0,"-",1-(Revenue!N5-N7-ABS(OpEx_CapEx!N8))/Revenue!N5),"-")
B15: DSCR covenant headroom (DSCR − 1.30x threshold) | D15: =IFERROR(IF(D8="-","-",D8-Assumptions!$D$73),"-") | E15: =IFERROR(IF(E8="-","-",E8-Assumptions!$D$73),"-") | F15: =IFERROR(IF(F8="-","-",F8-Assumptions!$D$73),"-") | G15: =IFERROR(IF(G8="-","-",G8-Assumptions!$D$73),"-") | H15: =IFERROR(IF(H8="-","-",H8-Assumptions!$D$73),"-") | I15: =IFERROR(IF(I8="-","-",I8-Assumptions!$D$73),"-") | J15: =IFERROR(IF(J8="-","-",J8-Assumptions!$D$73),"-") | K15: =IFERROR(IF(K8="-","-",K8-Assumptions!$D$73),"-") | ... N15: =IFERROR(IF(N8="-","-",N8-Assumptions!$D$73),"-")
B16: Debt-yield headroom (DY − 10% threshold) | D16: =IFERROR(IF(D13="-","-",D13-Assumptions!$D$75),"-") | E16: =IFERROR(IF(E13="-","-",E13-Assumptions!$D$75),"-") | F16: =IFERROR(IF(F13="-","-",F13-Assumptions!$D$75),"-") | G16: =IFERROR(IF(G13="-","-",G13-Assumptions!$D$75),"-") | H16: =IFERROR(IF(H13="-","-",H13-Assumptions!$D$75),"-") | I16: =IFERROR(IF(I13="-","-",I13-Assumptions!$D$75),"-") | J16: =IFERROR(IF(J13="-","-",J13-Assumptions!$D$75),"-") | K16: =IFERROR(IF(K13="-","-",K13-Assumptions!$D$75),"-") | ... N16: =IFERROR(IF(N13="-","-",N13-Assumptions!$D$75),"-")
B18: INSTITUTIONAL LENDER VERDICT
B19: Avg DSCR (excl bullet year) | D19: =AVERAGE(E8:M8)
B20: Min DSCR (excl bullet year) | D20: =MIN(E8:M8)
B21: Min LLCR | D21: =MIN(E10:N10)
B22: Min debt yield | D22: =MIN(E13:N13)
B23: Max break-even occupancy | D23: =MAX(E14:N14)
B24: Bankability score | D24: =IFERROR(IF(AND(D20>=Assumptions!$D$73,D21>=1.4,D22>=Assumptions!$D$75),"BANKABLE",IF(AND(D20>=1.15,D21>=1.20),"CONDITIONAL","NOT BANKABLE")),"REVIEW")

Sheet Restructured_Deal
B2: RESTRUCTURED DEAL — Institutional target structure
B3: Comparison of v4 deal as-presented vs the structure required for institutional approval. All restructured inputs sourced from Assumptions §15.
B5: Metric | C5: v4 As-Presented | D5: v5 Restructured | E5: Δ | F5: Rationale
B6: Acquisition price | C6: =Assumptions!$D$11 | D6: =Assumptions!$D$110 | E6: =IFERROR(D6-C6,0) | F6: Renegotiate basis: lower entry yield by ~10–15 bps absorbs cap risk.
B7: Acquisition costs % (RETT+broker+legal) | C7: =Assumptions!$D$15 | D7: =Assumptions!$D$15 | E7: =IFERROR(D7-C7,0) | F7: Largely fixed.
B8: Total project cost (pre-reserves) | C8: =C6*(1+C7) | D8: =D6*(1+D7) | E8: =IFERROR(D8-C8,0) | F8: Lower basis ⇒ smaller equity check.
B9: Year 1 NOI | C9: =OpEx_CapEx!$E$9 | D9: =OpEx_CapEx!$E$9*(1+Assumptions!$D$111) | E9: =IFERROR(D9-C9,0) | F9: 5% NOI uplift from repositioning, OpEx cut, lease optimisation.
B10: Entry cap (Y1 NOI / price) | C10: =C9/C6 | D10: =D9/D6 | E10: =IFERROR(D10-C10,0) | F10: Restructured entry yield substantially higher.
B11: LTV | C11: =Assumptions!$D$41 | D11: =Assumptions!$D$112 | E11: =IFERROR(D11-C11,0) | F11: Move to 55% — bank ceiling for income real estate.
B12: Debt amount | C12: =C8*C11 | D12: =D8*D11 | E12: =IFERROR(D12-C12,0)
B13: Equity amount | C13: =C8-C12 | D13: =D8-D12 | E13: =IFERROR(D13-C13,0)
B14: Cost of debt | C14: =Assumptions!$D$42 | D14: =Assumptions!$D$113 | E14: =IFERROR(D14-C14,0) | F14: Sized to current SAIBOR + 175bps; v4 underpriced.
B15: Amortizing structure | C15: =IF(Assumptions!$D$44=1,"YES","NO") | D15: =IF(Assumptions!$D$114=1,"YES","NO") | F15: Mandatory: removes exit-year bullet risk.
B16: Exit cap | C16: =Assumptions!$D$51 | D16: =Assumptions!$D$115 | E16: =IFERROR(D16-C16,0) | F16: Conservative 8% (KSA forward + risk premium).
B17: Stabilised debt yield (Y1 NOI / Debt) | C17: =C9/C12 | D17: =D9/D12 | E17: =IFERROR(D17-C17,0) | F17: Restructured ≥ 10–11%.
B18: Y1 interest expense | C18: =C12*C14 | D18: =D12*D14 | E18: =IFERROR(D18-C18,0)
B19: Y1 amortization (25-yr amort profile, 10-yr balloon) | C19: =IF(Assumptions!$D$44=1,C12/25,0) | D19: =IF(Assumptions!$D$114=1,D12/25,0) | E19: =IFERROR(D19-C19,0)
B20: Y1 DSCR (NOI / total DS) | C20: =C9/(C18+C19) | D20: =D9/(D18+D19) | E20: =IFERROR(D20-C20,0) | F20: Restructured DSCR ≥ 1.40x target.
B21: Equity IRR floor target | C21: =Assumptions!$D$71 | D21: =Assumptions!$D$116 | E21: =IFERROR(D21-C21,0) | F21: Set to 12% — KSA core-plus real estate institutional floor.
B22: Min DSCR floor target | C22: =Assumptions!$D$73 | D22: =Assumptions!$D$117 | E22: =IFERROR(D22-C22,0) | F22: Raised to 1.40x.
B25: RESTRUCTURED-DEAL VERDICT
B26: Combined effect on Y1 DSCR (v4 vs v5) | C26: =C20 | D26: =D20
B27: Hits institutional floors (Y1 DSCR ≥ floor AND IRR ≥ floor) | D27: =IF(AND(D20>=Assumptions!$D$117,D59>=Assumptions!$D$116),"PASS","FAIL")
B29: CONDITIONS REQUIRED FOR INSTITUTIONAL APPROVAL
B30: 1. Reprice acquisition to ≤ SAR 150M (vs SAR 200M) OR demonstrate 10%+ NOI uplift from Day-1 repositioning (signed broker/leasing plan).
B31: 2. Mandatory partial amortization on a 25-year profile with 10-year balloon (or refi commitment) — no straight bullet at exit; binding bank term sheet required.
B32: 3. LTV ceiling 55% (no exceptions); cost of debt ≥ SAIBOR + 175 bps with rate-cap hedge for 50% of debt for first 5 years.
B33: 4. Fund 6-month DSRA, 3-month OpEx reserve, 12-month CapEx reserve, and 1.5% contingency at closing.
B34: 5. DSCR covenant ≥ 1.30x with cash-sweep above 1.40x; LLCR ≥ 1.40x tested annually.
B35: 6. Cap-rate stress test: must remain NPV-positive at exit cap +150 bps (8.5%); equity IRR ≥ 10% at +250 bps.
B36: 7. Sponsor recourse / completion guarantee for any CapEx overrun and for first 24 months of debt service.
B37: 8. Tax/Zakat opinion from KSA Big-4: confirm 80%+ property shelter for Zakat base; otherwise raise zakat reserve.
B38: 9. Independent valuation at acquisition AND at proposed refinance year (Y5) — no related-party valuer.
B39: 10. Quarterly investor reporting with full DSCR, debt yield, liquidity runway disclosure.
B50: RESTRUCTURED DEAL — RETURN METRICS (analytic proxy)
B51: Y1 NOI (restructured) | D51: =OpEx_CapEx!$E$9*(1+Assumptions!$D$111)
B52: Avg NOI over hold (annuity proxy) | D52: =D51*((1+Assumptions!$D$20/2)^Assumptions!$D$7+1)/2
B53: Y10 NOI (forward) for exit | D53: =D51*(1+Assumptions!$D$20/2)^Assumptions!$D$7
B54: Exit value (Y10 NOI × (1+g) / restructured cap) | D54: =D53*(1+Assumptions!$D$20)/Assumptions!$D$115*(1-0.03)
B55: Restructured equity invested | D55: =D8-D12
B56: Annual equity FCF (NOI − interest − zakat − CapEx) | D56: =D52-D18-(Assumptions!$D$77*Assumptions!$D$57)-D51*Assumptions!$D$36
B57: Exit equity (exit value − refi debt remaining) | D57: =D54-D12+(D19*Assumptions!$D$7)
B58: Restructured MOIC | D58: =(Assumptions!$D$7*D56+D57)/D55
B59: Restructured Equity IRR (proxy) | D59: =IFERROR(D58^(1/Assumptions!$D$7)-1,0)
B60: vs Equity IRR target | D60: =Assumptions!$D$116
B61: PASS / FAIL vs target | D61: =IF(D59>=D60,"PASS","BELOW TARGET")
B62: Restructured Project NPV @ WACC | D62: =-D8+(D52-(Assumptions!$D$77*Assumptions!$D$57)-D51*Assumptions!$D$36)*((1-(1+Assumptions!$D$68)^-Assumptions!$D$7)/Assumptions!$D$68)+D54/(1+Assumptions!$D$68)^Assumptions!$D$7
B63: NPV PASS / FAIL | D63: =IF(D62>=0,"POSITIVE","NEGATIVE")
B66: PRICE-BREAK-EVEN SCAN (what acquisition price yields target IRR?)
B67: Price (SAR) | C67: 130000000 | D67: 140000000 | E67: 150000000 | F67: 160000000 | G67: 170000000 | H67: 180000000 | I67: 200000000
B68: Equity IRR (analytic) | C68: =IFERROR(((Assumptions!$D$7*((OpEx_CapEx!$E$9*(1+Assumptions!$D$111))*((1+Assumptions!$D$20/2)^Assumptions!$D$7+1)/2-((130000000*(1+Assumptions!$D$15))*Assumptions!$D$112)*Assumptions!$D$113-((130000000*(1+Assumptions!$D$15))*Assumptions!$D$112)/25-(Assumptions!$D$77*Assumptions!$D$57)-(OpEx_CapEx!$E$9*(1+Assumptions!$D$111))*Assumptions!$D$36)+((OpEx_CapEx!$E$9*(1+Assumptions!$D$111))*(1+Assumptions!$D$20/2)^Assumptions!$D$7*(1+Assumptions!$D$20)/Assumptions!$D$115*(1-0.03)-(((130000000*(1+Assumptions!$D$15))*Assumptions!$D$112)-((130000000*(1+Assumptions!$D$15))*Assumptions!$D$112)/25*Assumptions!$D$7)))/((130000000*(1+Assumptions!$D$15))-((130000000*(1+Assumptions!$D$15))*Assumptions!$D$112)))^(1/Assumptions!$D$7)-1,0) | D68: =IFERROR(((Assumptions!$D$7*((OpEx_CapEx!$E$9*(1+Assumptions!$D$111))*((1+Assumptions!$D$20/2)^Assumptions!$D$7+1)/2-((140000000*(1+Assumptions!$D$15))*Assumptions!$D$112)*Assumptions!$D$113-((140000000*(1+Assumptions!$D$15))*Assumptions!$D$112)/25-(Assumptions!$D$77*Assumptions!$D$57)-(OpEx_CapEx!$E$9*(1+Assumptions!$D$111))*Assumptions!$D$36)+((OpEx_CapEx!$E$9*(1+Assumptions!$D$111))*(1+Assumptions!$D$20/2)^Assumptions!$D$7*(1+Assumptions!$D$20)/Assumptions!$D$115*(1-0.03)-(((140000000*(1+Assumptions!$D$15))*Assumptions!$D$112)-((140000000*(1+Assumptions!$D$15))*Assumptions!$D$112)/25*Assumptions!$D$7)))/((140000000*(1+Assumptions!$D$15))-((140000000*(1+Assumptions!$D$15))*Assumptions!$D$112)))^(1/Assumptions!$D$7)-1,0) | E68: =IFERROR(((Assumptions!$D$7*((OpEx_CapEx!$E$9*(1+Assumptions!$D$111))*((1+Assumptions!$D$20/2)^Assumptions!$D$7+1)/2-((150000000*(1+Assumptions!$D$15))*Assumptions!$D$112)*Assumptions!$D$113-((150000000*(1+Assumptions!$D$15))*Assumptions!$D$112)/25-(Assumptions!$D$77*Assumptions!$D$57)-(OpEx_CapEx!$E$9*(1+Assumptions!$D$111))*Assumptions!$D$36)+((OpEx_CapEx!$E$9*(1+Assumptions!$D$111))*(1+Assumptions!$D$20/2)^Assumptions!$D$7*(1+Assumptions!$D$20)/Assumptions!$D$115*(1-0.03)-(((150000000*(1+Assumptions!$D$15))*Assumptions!$D$112)-((150000000*(1+Assumptions!$D$15))*Assumptions!$D$112)/25*Assumptions!$D$7)))/((150000000*(1+Assumptions!$D$15))-((150000000*(1+Assumptions!$D$15))*Assumptions!$D$112)))^(1/Assumptions!$D$7)-1,0) | F68: =IFERROR(((Assumptions!$D$7*((OpEx_CapEx!$E$9*(1+Assumptions!$D$111))*((1+Assumptions!$D$20/2)^Assumptions!$D$7+1)/2-((160000000*(1+Assumptions!$D$15))*Assumptions!$D$112)*Assumptions!$D$113-((160000000*(1+Assumptions!$D$15))*Assumptions!$D$112)/25-(Assumptions!$D$77*Assumptions!$D$57)-(OpEx_CapEx!$E$9*(1+Assumptions!$D$111))*Assumptions!$D$36)+((OpEx_CapEx!$E$9*(1+Assumptions!$D$111))*(1+Assumptions!$D$20/2)^Assumptions!$D$7*(1+Assumptions!$D$20)/Assumptions!$D$115*(1-0.03)-(((160000000*(1+Assumptions!$D$15))*Assumptions!$D$112)-((160000000*(1+Assumptions!$D$15))*Assumptions!$D$112)/25*Assumptions!$D$7)))/((160000000*(1+Assumptions!$D$15))-((160000000*(1+Assumptions!$D$15))*Assumptions!$D$112)))^(1/Assumptions!$D$7)-1,0) | G68: =IFERROR(((Assumptions!$D$7*((OpEx_CapEx!$E$9*(1+Assumptions!$D$111))*((1+Assumptions!$D$20/2)^Assumptions!$D$7+1)/2-((170000000*(1+Assumptions!$D$15))*Assumptions!$D$112)*Assumptions!$D$113-((170000000*(1+Assumptions!$D$15))*Assumptions!$D$112)/25-(Assumptions!$D$77*Assumptions!$D$57)-(OpEx_CapEx!$E$9*(1+Assumptions!$D$111))*Assumptions!$D$36)+((OpEx_CapEx!$E$9*(1+Assumptions!$D$111))*(1+Assumptions!$D$20/2)^Assumptions!$D$7*(1+Assumptions!$D$20)/Assumptions!$D$115*(1-0.03)-(((170000000*(1+Assumptions!$D$15))*Assumptions!$D$112)-((170000000*(1+Assumptions!$D$15))*Assumptions!$D$112)/25*Assumptions!$D$7)))/((170000000*(1+Assumptions!$D$15))-((170000000*(1+Assumptions!$D$15))*Assumptions!$D$112)))^(1/Assumptions!$D$7)-1,0) | H68: =IFERROR(((Assumptions!$D$7*((OpEx_CapEx!$E$9*(1+Assumptions!$D$111))*((1+Assumptions!$D$20/2)^Assumptions!$D$7+1)/2-((180000000*(1+Assumptions!$D$15))*Assumptions!$D$112)*Assumptions!$D$113-((180000000*(1+Assumptions!$D$15))*Assumptions!$D$112)/25-(Assumptions!$D$77*Assumptions!$D$57)-(OpEx_CapEx!$E$9*(1+Assumptions!$D$111))*Assumptions!$D$36)+((OpEx_CapEx!$E$9*(1+Assumptions!$D$111))*(1+Assumptions!$D$20/2)^Assumptions!$D$7*(1+Assumptions!$D$20)/Assumptions!$D$115*(1-0.03)-(((180000000*(1+Assumptions!$D$15))*Assumptions!$D$112)-((180000000*(1+Assumptions!$D$15))*Assumptions!$D$112)/25*Assumptions!$D$7)))/((180000000*(1+Assumptions!$D$15))-((180000000*(1+Assumptions!$D$15))*Assumptions!$D$112)))^(1/Assumptions!$D$7)-1,0) | I68: =IFERROR(((Assumptions!$D$7*((OpEx_CapEx!$E$9*(1+Assumptions!$D$111))*((1+Assumptions!$D$20/2)^Assumptions!$D$7+1)/2-((200000000*(1+Assumptions!$D$15))*Assumptions!$D$112)*Assumptions!$D$113-((200000000*(1+Assumptions!$D$15))*Assumptions!$D$112)/25-(Assumptions!$D$77*Assumptions!$D$57)-(OpEx_CapEx!$E$9*(1+Assumptions!$D$111))*Assumptions!$D$36)+((OpEx_CapEx!$E$9*(1+Assumptions!$D$111))*(1+Assumptions!$D$20/2)^Assumptions!$D$7*(1+Assumptions!$D$20)/Assumptions!$D$115*(1-0.03)-(((200000000*(1+Assumptions!$D$15))*Assumptions!$D$112)-((200000000*(1+Assumptions!$D$15))*Assumptions!$D$112)/25*Assumptions!$D$7)))/((200000000*(1+Assumptions!$D$15))-((200000000*(1+Assumptions!$D$15))*Assumptions!$D$112)))^(1/Assumptions!$D$7)-1,0)
B69: Y1 DSCR (incl. amort) | C69: =(OpEx_CapEx!$E$9*(1+Assumptions!$D$111))/(((130000000*(1+Assumptions!$D$15))*Assumptions!$D$112)*Assumptions!$D$113+((130000000*(1+Assumptions!$D$15))*Assumptions!$D$112)/25) | D69: =(OpEx_CapEx!$E$9*(1+Assumptions!$D$111))/(((140000000*(1+Assumptions!$D$15))*Assumptions!$D$112)*Assumptions!$D$113+((140000000*(1+Assumptions!$D$15))*Assumptions!$D$112)/25) | E69: =(OpEx_CapEx!$E$9*(1+Assumptions!$D$111))/(((150000000*(1+Assumptions!$D$15))*Assumptions!$D$112)*Assumptions!$D$113+((150000000*(1+Assumptions!$D$15))*Assumptions!$D$112)/25) | F69: =(OpEx_CapEx!$E$9*(1+Assumptions!$D$111))/(((160000000*(1+Assumptions!$D$15))*Assumptions!$D$112)*Assumptions!$D$113+((160000000*(1+Assumptions!$D$15))*Assumptions!$D$112)/25) | G69: =(OpEx_CapEx!$E$9*(1+Assumptions!$D$111))/(((170000000*(1+Assumptions!$D$15))*Assumptions!$D$112)*Assumptions!$D$113+((170000000*(1+Assumptions!$D$15))*Assumptions!$D$112)/25) | H69: =(OpEx_CapEx!$E$9*(1+Assumptions!$D$111))/(((180000000*(1+Assumptions!$D$15))*Assumptions!$D$112)*Assumptions!$D$113+((180000000*(1+Assumptions!$D$15))*Assumptions!$D$112)/25) | I69: =(OpEx_CapEx!$E$9*(1+Assumptions!$D$111))/(((200000000*(1+Assumptions!$D$15))*Assumptions!$D$112)*Assumptions!$D$113+((200000000*(1+Assumptions!$D$15))*Assumptions!$D$112)/25)
B70: Verdict | C70: =IF(AND(C68>=Assumptions!$D$116,C69>=Assumptions!$D$117),"PASS",IF(C68>=0.10,"MARGINAL","FAIL")) | D70: =IF(AND(D68>=Assumptions!$D$116,D69>=Assumptions!$D$117),"PASS",IF(D68>=0.10,"MARGINAL","FAIL")) | E70: =IF(AND(E68>=Assumptions!$D$116,E69>=Assumptions!$D$117),"PASS",IF(E68>=0.10,"MARGINAL","FAIL")) | F70: =IF(AND(F68>=Assumptions!$D$116,F69>=Assumptions!$D$117),"PASS",IF(F68>=0.10,"MARGINAL","FAIL")) | G70: =IF(AND(G68>=Assumptions!$D$116,G69>=Assumptions!$D$117),"PASS",IF(G68>=0.10,"MARGINAL","FAIL")) | H70: =IF(AND(H68>=Assumptions!$D$116,H69>=Assumptions!$D$117),"PASS",IF(H68>=0.10,"MARGINAL","FAIL")) | I70: =IF(AND(I68>=Assumptions!$D$116,I69>=Assumptions!$D$117),"PASS",IF(I68>=0.10,"MARGINAL","FAIL"))

Sheet Audit
B2: MODEL INTEGRITY CHECKS
B3: All checks must return OK before model is used for IC/financing.
B5: Check | C5: Expected | D5: Actual | E5: Status
B6: Debt + Equity = Total cost | C6: =Assumptions!$D$16 | D6: =Assumptions!$D$47+Assumptions!$D$48 | E6: =IF(ABS(D6-C6)<MAX(1,ABS(C6)*0.001),"OK","REVIEW")
B7: Y0 acquisition outflow = Total cost (negative) | C7: =-Assumptions!$D$16 | D7: =Cash_Flow!D12 | E7: =IF(ABS(D7-C7)<MAX(1,ABS(C7)*0.001),"OK","REVIEW")
B8: Y0 debt drawdown = Debt amount | C8: =Assumptions!$D$47 | D8: =Debt!D6 | E8: =IF(ABS(D8-C8)<MAX(1,ABS(C8)*0.001),"OK","REVIEW")
B9: Debt closing balance at exit = 0 | C9: =0 | D9: =Debt!N9 | E9: =IF(ABS(D9-C9)<MAX(1,ABS(C9)*0.001),"OK","REVIEW")
B10: Sum of principal+bullet across life = Debt amount | C10: =Assumptions!$D$47 | D10: =ABS(SUM(Debt!D7:N7))+ABS(SUM(Debt!D8:N8)) | E10: =IF(ABS(D10-C10)<MAX(1,ABS(C10)*0.001),"OK","REVIEW")
B11: Project FCF positive in Y_exit (driven by exit value) | C11: Positive | D11: =Cash_Flow!N15 | E11: =IF(D11>0,"OK","ERROR")
B12: Equity outflow only in Y0 | C12: Only Y0 negative | D12: =COUNTIF(Cash_Flow!E25:N25,"<0") | E12: =IF(D12=0,"OK","ERROR")
B13: WACC > Cost of debt after-tax | C13: WACC > Kd | D13: =IF(Assumptions!$D$68>Assumptions!$D$67,"OK","ERROR") | E13: =IF(D13="OK","OK","ERROR")
B14: Min Operating DSCR (excl. bullet/refi yr) ≥ threshold | C14: =Assumptions!$D$73 | D14: =IFERROR(MIN(Debt!E19:M19),0) | E14: =IF(D14>=C14,"OK","ERROR")
B15: Initial LTV ≤ Max LTV | C15: =Assumptions!$D$74 | D15: =Assumptions!$D$47/Assumptions!$D$16 | E15: =IF(D15<=C15,"OK","ERROR")
B16: Equity IRR ≥ Hurdle | C16: =Assumptions!$D$71 | D16: =Returns!D6 | E16: =IF(D16>=C16,"OK","ERROR")
B17: Project IRR ≥ WACC | C17: =Assumptions!$D$68 | D17: =Returns!D5 | E17: =IF(D17>=C17,"OK","ERROR")
B18: NPV (Project) ≥ 0 | C18: ≥ 0 | D18: =DCF!D17 | E18: =IF(D18>0,"OK","ERROR")
B19: MOIC ≥ MOIC target | C19: =Assumptions!$D$72 | D19: =Returns!D17 | E19: =IF(D19>=C19,"OK","ERROR")
B20: Exit value computed only at exit year | C20: 1 non-zero cell | D20: =COUNTIF(DCF!D9:N9,">0") | E20: =IF(D20=1,"OK","ERROR")
B21: Tax line is non-positive (cash outflow) | C21: ≤ 0 every year | D21: =COUNTIF(Cash_Flow!E24:N24,">0") | E21: =IF(D21=0,"OK","ERROR")
B22: Refinance plan active OR exit-year DSCR ≥ threshold | C22: OK or REVIEW | D22: =IF(OR(Assumptions!$D$79=1,Debt!N16>=Assumptions!$D$73),"OK","REFI REQUIRED") | E22: =IF(D22="OK","OK","REVIEW")
B23: Zakat ≤ 20% of EBITDA (sanity check) | C23: ≤ 20% | D23: =IFERROR(ABS(Tax!E9)/MAX(OpEx_CapEx!E18,1),1) | E23: =IF(D23<=0.20,"OK","REVIEW")
B24: NPV (Project) ≥ 0 under DOWNSIDE | C24: ≥ 0 | D24: =Scenario_Engine!D17 | E24: =IF(D24>=0,"OK","ERROR")
B25: DSRA funded at closing | C25: ≥ required | D25: =Reserves!D8 | E25: =IF(D25>=Reserves!D7,"OK","ERROR")

Sheet Cover
B2: BIN AMER HOLDING — INVESTMENT UNDERWRITING MODEL v4
B4: Document | C4: Institutional-grade real estate / income-asset underwriting model
B5: Prepared for | C5: Investment Committee / Bank / JV Partner Review
B6: Currency | C6: SAR (Saudi Riyal) unless stated
B7: Periodicity | C7: Annual, Y0 (closing) + Y1–Y10 (operating)
B8: Version | C8: v4.0 — Institutional Rebuild
B10: COLOR-CODING CONVENTIONS
B11: BLUE | C11: Hardcoded user input
B12: BLACK | C12: Formula / calculation
B13: GREEN | C13: Cross-sheet link
B14: YELLOW fill | C14: Key assumption requiring management sign-off
B15: YELLOW fill | C15: Warning / negative result / audit error
B17: SHEET MAP
B18: Assumptions | C18: Single source of truth for all hardcoded inputs
B19: Timeline | C19: Period flags, calendar years, operating-year switches
B20: Revenue | C20: Gross revenue, vacancy, EGI build-up
B21: OpEx_CapEx | C21: Operating expense build, maintenance + refurbishment CapEx
B22: Debt | C22: Amortization OR bullet schedule, ICR, DSCR per year
B23: Tax | C23: Zakat, corporate tax, withholding, disposal tax
B24: Cash_Flow | C24: Layered: NOI → EBITDA → EBT → Project FCF → Equity FCF
B25: DCF | C25: Unlevered DCF using exit-cap terminal value (no double-count)
B26: Returns | C26: IRR, NPV, MOIC, DSCR, LTV, debt yield, payback, CoC
B27: Scenarios | C27: Base / Downside / Severe / Upside cases
B28: Sensitivity | C28: Two-variable sensitivities on key drivers
B29: Audit | C29: Integrity, sign convention, balance, reconciliation checks
B30: Dashboard | C30: IC-ready executive summary
B32: KEY MODEL CHANGES vs v3 (read before use)
B33: 1. | C33: Removed Gordon-Growth terminal value — was double-counted with Exit Cap Value.
B34: 2. | C34: Exit Value now uses FORWARD NOI net of disposal costs (broker + legal).
B35: 3. | C35: True NOI line now excludes fund/admin/custodian fees (moved below to corporate).
B36: 4. | C36: Full annual debt schedule with amortization OR bullet toggle; DSCR computed per year.
B37: 5. | C37: Zakat, corporate tax, and withholding tax now flow through cash flow and IRR.
B38: 6. | C38: Maintenance CapEx and periodic refurbishment CapEx modelled separately.
B39: 7. | C39: Y0/Y1 timing corrected: Y0 = closing year (outflow), Y1 = first operating year.
B40: 8. | C40: Project IRR/NPV use Project FCF; Equity IRR/NPV use Equity FCF after debt + tax.
B41: 9. | C41: Audit sheet flags any structural error with OK / ERROR status.
B42: 10. | C42: Sensitivity tables for cap rate, vacancy, revenue growth, interest rate, OpEx.
